[{"id":"page-/","title":"Computational Arithmetic Geometry","content":"AG Computational Arithmetic Geometry Prof. Dr. Gebhard BÃ¶ckle Research Group at the Interdisciplinary Center for Scientific Computing (IWR), Heidelberg University .hero-header { position: relative; width: 100%; height: 500px; overflow: hidden; border-radius: 12px; box-shadow: 0 8px 32px rgba(0,0,0,0.15); margin-bottom: 2rem; } .hero-image { width: 100%; height: 100%; object-fit: cover; object-position: 50% 0%; background: transparent; } .hero-overlay { position: absolute; top: 0; left: 0; right: 0; bottom: 0; background: linear-gradient(135deg, rgba(0,0,0,0.7) 0%, rgba(0,0,0,0.4) 50%, rgba(0,0,0,0.2) 100%); display: flex; align-items: center; justify-content: center; } .hero-content { text-align: center; color: ffffff !important; padding: 2rem; } / Ensure all text in hero content is white / .hero-content { color: ffffff !important; } .hero-title { font-size: 3rem; font-weight: 700; margin-bottom: 0.5rem; text-shadow: 2px 2px 4px rgba(0,0,0,0.8); color: ffffff !important; } / Override any global heading styles for hero title / .hero-header .hero-title, .hero-overlay .hero-title, .hero-content .hero-title { color: ffffff !important; } .hero-subtitle { font-size: 1.5rem; font-weight: 400; margin-bottom: 0.75rem; text-shadow: 1px 1px 2px rgba(0,0,0,0.8); color: ffffff !important; } / Override any global styles for hero subtitle / .hero-header .hero-subtitle, .hero-overlay .hero-subtitle, .hero-content .hero-subtitle { color: ffffff !important; } .hero-description { font-size: 1.1rem; font-weight: 300; margin: 0; opacity: 0.9; text-shadow: 1px 1px 2px rgba(0,0,0,0.8); color: ffffff !important; } / Override any global styles for hero description / .hero-header .hero-description, .hero-overlay .hero-description, .hero-content .hero-description, .hero-description { color: ffffff !important; } @media (max-width: 768px) { .hero-header { height: 360px; } .hero-title { font-size: 2rem; } .hero-subtitle { font-size: 1.2rem; } .hero-description { font-size: 1rem; } } / Horizontal Card Layout Styles / .main-container { width: 100%; margin: 0; padding: 0 0.75rem; } .content-grid { display: grid; grid-template-columns: repeat(auto-fit, minmax(280px, 1fr)); gap: 1rem; margin-bottom: 2rem; } .feature-card { background: var(--bg-primary); border-radius: var(--radius-lg); border: 1px solid var(--border-color); box-shadow: var(--shadow-sm); transition: all var(--transition-base); overflow: hidden; position: relative; } .feature-card:hover { box-shadow: var(--shadow-md); transform: translateY(-4px); border-color: var(--primary); } .card-header { background: linear-gradient(135deg, var(--primary) 0%, var(--heidelberg-red) 100%); padding: 0.75rem; color: white; position: relative; } .card-icon { width: 45px; height: 45px; background: rgba(255, 255, 255, 0.2); border-radius: 50%; display: flex; align-items: center; justify-content: center; font-size: 1.25rem; margin-bottom: 0.5rem; backdrop-filter: blur(10px); } .card-header h3 { margin: 0; font-size: 1.25rem; font-weight: 600; line-height: 1.2; } .card-body { padding: 1rem; } .card-body p { color: var(--text-secondary); font-size: 0.9rem; line-height: 1.4; margin-bottom: 1rem; } .card-footer { padding: 0 1rem 1rem 1rem; display: flex; gap: 0.5rem; flex-wrap: wrap; } .card-link { display: inline-flex; align-items: center; gap: 0.25rem; padding: 0.5rem 1rem; background: transparent; color: var(--primary); border: 2px solid var(--primary); border-radius: var(--radius-md); text-decoration: none; font-weight: 500; font-size: 0.8rem; transition: all var(--transition-base); } .card-link:hover { background: var(--primary); color: var(--primary-text); transform: translateY(-2px); box-shadow: var(--shadow-sm); } / Responsive Design / @media (max-width: 768px) { .content-grid { grid-template-columns: 1fr; gap: 0.75rem; } .card-footer { flex-direction: column; } .card-link { width: 100%; justify-content: center; } } @media (max-width: 480px) { .main-container { padding: 0 0.5rem; } .card-header { padding: 0.5rem; } .card-body { padding: 0.75rem; } .card-footer { padding: 0 0.75rem 0.75rem 0.75rem; } } About Our Research Group Website of the computational arithmetic geometry research group at IWR, Heidelberg University. Conducting cutting-edge research in algebraic number theory and arithmetic geometry. Research Areas Our Team Research Focus Focus on Galois representations, modular forms, elliptic curves, deformation theory, and function field arithmetic including L-functions and Drinfeld modular forms. Explore Research Our Methods We apply theoretical methods and computer algebra experiments to solve problems in number theory and arithmetic geometry, developing computational tools and gathering examples. Publications  Computational Arithmetic Geometry","url":"/","category":"page","description":"","tags":"","date":null,"layout":"page"},{"id":"page-/assets/css/main.css","title":"main.scss","content":"// Use modern @use syntax instead of deprecated @import @use \"forward\"; // Import variables directly for backward compatibility @use \"variables\"; // Enhanced High-Contrast Academic Theme // Optimized for performance and accessibility // CSS Custom Properties for enhanced functionality :root { // Spacing utilities --space-xs: 0.25rem; --space-sm: 0.5rem; --space-md: 1rem; --space-lg: 1.5rem; --space-xl: 2rem; --space-2xl: 2.5rem; // Border radius utilities --radius-sm: 0.25rem; --radius-md: 0.375rem; --radius-lg: 0.5rem; --radius-xl: 0.75rem; --radius-2xl: 1rem; --radius-full: 9999px; // Typography scale --text-xs: 0.75rem; --text-sm: 0.875rem; --text-base: 1rem; --text-lg: 1.125rem; --text-xl: 1.25rem; --text-2xl: 1.5rem; --text-3xl: 1.875rem; --text-4xl: 2.25rem; // Z-index layers --z-dropdown: 1000; --z-sticky: 1020; --z-fixed: 1030; --z-modal: 1050; --z-tooltip: 1070; } // Enhanced body and html styling html { scroll-behavior: smooth; -webkit-font-smoothing: antialiased; -moz-osx-font-smoothing: grayscale; font-size: 16px; line-height: 1.6; } body { margin: 0; padding: 0; background-color: var(--bg-primary) !important; color: var(--text-primary) !important; font-family: 'Inter', -apple-system, BlinkMacSystemFont, 'Segoe UI', 'Roboto', 'Oxygen', 'Ubuntu', 'Cantarell', 'Fira Sans', 'Droid Sans', 'Helvetica Neue', sans-serif; line-height: 1.6; -webkit-font-smoothing: antialiased; -moz-osx-font-smoothing: grayscale; transition: background-color 0.3s ease, color 0.3s ease; overflow-x: hidden; } // Typography enhancements h1, h2, h3, h4, h5, h6 { color: var(--text-primary) !important; font-weight: 600; margin: 0.5em 0; line-height: 1.2; } h1 { font-size: var(--text-4xl); } h2 { font-size: var(--text-3xl); } h3 { font-size: var(--text-2xl); } h4 { font-size: var(--text-xl); } h5 { font-size: var(--text-lg); } h6 { font-size: var(--text-base); } p, span, li, td, th, label, strong, em { color: var(--text-primary) !important; } small, .small { font-size: var(--text-sm); color: var(--text-muted) !important; } // Enhanced link styling a { color: var(--link-color) !important; text-decoration: none; transition: all 0.2s ease; &:hover, &:focus { color: var(--link-hover) !important; text-decoration: underline; } } // Dark mode link adjustments for better visibility [data-theme=\"dark\"] a, body.dark-mode a, html.dark-mode a { color: ff6b6b !important; } [data-theme=\"dark\"] a:hover, [data-theme=\"dark\"] a:focus, body.dark-mode a:hover, body.dark-mode a:focus, html.dark-mode a:hover, html.dark-mode a:focus { color: ff5252 !important; } // Enhanced dark mode styling for all elements [data-theme=\"dark\"], body.dark-mode, html.dark-mode { // Force dark backgrounds background-color: 000000 !important; // Enhanced dark mode for all containers .container, .container-fluid, .row, .col, main, section, article, .content, .page-content { background-color: 000000 !important; color: ffffff !important; } // Additional dark mode fixes for specific pages .teaching-page, .publications-page, .links-list, .contact-form-section { background-color: 000000 !important; color: ffffff !important; } // Fix for list group items in links page .list-group-item { background-color: 111827 !important; border-color: 374151 !important; color: ffffff !important; transition: all 0.3s ease !important; box-shadow: 0 2px 8px rgba(0, 0, 0, 0.1) !important; } .list-group-item:hover { background-color: 1f2937 !important; border-color: f87171 !important; transform: translateY(-2px) !important; box-shadow: 0 4px 12px rgba(248, 113, 113, 0.2) !important; } .list-group-item h5 { color: ffffff !important; } .list-group-item small, .list-group-item p { color: d1d5db !important; } // Teaching page specific fixes .teaching-page { background-color: 000000 !important; } .teaching-header { background: linear-gradient(135deg, 1f2937 0%, 111827 100%) !important; border-bottom: 3px solid f87171 !important; box-shadow: 0 4px 20px rgba(0, 0, 0, 0.3) !important; } .teaching-header::before { background: linear-gradient(135deg, rgba(248, 113, 113, 0.1) 0%, rgba(248, 113, 113, 0.05) 100%) !important; } .filter-controls { background: var(--bg-primary) !important; border: 1px solid var(--border-color) !important; box-shadow: var(--shadow-sm) !important; border-radius: 12px !important; display: flex; } .filter-select, .filter-input { background: linear-gradient(135deg, 1f2937 0%, 374151 100%) !important; border-color: 374151 !important; color: ffffff !important; box-shadow: 0 2px 8px rgba(0, 0, 0, 0.1) !important; transition: all 0.3s ease !important; } .filter-select:focus, .filter-input:focus { border-color: f87171 !important; box-shadow: 0 0 0 3px rgba(248, 113, 113, 0.2), 0 4px 12px rgba(0, 0, 0, 0.2) !important; transform: translateY(-1px) !important; } .semester-group { background-color: 111827 !important; border-color: 374151 !important; box-shadow: 0 4px 12px rgba(0, 0, 0, 0.2) !important; } .semester-group:hover { box-shadow: 0 6px 20px rgba(0, 0, 0, 0.3) !important; border-color: f87171 !important; } .course-item { background-color: 1f2937 !important; border-color: 374151 !important; color: ffffff !important; transition: all 0.3s ease !important; } .course-item:hover { background-color: 374151 !important; border-color: f87171 !important; transform: translateY(-2px) !important; box-shadow: 0 4px 12px rgba(248, 113, 113, 0.2) !important; } .course-badge { background: linear-gradient(135deg, f87171 0%, ef4444 100%) !important; color: 000000 !important; box-shadow: 0 2px 8px rgba(248, 113, 113, 0.3) !important; border-radius: 20px !important; padding: 0.25rem 0.75rem !important; } .course-link { color: f87171 !important; } .course-link:hover { color: fca5a5 !important; } .instructors { color: 9ca3af !important; } // Research page specific fixes .research-areas { background-color: 000000 !important; } .research-area-card { background-color: 111827 !important; border-color: 374151 !important; color: ffffff !important; } .research-area-card:hover { background-color: 1f2937 !important; border-color: f87171 !important; } .research-content h3 { color: ffffff !important; border-bottom-color: f87171 !important; } .research-text p { color: d1d5db !important; } .highlight-box { background: linear-gradient(135deg, 1f2937 0%, 374151 100%) !important; border-left-color: f87171 !important; color: ffffff !important; } .highlight-box p { color: ffffff !important; } // Enhanced dark mode for cards .card { background-color: 111827 !important; border-color: 374151 !important; color: ffffff !important; } .card-header { background-color: 1f2937 !important; border-color: 374151 !important; color: ffffff !important; } .card-body { background-color: 111827 !important; color: ffffff !important; } .card-footer { background-color: 1f2937 !important; border-color: 374151 !important; color: ffffff !important; } // Enhanced dark mode for forms .form-control, .form-select, input, textarea, select { background-color: 111827 !important; border-color: 374151 !important; color: ffffff !important; } .form-control:focus, .form-select:focus, input:focus, textarea:focus, select:focus { background-color: 111827 !important; border-color: f87171 !important; color: ffffff !important; box-shadow: 0 0 0 3px rgba(248, 113, 113, 0.2) !important; } // Enhanced dark mode for tables table { background-color: 111827 !important; color: ffffff !important; } thead th { background-color: 1f2937 !important; border-color: 374151 !important; color: ffffff !important; } tbody tr { border-color: 374151 !important; } tbody tr:hover { background-color: 1f2937 !important; } tbody tr:nth-child(even) { background-color: 1f2937 !important; } tbody tr:nth-child(even):hover { background-color: 374151 !important; } tbody td { color: ffffff !important; } // Enhanced dark mode for buttons .btn-secondary { background-color: 374151 !important; border-color: 4b5563 !important; color: ffffff !important; } .btn-secondary:hover, .btn-secondary:focus { background-color: 4b5563 !important; border-color: 6b7280 !important; color: ffffff !important; } // Enhanced dark mode for dropdowns .dropdown-menu { background-color: 111827 !important; border-color: 374151 !important; color: ffffff !important; } .dropdown-item { color: ffffff !important; } .dropdown-item:hover, .dropdown-item:focus { background-color: 1f2937 !important; color: ffffff !important; } // Enhanced dark mode for search .search-input { background-color: 111827 !important; border-color: 374151 !important; color: ffffff !important; box-shadow: 0 4px 12px rgba(0, 0, 0, 0.2) !important; } .search-input:focus { background-color: 111827 !important; border-color: f87171 !important; color: ffffff !important; box-shadow: 0 0 0 4px rgba(248, 113, 113, 0.15), 0 8px 25px rgba(0, 0, 0, 0.3) !important; transform: translateY(-2px) !important; } // Publications page specific fixes .publications-page { background-color: 000000 !important; } .filter-section { background: transparent !important; border: none !important; box-shadow: none !important; } // Fix for publication cards to ensure proper dark backgrounds .publication-card { background-color: 111827 !important; border-color: 374151 !important; color: ffffff !important; } .publication-card:hover { background-color: 1f2937 !important; border-color: f87171 !important; } // Fix for publication card elements .publication-header, .publication-body, .publication-footer { background-color: transparent !important; color: ffffff !important; } .publication-title a { color: f87171 !important; } .publication-title a:hover { color: fca5a5 !important; } .publication-authors { color: d1d5db !important; } .publication-venue { color: 9ca3af !important; } .publication-abstract { color: d1d5db !important; } .publication-keywords { color: 9ca3af !important; } .search-results-info { background: linear-gradient(135deg, 1f2937 0%, 374151 100%) !important; color: d1d5db !important; border-color: 374151 !important; box-shadow: 0 2px 8px rgba(0, 0, 0, 0.2) !important; border-radius: 20px !important; } .quick-filter-btn { background: linear-gradient(135deg, f87171 0%, ef4444 100%) !important; border-color: f87171 !important; color: 000000 !important; box-shadow: 0 2px 8px rgba(248, 113, 113, 0.3) !important; transition: all 0.3s ease !important; } .quick-filter-btn:hover { transform: translateY(-2px) !important; box-shadow: 0 4px 12px rgba(248, 113, 113, 0.4) !important; } .quick-filter-btn:not(.active) { background: linear-gradient(135deg, 1f2937 0%, 374151 100%) !important; color: f87171 !important; border-color: f87171 !important; box-shadow: 0 2px 8px rgba(0, 0, 0, 0.2) !important; } .quick-filter-btn:not(.active):hover { background: linear-gradient(135deg, 374151 0%, 4b5563 100%) !important; color: fca5a5 !important; border-color: fca5a5 !important; transform: translateY(-2px) !important; box-shadow: 0 4px 12px rgba(248, 113, 113, 0.3) !important; } .search-results-container { background-color: 111827 !important; border-color: 374151 !important; color: ffffff !important; } .search-result-item { border-color: 374151 !important; color: ffffff !important; } .search-result-item:hover, .search-result-item.active { background-color: 1f2937 !important; color: ffffff !important; } .search-result-title { color: ffffff !important; } .search-result-content { color: d1d5db !important; } .search-result-url { color: 9ca3af !important; } .search-result-category { background-color: 374151 !important; color: 9ca3af !important; } } // Main content areas with proper backgrounds main, .container, .container-fluid, .hero-section, section, article, .content { background-color: var(--bg-primary) !important; color: var(--text-primary) !important; } // Enhanced card styling .card { background: var(--bg-primary) !important; color: var(--text-primary) !important; border: 1px solid var(--border-color); border-radius: var(--radius-lg); box-shadow: var(--shadow-sm); transition: all var(--transition-base); overflow: hidden; &:hover { box-shadow: var(--shadow-md); transform: translateY(-2px); } } .card-header { background: var(--bg-secondary) !important; color: var(--text-primary) !important; border-bottom: 1px solid var(--border-color); padding: var(--space-md) var(--space-lg); font-weight: 600; } .card-body { background: var(--bg-primary) !important; color: var(--text-primary) !important; padding: var(--space-lg); } .card-footer { background: var(--bg-secondary) !important; color: var(--text-primary) !important; border-top: 1px solid var(--border-color); padding: var(--space-md) var(--space-lg); } // Enhanced button styling .btn { font-weight: 500; border-radius: var(--radius-lg); transition: all var(--transition-base); border: 1px solid transparent; padding: 0.5rem 1rem; font-size: var(--text-base); line-height: 1.5; cursor: pointer; min-height: 44px; // Accessibility: minimum touch target size &:focus { outline: 2px solid var(--primary); outline-offset: 2px; } } .btn-primary { background: var(--primary) !important; color: var(--primary-text) !important; border-color: var(--primary) !important; &:hover, &:focus { background: var(--primary-hover) !important; border-color: var(--primary-hover) !important; color: var(--primary-text) !important; transform: translateY(-1px); box-shadow: var(--shadow-md); } } .btn-secondary { background: var(--bg-secondary) !important; color: var(--text-primary) !important; border-color: var(--border-color) !important; &:hover, &:focus { background: var(--bg-muted) !important; color: var(--text-primary) !important; border-color: var(--border-dark) !important; } } .btn-outline-primary { background: transparent !important; color: var(--primary) !important; border-color: var(--primary) !important; &:hover, &:focus { background: var(--primary) !important; color: var(--primary-text) !important; border-color: var(--primary) !important; } } .btn-outline-light { background: rgba(255, 255, 255, 0.1) !important; color: var(--white) !important; border-color: rgba(255, 255, 255, 0.3) !important; &:hover, &:focus { background: rgba(255, 255, 255, 0.2) !important; color: var(--white) !important; border-color: rgba(255, 255, 255, 0.5) !important; } } // Enhanced form styling .form-control, .form-select, input[type=\"text\"], input[type=\"email\"], input[type=\"password\"], input[type=\"search\"], input[type=\"url\"], input[type=\"tel\"], input[type=\"number\"], textarea { background: var(--bg-primary) !important; color: var(--text-primary) !important; border: 2px solid var(--border-color) !important; border-radius: var(--radius-md); padding: 0.5rem 0.75rem; transition: all var(--transition-fast); font-size: var(--text-base); min-height: 44px; // Accessibility: minimum touch target size &:focus { background: var(--bg-primary) !important; color: var(--text-primary) !important; border-color: var(--primary) !important; box-shadow: 0 0 0 3px rgba(194, 32, 50, 0.1) !important; outline: none; } &::placeholder { color: var(--text-muted) !important; opacity: 0.7; } } // Enhanced Search Bar Styling - Modern Design .search-container { position: relative; display: flex; align-items: center; background: rgba(255, 255, 255, 0.08); border: 1px solid rgba(255, 255, 255, 0.15); border-radius: 1rem; padding: 0.5rem; backdrop-filter: blur(10px); transition: all 0.3s cubic-bezier(0.4, 0, 0.2, 1); box-shadow: 0 4px 6px -1px rgba(0, 0, 0, 0.1), 0 2px 4px -1px rgba(0, 0, 0, 0.06); } .search-container:hover { background: rgba(255, 255, 255, 0.12); border-color: rgba(255, 255, 255, 0.25); transform: translateY(-1px); box-shadow: 0 10px 15px -3px rgba(0, 0, 0, 0.1), 0 4px 6px -2px rgba(0, 0, 0, 0.05); } .search-container:focus-within { background: rgba(255, 255, 255, 0.15); border-color: var(--primary); box-shadow: 0 0 0 3px rgba(220, 38, 38, 0.15), 0 10px 25px -5px rgba(0, 0, 0, 0.1); transform: translateY(-2px); } .search-container-center { flex: 1 1 auto; justify-content: center; max-width: none; width: 100%; margin: 0 1.5rem; } // Enhanced search input wrapper .search-input-wrapper { position: relative; flex: 1; display: flex; align-items: center; } .search-input-icon { position: absolute; left: 1rem; color: rgba(255, 255, 255, 0.6); font-size: 1.1rem; z-index: 1; pointer-events: none; transition: color 0.2s ease; } .search-input { width: 100%; background: transparent; border: none; color: var(--white); font-size: 0.95rem; font-weight: 500; padding: 0.75rem 1rem 0.75rem 3rem; border-radius: 0.75rem; transition: all 0.2s ease; min-height: 48px; letter-spacing: 0.025em; } .search-input:focus { outline: none; background: rgba(255, 255, 255, 0.05); } .search-input:focus + .search-input-icon, .search-container:focus-within .search-input-icon { color: var(--primary); } .search-input::placeholder { color: rgba(255, 255, 255, 0.6); font-weight: 400; transition: color 0.2s ease; } .search-input:focus::placeholder { color: rgba(255, 255, 255, 0.4); } // Enhanced search toggle button .search-toggle-btn { display: flex; align-items: center; justify-content: center; width: 48px; height: 48px; border-radius: 0.75rem; transition: all 0.2s cubic-bezier(0.4, 0, 0.2, 1); background: rgba(255, 255, 255, 0.1); border: 1px solid rgba(255, 255, 255, 0.2); color: var(--white); cursor: pointer; position: relative; overflow: hidden; } .search-toggle-btn::before { content: ''; position: absolute; top: 0; left: 0; right: 0; bottom: 0; background: linear-gradient(135deg, rgba(255, 255, 255, 0.1), rgba(255, 255, 255, 0.05)); opacity: 0; transition: opacity 0.2s ease; } .search-toggle-btn:hover { background: rgba(255, 255, 255, 0.15); border-color: rgba(255, 255, 255, 0.3); transform: translateY(-1px) scale(1.02); box-shadow: 0 4px 12px rgba(0, 0, 0, 0.15); } .search-toggle-btn:hover::before { opacity: 1; } .search-toggle-btn:active { transform: translateY(0) scale(0.98); } .search-toggle-btn i { font-size: 1.1rem; position: relative; z-index: 1; transition: transform 0.2s ease; } .search-toggle-btn:hover i { transform: scale(1.1); } // Enhanced search results container - Bigger and better .search-results-container { display: none; position: absolute; top: calc(100% + 0.75rem); left: 0; width: 100%; background: var(--bg-primary); border: 2px solid var(--border-dark); border-radius: 0; box-shadow: 0 25px 50px -12px rgba(0, 0, 0, 0.25), 0 0 0 1px rgba(255, 255, 255, 0.05); z-index: var(--z-dropdown); max-height: 600px; overflow-y: auto; overflow-x: hidden; backdrop-filter: blur(20px); animation: searchResultsSlideIn 0.3s cubic-bezier(0.4, 0, 0.2, 1); } .search-results-container.show { display: block; } .search-results-container::before { display: none; } // Enhanced search result items - Bigger and more prominent .search-result-item { padding: 1.25rem 1.5rem; border-bottom: 1px solid var(--border-dark); cursor: pointer; transition: all 0.2s cubic-bezier(0.4, 0, 0.2, 1); position: relative; min-height: 60px; background: var(--bg-primary); &:last-child { border-bottom: none; } &:hover, &.active { background: var(--bg-secondary); transform: translateX(6px); box-shadow: 0 8px 25px rgba(0, 0, 0, 0.15); } &:active { transform: translateX(3px) scale(0.98); } } .search-result-item::before { content: ''; position: absolute; left: 0; top: 0; bottom: 0; width: 3px; background: var(--primary); transform: scaleY(0); transition: transform 0.2s ease; } .search-result-item:hover::before, .search-result-item.active::before { transform: scaleY(1); } .search-result-header { display: flex; justify-content: space-between; align-items: flex-start; margin-bottom: 0.5rem; gap: 0.75rem; } .search-result-title { font-weight: 700; color: var(--text-primary); font-size: 1.1rem; line-height: 1.3; flex: 1; margin: 0; margin-bottom: 0.25rem; } .search-result-category { font-size: 0.7rem; color: var(--text-muted); background: var(--bg-tertiary); padding: 0.25rem 0.5rem; border-radius: 0.5rem; white-space: nowrap; font-weight: 500; text-transform: uppercase; letter-spacing: 0.05em; } .search-result-content { color: var(--text-secondary); font-size: 0.95rem; line-height: 1.5; margin-bottom: 0.75rem; display: -webkit-box; -webkit-line-clamp: 3; -webkit-box-orient: vertical; overflow: hidden; } .search-result-url { font-size: 0.75rem; color: var(--text-muted); font-family: var(--font-mono); opacity: 0.8; word-break: break-all; } // Enhanced empty state .search-empty-state { padding: 3rem 2rem; text-align: center; color: var(--text-muted); background: var(--bg-primary); } .search-empty-state i { font-size: 3rem; margin-bottom: 1rem; opacity: 0.4; color: var(--text-tertiary); } .search-empty-state p { margin-bottom: 0.5rem; font-weight: 500; font-size: 1rem; color: var(--text-secondary); } .search-empty-state small { font-size: 0.85rem; opacity: 0.7; color: var(--text-tertiary); } // Enhanced search term highlighting .search-result-item mark { background: linear-gradient(135deg, var(--primary), dc2626); color: var(--white); padding: 0.1rem 0.3rem; border-radius: 0.25rem; font-weight: 600; box-shadow: 0 1px 2px rgba(0, 0, 0, 0.1); } // Search animations @keyframes searchResultsSlideIn { from { opacity: 0; transform: translateY(-10px) scale(0.95); } to { opacity: 1; transform: translateY(0) scale(1); } } @keyframes searchInputFocus { from { transform: scale(1); } to { transform: scale(1.02); } } // Mobile search adjustments @media (max-width: 1199.98px) { .search-container-center { display: none !important; } } @media (max-width: 991.98px) { .search-container { width: 100%; margin: 0.75rem 0; gap: 0.5rem; } .search-input { font-size: 0.9rem; padding: 0.75rem 1rem; } .search-results-container { width: 100%; left: 0; right: 0; max-width: none; } .search-results-container::before { left: 50%; transform: translateX(-50%) rotate(45deg); } } @media (max-width: 576px) { .search-container { gap: 0.5rem; padding: 0.5rem; border-radius: 0.75rem; } .search-input { font-size: 0.85rem; padding: 0.75rem; min-height: 44px; } .search-toggle-btn { width: 44px; height: 44px; border-radius: 0.75rem; } .search-toggle-btn i { font-size: 1rem; } .search-result-item { padding: 1rem; } .search-result-title { font-size: 0.9rem; } .search-result-content { font-size: 0.8rem; } } // Dark mode enhancements [data-theme=\"dark\"] .search-container, body.dark-mode .search-container { background: rgba(0, 0, 0, 0.3); border-color: rgba(255, 255, 255, 0.1); } [data-theme=\"dark\"] .search-container:hover, body.dark-mode .search-container:hover { background: rgba(0, 0, 0, 0.4); border-color: rgba(255, 255, 255, 0.15); } [data-theme=\"dark\"] .search-container:focus-within, body.dark-mode .search-container:focus-within { background: rgba(0, 0, 0, 0.5); border-color: var(--primary); } [data-theme=\"dark\"] .search-toggle-btn, body.dark-mode .search-toggle-btn { background: rgba(255, 255, 255, 0.05); border-color: rgba(255, 255, 255, 0.1); } [data-theme=\"dark\"] .search-toggle-btn:hover, body.dark-mode .search-toggle-btn:hover { background: rgba(255, 255, 255, 0.1); border-color: rgba(255, 255, 255, 0.2); } / Table of Contents Styling / .toc-container { background: var(--bg-secondary); padding: 1rem 1.5rem; margin-bottom: 2rem; border-radius: var(--radius-lg); border: 1px solid var(--border-color); } toc.nav-pills .nav-link { color: var(--text-secondary); } toc.nav-pills .nav-link.active, toc.nav-pills .show > .nav-link { color: var(--primary-text); background-color: var(--primary); } toc .nav .nav-link { padding-left: 2rem; font-size: 0.9rem; } toc .nav .nav .nav-link { padding-left: 3rem; } // Dark mode form adjustments [data-theme=\"dark\"] .form-control:focus, [data-theme=\"dark\"] .form-select:focus, [data-theme=\"dark\"] input:focus, [data-theme=\"dark\"] textarea:focus, body.dark-mode .form-control:focus, body.dark-mode .form-select:focus, body.dark-mode input:focus, body.dark-mode textarea:focus { box-shadow: 0 0 0 3px rgba(220, 38, 38, 0.2) !important; } // Enhanced table styling table { background: var(--bg-primary) !important; color: var(--text-primary) !important; border-collapse: collapse; width: 100%; } thead th { background: var(--bg-secondary) !important; color: var(--text-primary) !important; border-bottom: 2px solid var(--border-dark) !important; font-weight: 600; padding: 0.75rem; text-align: left; } tbody tr { border-bottom: 1px solid var(--border-color) !important; &:hover { background: var(--bg-muted) !important; } &:nth-child(even) { background: var(--bg-secondary) !important; } &:nth-child(even):hover { background: var(--bg-muted) !important; } } tbody td { color: var(--text-primary) !important; padding: 0.75rem; vertical-align: top; } // Enhanced navbar mobile responsiveness @media (max-width: 991.98px) { .navbar-collapse { background: var(--primary) !important; border-radius: var(--radius-lg); margin-top: 0.5rem; padding: 1rem; box-shadow: var(--shadow-md); } [data-theme=\"dark\"] .navbar-collapse, body.dark-mode .navbar-collapse { background: var(--primary) !important; } .navbar-nav { gap: 0.25rem; } .navbar-nav .nav-link { padding: 0.75rem 1rem !important; border-radius: var(--radius-md); margin: 0.125rem 0; min-height: 44px; // Accessibility } } // Utility classes .text-center { text-align: center; } .text-left { text-align: left; } .text-right { text-align: right; } .text-justify { text-align: justify; } .fw-normal { font-weight: 400; } .fw-medium { font-weight: 500; } .fw-semibold { font-weight: 600; } .fw-bold { font-weight: 700; } .d-none { display: none; } .d-block { display: block; } .d-inline { display: inline; } .d-inline-block { display: inline-block; } .d-flex { display: flex; } .flex-column { flex-direction: column; } .flex-row { flex-direction: row; } .justify-content-center { justify-content: center; } .justify-content-between { justify-content: space-between; } .align-items-center { align-items: center; } .gap-1 { gap: var(--space-xs); } .gap-2 { gap: var(--space-sm); } .gap-3 { gap: var(--space-md); } .gap-4 { gap: var(--space-lg); } .p-0 { padding: 0; } .p-1 { padding: var(--space-xs); } .p-2 { padding: var(--space-sm); } .p-3 { padding: var(--space-md); } .p-4 { padding: var(--space-lg); } .m-0 { margin: 0; } .m-1 { margin: var(--space-xs); } .m-2 { margin: var(--space-sm); } .m-3 { margin: var(--space-md); } .m-4 { margin: var(--space-lg); } .mt-0 { margin-top: 0; } .mt-1 { margin-top: var(--space-xs); } .mt-2 { margin-top: var(--space-sm); } .mt-3 { margin-top: var(--space-md); } .mt-4 { margin-top: var(--space-lg); } .mb-0 { margin-bottom: 0; } .mb-1 { margin-bottom: var(--space-xs); } .mb-2 { margin-bottom: var(--space-sm); } .mb-3 { margin-bottom: var(--space-md); } .mb-4 { margin-bottom: var(--space-lg); } .me-1 { margin-right: var(--space-xs); } .me-2 { margin-right: var(--space-sm); } .me-3 { margin-right: var(--space-md); } .ms-auto { margin-left: auto; } .me-auto { margin-right: auto; } // Responsive utilities @media (max-width: 576px) { .d-sm-none { display: none; } .d-sm-block { display: block; } } @media (min-width: 768px) { .d-md-none { display: none; } .d-md-block { display: block; } .d-md-flex { display: flex; } } @media (min-width: 992px) { .d-lg-none { display: none; } .d-lg-block { display: block; } .d-lg-flex { display: flex; } } // Mobile font size adjustments @media (max-width: 768px) { h1 { font-size: var(--text-3xl); } h2 { font-size: var(--text-2xl); } h3 { font-size: var(--text-xl); } h4 { font-size: var(--text-lg); } .btn { padding: 0.75rem 1rem; font-size: var(--text-sm); } .card-body, .card-header, .card-footer { padding: var(--space-md); } } // Accessibility enhancements @media (prefers-reduced-motion: reduce) { { animation-duration: 0.01ms !important; animation-iteration-count: 1 !important; transition-duration: 0.01ms !important; } } // High contrast mode support @media (prefers-contrast: high) { .btn, .form-control, .search-input { border-width: 2px; } .card { border-width: 2px; } } // Print styles @media print { { background: white !important; color: black !important; box-shadow: none !important; } .navbar, .floating-controls, .theme-switcher, .skip-link { display: none !important; } a[href]:after { content: \" (\" attr(href) \")\"; font-size: 0.8em; color: 666; } } / Search Results Box Overrides (ensure square corners and visible separators) / .heidelberg-navbar .search-results-container { border-radius: 0 !important; border: 2px solid rgba(0, 0, 0, 0.5) !important; overflow-y: auto !important; overflow-x: hidden !important; } .heidelberg-navbar .search-results-container::before { display: none !important; } .heidelberg-navbar .search-result-item { border-bottom: 1px solid rgba(0, 0, 0, 0.2) !important; } [data-theme=\"dark\"] .heidelberg-navbar .search-results-container, body.dark-mode .heidelberg-navbar .search-results-container { border-color: rgba(255, 255, 255, 0.2) !important; } [data-theme=\"dark\"] .heidelberg-navbar .search-result-item, body.dark-mode .heidelberg-navbar .search-result-item { border-bottom-color: rgba(255, 255, 255, 0.12) !important; } // Additional search enhancements .search-shortcut-triggered { animation: searchShortcutPulse 0.3s ease; } @keyframes searchShortcutPulse { 0% { transform: scale(1); } 50% { transform: scale(1.05); } 100% { transform: scale(1); } } // Enhanced search container states .search-container { &.search-focused { background: rgba(255, 255, 255, 0.18); border-color: var(--primary); box-shadow: 0 0 0 4px rgba(220, 38, 38, 0.2), 0 15px 35px -5px rgba(0, 0, 0, 0.15); } &.search-active { background: rgba(255, 255, 255, 0.2); border-color: rgba(255, 255, 255, 0.4); } } // Improved search input states .search-input { &:focus { background: rgba(255, 255, 255, 0.08); box-shadow: inset 0 2px 4px rgba(0, 0, 0, 0.1); } &:hover:not(:focus) { background: rgba(255, 255, 255, 0.03); } } // Enhanced search toggle button states .search-toggle-btn { &:focus { outline: none; box-shadow: 0 0 0 3px rgba(255, 255, 255, 0.3); } &:active { transform: translateY(1px) scale(0.95); } &.search-active { background: rgba(255, 255, 255, 0.2); border-color: rgba(255, 255, 255, 0.4); i { transform: scale(1.1); color: var(--primary); } } } // Enhanced search results with better animations .search-results-container { &.show { animation: searchResultsSlideIn 0.3s cubic-bezier(0.4, 0, 0.2, 1); } // Improved scrollbar styling &::-webkit-scrollbar { width: 6px; } &::-webkit-scrollbar-track { background: var(--bg-secondary); border-radius: 3px; } &::-webkit-scrollbar-thumb { background: var(--border-color); border-radius: 3px; &:hover { background: var(--text-muted); } } } // Enhanced search result items with better interactions .search-result-item { &:hover { .search-result-title { color: var(--primary); } } &.active { background: var(--bg-secondary); border-left: 3px solid var(--primary); .search-result-title { color: var(--primary); } } // Improved loading state &.loading { opacity: 0.6; pointer-events: none; } } // Enhanced search result content .search-result-content { position: relative; &::after { content: ''; position: absolute; bottom: 0; left: 0; right: 0; height: 1px; background: linear-gradient(90deg, transparent, var(--border-color), transparent); opacity: 0; transition: opacity 0.2s ease; } } .search-result-item:hover .search-result-content::after { opacity: 1; } // Enhanced search highlighting .search-result-item mark { position: relative; &::before { content: ''; position: absolute; top: 0; left: 0; right: 0; bottom: 0; background: currentColor; opacity: 0.1; border-radius: 0.25rem; z-index: -1; } } // Enhanced empty state .search-empty-state { position: relative; &::before { content: ''; position: absolute; top: 50%; left: 50%; transform: translate(-50%, -50%); width: 4rem; height: 4rem; background: radial-gradient(circle, var(--border-color) 1px, transparent 1px); background-size: 1rem 1rem; opacity: 0.1; z-index: -1; } i { position: relative; z-index: 1; } } // Enhanced loading states .search-loading-state { position: relative; .search-spinner { position: relative; &::after { content: ''; position: absolute; top: -2px; left: -2px; right: -2px; bottom: -2px; border: 2px solid transparent; border-top: 2px solid var(--primary); border-radius: 50%; animation: spin 1.5s linear infinite reverse; opacity: 0.3; } } } // Enhanced typing indicator .search-typing-indicator { .typing-dots { span { background: var(--primary); box-shadow: 0 0 4px rgba(220, 38, 38, 0.3); } } } // Responsive improvements @media (max-width: 768px) { .search-container { margin: 0.5rem 0; &:hover { transform: none; } &:focus-within { transform: none; } } .search-results-container { max-height: 60vh; } .search-result-item { padding: 0.875rem 1rem; &:hover { transform: translateX(2px); } } } // Accessibility improvements @media (prefers-reduced-motion: reduce) { .search-container, .search-toggle-btn, .search-result-item, .search-results-container { transition: none; animation: none; } .search-spinner, .typing-dots span { animation: none; } } // High contrast mode improvements @media (prefers-contrast: high) { .search-container { border-width: 2px; background: var(--bg-primary); } .search-toggle-btn { border-width: 2px; } .search-result-item { border-bottom-width: 2px; } .search-result-item mark { background: var(--primary); color: var(--white); border: 1px solid var(--primary); } } // Enhanced header control buttons .header-control-btn { display: flex; align-items: center; justify-content: center; width: 44px; height: 44px; border-radius: 0.75rem; transition: all 0.2s cubic-bezier(0.4, 0, 0.2, 1); background: rgba(255, 255, 255, 0.1); border: 1px solid rgba(255, 255, 255, 0.2); color: var(--white); cursor: pointer; position: relative; overflow: hidden; font-size: 0.9rem; font-weight: 500; } .header-control-btn::before { content: ''; position: absolute; top: 0; left: 0; right: 0; bottom: 0; background: linear-gradient(135deg, rgba(255, 255, 255, 0.1), rgba(255, 255, 255, 0.05)); opacity: 0; transition: opacity 0.2s ease; } .header-control-btn:hover { background: rgba(255, 255, 255, 0.15); border-color: rgba(255, 255, 255, 0.3); transform: translateY(-1px) scale(1.02); box-shadow: 0 4px 12px rgba(0, 0, 0, 0.15); } .header-control-btn:hover::before { opacity: 1; } .header-control-btn:active { transform: translateY(0) scale(0.98); } .header-control-btn:focus { outline: none; box-shadow: 0 0 0 3px rgba(255, 255, 255, 0.3); } .header-control-btn i { font-size: 1rem; position: relative; z-index: 1; transition: transform 0.2s ease; } .header-control-btn:hover i { transform: scale(1.1); } // Theme toggle specific styles .header-control-btn theme-toggle { .theme-icon { transition: transform 0.3s ease; } &:hover .theme-icon { transform: rotate(15deg) scale(1.1); } } / Ensure red circular icons render white glyphs in both themes / .section-icon, .publication-type, .course-badge { background: var(--primary) !important; color: var(--primary-text) !important; } // Mobile responsive adjustments for header controls @media (max-width: 768px) { .header-control-btn { width: 40px; height: 40px; font-size: 0.85rem; } .header-control-btn .flag-icon { width: 1.1rem; height: 1.1rem; } .header-control-btn .language-code { font-size: 0.75rem; } } @media (max-width: 576px) { .header-control-btn { width: 38px; height: 38px; } .header-control-btn i { font-size: 0.9rem; } } // Search System Styles // Modern, accessible, and responsive search interface // Search Container Styles .search-container { position: relative; width: 100%; max-width: 600px; margin: 0 auto; transition: all 0.3s cubic-bezier(0.4, 0, 0.2, 1); } .search-container-center { display: flex; justify-content: center; align-items: center; flex: 1; margin: 0 2rem; } // Search Input Styles .search-input-wrapper { position: relative; width: 100%; transition: all 0.3s ease; } .search-input-icon { position: absolute; left: 1rem; top: 50%; transform: translateY(-50%); color: rgba(255, 255, 255, 0.7); font-size: 1.1rem; pointer-events: none; transition: all 0.2s ease; z-index: 2; } .search-input { width: 100%; background: rgba(255, 255, 255, 0.1); border: 2px solid rgba(255, 255, 255, 0.2); border-radius: 1rem; color: var(--white); font-size: 0.95rem; font-weight: 500; padding: 0.875rem 1rem 0.875rem 3rem; transition: all 0.3s cubic-bezier(0.4, 0, 0.2, 1); min-height: 52px; letter-spacing: 0.025em; backdrop-filter: blur(10px); } .search-input::placeholder { color: rgba(255, 255, 255, 0.6); font-weight: 400; transition: color 0.2s ease; } .search-input:focus { outline: none; background: rgba(255, 255, 255, 0.15); border-color: rgba(255, 255, 255, 0.4); box-shadow: 0 0 0 4px rgba(255, 255, 255, 0.1); transform: translateY(-1px); } .search-input:focus::placeholder { color: rgba(255, 255, 255, 0.4); } .search-input:focus + .search-input-icon { color: var(--white); transform: translateY(-50%) scale(1.1); } .search-input.search-loading { background: rgba(255, 255, 255, 0.2); } .search-input.search-loading + .search-input-icon { animation: searchPulse 1.5s ease-in-out infinite; } // Search Results Container .search-results-container { position: absolute; top: calc(100% + 0.5rem); left: 0; right: 0; background: var(--white); border-radius: 1rem; box-shadow: 0 20px 25px -5px rgba(0, 0, 0, 0.1), 0 10px 10px -5px rgba(0, 0, 0, 0.04); border: 1px solid rgba(0, 0, 0, 0.1); max-height: 500px; overflow-y: auto; z-index: 1000; display: none; } // Search Result Items .search-result-item { display: flex; align-items: flex-start; padding: 1rem; border-bottom: 1px solid rgba(0, 0, 0, 0.05); cursor: pointer; transition: all 0.2s ease; } .search-result-item:last-child { border-bottom: none; } .search-result-item:hover { background: rgba(0, 0, 0, 0.02); transform: translateX(4px); } .search-result-item.search-result-selected { background: rgba(59, 130, 246, 0.1); border-left: 3px solid 3B82F6; } .search-result-item:active { transform: scale(0.98); } / Hide category icon bubble in results for a cleaner UI / .search-result-icon { display: none; } .search-result-content { flex: 1; min-width: 0; } .search-result-header { display: flex; align-items: flex-start; justify-content: space-between; margin-bottom: 0.5rem; gap: 0.5rem; } .search-result-title { font-size: 0.95rem; font-weight: 600; color: var(--text-primary); margin: 0; line-height: 1.3; flex: 1; min-width: 0; } .search-result-category { font-size: 0.75rem; font-weight: 500; padding: 0.25rem 0.5rem; border-radius: 0.5rem; background: rgba(0, 0, 0, 0.05); white-space: nowrap; flex-shrink: 0; } .search-result-description { font-size: 0.85rem; color: var(--text-secondary); line-height: 1.4; margin-bottom: 0.5rem; display: -webkit-box; -webkit-line-clamp: 2; -webkit-box-orient: vertical; overflow: hidden; } .search-result-meta { display: flex; align-items: center; gap: 1rem; font-size: 0.75rem; color: var(--text-muted); } .search-result-url { font-family: 'Monaco', 'Menlo', 'Ubuntu Mono', monospace; background: rgba(0, 0, 0, 0.05); padding: 0.125rem 0.375rem; border-radius: 0.25rem; overflow: hidden; text-overflow: ellipsis; white-space: nowrap; max-width: 200px; } .search-result-date { color: var(--text-muted); } // Search Highlight .search-highlight { background: rgba(255, 193, 7, 0.3); color: inherit; padding: 0.125rem 0.25rem; border-radius: 0.25rem; font-weight: 600; } // Empty State .search-empty-state { padding: 2rem; text-align: center; color: var(--text-muted); } .search-empty-icon { font-size: 2rem; margin-bottom: 1rem; opacity: 0.5; } .search-empty-content h4 { margin: 0 0 0.5rem 0; font-size: 1rem; font-weight: 600; } .search-empty-content p { margin: 0 0 0.5rem 0; font-size: 0.9rem; } .search-empty-content small { font-size: 0.8rem; opacity: 0.7; } // Error State .search-error-state { padding: 1.5rem; text-align: center; color: EF4444; } .search-error-state i { font-size: 1.5rem; margin-bottom: 0.5rem; display: block; } .search-error-state p { margin: 0; font-size: 0.9rem; } // Search Overlay (Mobile) .search-overlay { position: fixed; top: 0; left: 0; right: 0; bottom: 0; background: rgba(0, 0, 0, 0.8); backdrop-filter: blur(8px); z-index: 9999; opacity: 0; visibility: hidden; transition: all 0.3s cubic-bezier(0.4, 0, 0.2, 1); } .search-overlay.search-overlay-active { opacity: 1; visibility: visible; } .search-overlay-content { position: absolute; top: 0; left: 0; right: 0; bottom: 0; background: var(--white); display: flex; flex-direction: column; transform: translateY(-100%); transition: transform 0.3s cubic-bezier(0.4, 0, 0.2, 1); } .search-overlay.search-overlay-active .search-overlay-content { transform: translateY(0); } .search-overlay-header { display: flex; align-items: center; justify-content: space-between; padding: 1rem 1.5rem; border-bottom: 1px solid rgba(0, 0, 0, 0.1); background: var(--white); } .search-overlay-header h3 { margin: 0; font-size: 1.25rem; font-weight: 600; color: var(--text-primary); } .search-overlay-close { background: none; border: none; font-size: 1.5rem; color: var(--text-muted); cursor: pointer; padding: 0.5rem; border-radius: 0.5rem; transition: all 0.2s ease; } .search-overlay-close:hover { background: rgba(0, 0, 0, 0.05); color: var(--text-primary); } .search-overlay-input-container { position: relative; padding: 1rem 1.5rem; background: var(--white); border-bottom: 1px solid rgba(0, 0, 0, 0.1); } .search-overlay-input-container i { position: absolute; left: 2rem; top: 50%; transform: translateY(-50%); color: var(--text-muted); font-size: 1.1rem; pointer-events: none; } .search-overlay-input { width: 100%; background: rgba(0, 0, 0, 0.05); border: 2px solid transparent; border-radius: 1rem; padding: 0.875rem 1rem 0.875rem 3rem; font-size: 1rem; transition: all 0.2s ease; } .search-overlay-input:focus { outline: none; background: var(--white); border-color: 3B82F6; box-shadow: 0 0 0 3px rgba(59, 130, 246, 0.1); } .search-overlay-results { flex: 1; overflow-y: auto; padding: 0; } .search-overlay-results .search-result-item { margin: 0; border-radius: 0; } // Focus States .search-focused .search-input { transform: translateY(-2px); box-shadow: 0 8px 25px -5px rgba(0, 0, 0, 0.1), 0 4px 10px -5px rgba(0, 0, 0, 0.04); } // Mobile Responsive @media (max-width: 991.98px) { .search-container-center { display: none; } .search-container { max-width: none; } .search-results-container { position: fixed; top: auto; bottom: 0; left: 0; right: 0; max-height: 60vh; border-radius: 1rem 1rem 0 0; border: none; box-shadow: 0 -10px 25px -5px rgba(0, 0, 0, 0.1); } .search-container.search-active .search-results-container { display: block; } } // Dark Mode Support [data-theme=\"dark\"] .search-results-container, body.dark-mode .search-results-container { background: var(--dark-bg); border-color: rgba(255, 255, 255, 0.1); box-shadow: 0 20px 25px -5px rgba(0, 0, 0, 0.3), 0 10px 10px -5px rgba(0, 0, 0, 0.2); } [data-theme=\"dark\"] .search-results-container .search-result-item, body.dark-mode .search-results-container .search-result-item { border-bottom-color: rgba(255, 255, 255, 0.1); } [data-theme=\"dark\"] .search-results-container .search-result-item:hover, body.dark-mode .search-results-container .search-result-item:hover { background: rgba(255, 255, 255, 0.05); } [data-theme=\"dark\"] .search-results-container .search-result-item.search-result-selected, body.dark-mode .search-results-container .search-result-item.search-result-selected { background: rgba(59, 130, 246, 0.2); } [data-theme=\"dark\"] .search-results-container .search-result-title, body.dark-mode .search-results-container .search-result-title { color: var(--white); } [data-theme=\"dark\"] .search-results-container .search-result-description, body.dark-mode .search-results-container .search-result-description { color: rgba(255, 255, 255, 0.7); } [data-theme=\"dark\"] .search-results-container .search-result-url, body.dark-mode .search-results-container .search-result-url { background: rgba(255, 255, 255, 0.1); } [data-theme=\"dark\"] .search-results-container .search-result-category, body.dark-mode .search-results-container .search-result-category { background: rgba(255, 255, 255, 0.1); } [data-theme=\"dark\"] .search-overlay-content, body.dark-mode .search-overlay-content { background: var(--dark-bg); } [data-theme=\"dark\"] .search-overlay-content .search-overlay-header, body.dark-mode .search-overlay-content .search-overlay-header { background: var(--dark-bg); border-bottom-color: rgba(255, 255, 255, 0.1); } [data-theme=\"dark\"] .search-overlay-content .search-overlay-header h3, body.dark-mode .search-overlay-content .search-overlay-header h3 { color: var(--white); } [data-theme=\"dark\"] .search-overlay-content .search-overlay-input-container, body.dark-mode .search-overlay-content .search-overlay-input-container { background: var(--dark-bg); border-bottom-color: rgba(255, 255, 255, 0.1); } [data-theme=\"dark\"] .search-overlay-content .search-overlay-input, body.dark-mode .search-overlay-content .search-overlay-input { background: rgba(255, 255, 255, 0.1); color: var(--white); } [data-theme=\"dark\"] .search-overlay-content .search-overlay-input:focus, body.dark-mode .search-overlay-content .search-overlay-input:focus { background: var(--dark-bg); } // Fix z-index and overlapping issues for dark mode [data-theme=\"dark\"] .search-wrapper, body.dark-mode .search-wrapper { z-index: 10 !important; } [data-theme=\"dark\"] .search-results-container, body.dark-mode .search-results-container { z-index: 20 !important; } [data-theme=\"dark\"] .dropdown-menu, body.dark-mode .dropdown-menu { z-index: 30 !important; } [data-theme=\"dark\"] .modal, body.dark-mode .modal { z-index: 50 !important; } / Floating theme toggle styles removed / // Animations @keyframes searchResultSlideIn { from { opacity: 0; transform: translateX(-20px); } to { opacity: 1; transform: translateX(0); } } @keyframes searchPulse { 0%, 100% { opacity: 0.7; transform: translateY(-50%) scale(1); } 50% { opacity: 1; transform: translateY(-50%) scale(1.1); } } // Loading Animation .search-loading-indicator { display: flex; align-items: center; justify-content: center; padding: 2rem; color: var(--text-muted); } .search-loading-indicator .spinner { width: 1.5rem; height: 1.5rem; border: 2px solid rgba(0, 0, 0, 0.1); border-top: 2px solid 3B82F6; border-radius: 50%; animation: spin 1s linear infinite; margin-right: 0.75rem; } @keyframes spin { 0% { transform: rotate(0deg); } 100% { transform: rotate(360deg); } } // Accessibility .search-input:focus-visible, .search-overlay-input:focus-visible { outline: 2px solid 3B82F6; outline-offset: 2px; } .search-result-item:focus-visible { outline: 2px solid 3B82F6; outline-offset: -2px; } // High contrast mode @media (prefers-contrast: high) { .search-input { border-width: 3px; } .search-result-item { border-bottom-width: 2px; } .search-highlight { background: FFD700; color: 000; } } // Reduced motion @media (prefers-reduced-motion: reduce) { .search-container, .search-input, .search-results-container, .search-result-item, .search-overlay, .search-overlay-content { transition: none; } .search-result-item { animation: none; } }","url":"/assets/css/main.css","category":"page","description":"","tags":"","date":null,"layout":null},{"id":"member-aesrdgtfh","title":"aesrdgtfh","content":"aesrdgtfh Alumni active efsdgbbcbvbcvbcvbcvbcvbccvbcvbvb Aesrdgtfh aesrdgtfh .md","url":"/members/aesrdgtfh/","category":"member","description":"","tags":"","position":"","email":"efsdgbbcbvbcvbcvbcvbcvbccvbcvbvb","research_interests":"","status":"active","role":"Alumni"},{"id":"member-Alain Muller","title":"Alain Muller","content":"title: {{ page.name }} Alain Muller was a member of the AG Computational Arithmetic Geometry research group at the Heidelberg University.  Alain Muller Alain Muller arithgeo@iwr.uni-heidelberg.de Postdoctoral Researcher alumni /assets/img/alain-muller.jpg Former Member alain-muller .md","url":"/members/?section=alumni","category":"member","description":"","tags":"","position":"","email":"arithgeo@iwr.uni-heidelberg.de","research_interests":"","status":"alumni","role":"Postdoctoral Researcher"},{"id":"member-Alireza Shavali","title":"Alireza Shavali","content":"title: {{ page.name }} Alireza Shavali is a member of the AG Computational Arithmetic Geometry research group at the Heidelberg University.  Alireza Shavali Alireza Shavali arithgeo@iwr.uni-heidelberg.de PhD Student active /assets/img/alireza-shavali.jpg alireza-shavali .md","url":"/members/alireza-shavali/","category":"member","description":"","tags":"","position":"","email":"arithgeo@iwr.uni-heidelberg.de","research_interests":"","status":"active","role":"PhD Student"},{"id":"member-Andrea Conti","title":"Andrea Conti","content":"title: {{ page.name }} Andrea Conti was a member of the AG Computational Arithmetic Geometry research group at the Heidelberg University.  Andrea Conti Andrea Conti arithgeo@iwr.uni-heidelberg.de Postdoctoral Researcher alumni /assets/img/andrea-conti.jpg Former Member andrea-conti .md","url":"/members/?section=alumni","category":"member","description":"","tags":"","position":"","email":"arithgeo@iwr.uni-heidelberg.de","research_interests":"","status":"alumni","role":"Postdoctoral Researcher"},{"id":"member-Andreas Maurischat","title":"Andreas Maurischat","content":"title: {{ page.name }} Andreas Maurischat was a member of the AG Computational Arithmetic Geometry research group at the Heidelberg University.  Andreas Maurischat Andreas Maurischat arithgeo@iwr.uni-heidelberg.de Postdoctoral Researcher alumni /assets/img/andreas-maurischat.jpg Former Member andreas-maurischat .md","url":"/members/?section=alumni","category":"member","description":"","tags":"","position":"","email":"arithgeo@iwr.uni-heidelberg.de","research_interests":"","status":"alumni","role":"Postdoctoral Researcher"},{"id":"member-Ann-Kristin Juschka","title":"Ann-Kristin Juschka","content":"title: {{ page.name }} Ann-Kristin Juschka was a member of the AG Computational Arithmetic Geometry research group at the Heidelberg University.  Ann-Kristin Juschka Ann-Kristin Juschka arithgeo@iwr.uni-heidelberg.de Postdoctoral Researcher alumni /assets/img/ann-kristin-juschka.jpg Former Member ann-kristin-juschka .md","url":"/members/?section=alumni","category":"member","description":"","tags":"","position":"","email":"arithgeo@iwr.uni-heidelberg.de","research_interests":"","status":"alumni","role":"Postdoctoral Researcher"},{"id":"member-Archiebold Karumbidza","title":"Archiebold Karumbidza","content":"title: {{ page.name }} Archiebold Karumbidza was a member of the AG Computational Arithmetic Geometry research group at the Heidelberg University.  Archiebold Karumbidza Archiebold Karumbidza arithgeo@iwr.uni-heidelberg.de Postdoctoral Researcher alumni /assets/img/archiebold-karumbidza.jpg Former Member archiebold-karumbidza .md","url":"/members/?section=alumni","category":"member","description":"","tags":"","position":"","email":"arithgeo@iwr.uni-heidelberg.de","research_interests":"","status":"alumni","role":"Postdoctoral Researcher"},{"id":"member-Astrid Cederbaum","title":"Astrid Cederbaum","content":"title: {{ page.name }} Astrid Cederbaum is a member of the AG Computational Arithmetic Geometry research group at the Heidelberg University.  Astrid Cederbaum Astrid Cederbaum arithgeo@iwr.uni-heidelberg.de Secretary active /assets/img/astrid-cederbaum.jpg astrid-cederbaum .md","url":"/members/astrid-cederbaum/","category":"member","description":"","tags":"","position":"","email":"arithgeo@iwr.uni-heidelberg.de","research_interests":"","status":"active","role":"Secretary"},{"id":"member-Barinder Banwait","title":"Barinder Banwait","content":"title: {{ page.name }} Barinder Banwait was a member of the AG Computational Arithmetic Geometry research group at Heidelberg University.  Barinder Banwait Barinder Banwait arithgeo@iwr.uni-heidelberg.de Postdoctoral Researcher alumni /assets/img/barinder-banwait.jpg Former Member barinder-banwait .md","url":"/members/?section=alumni","category":"member","description":"","tags":"","position":"","email":"arithgeo@iwr.uni-heidelberg.de","research_interests":"","status":"alumni","role":"Postdoctoral Researcher"},{"id":"member-David-A. Guiraud","title":"David-A. Guiraud","content":"title: {{ page.name }} David-A. Guiraud was a member of the AG Computational Arithmetic Geometry research group at Heidelberg University.  David-A. Guiraud David-A. Guiraud arithgeo@iwr.uni-heidelberg.de Postdoctoral Researcher alumni /assets/img/david-a-guiraud.jpg Former Member david-a-guiraud .md","url":"/members/?section=alumni","category":"member","description":"","tags":"","position":"","email":"arithgeo@iwr.uni-heidelberg.de","research_interests":"","status":"alumni","role":"Postdoctoral Researcher"},{"id":"member-David Guiraud","title":"David Guiraud","content":"title: {{ page.name }}  David Guiraud david.guiraud@math.uni-heidelberg.de David Guiraud Alumni alumni /assets/img/david-guiraud.jpg david-guiraud .md","url":"/members/?section=alumni","category":"member","description":"","tags":"","position":"","email":"david.guiraud@math.uni-heidelberg.de","research_interests":"","status":"alumni","role":"Alumni"},{"id":"member-Dr. Rudolph Perkins","title":"Dr. Rudolph Perkins","content":"title: {{ page.name }} Dr. Rudolph Perkins is a postdoctoral researcher in the AG Computational Arithmetic Geometry group at Heidelberg University. His research focuses on Drinfeld modular forms, p-adic automorphic forms, and L-functions. Research Areas - Drinfeld Modular Forms : Classical and p-adic aspects of Drinfeld modular forms - p-adic Automorphic Forms : L-invariants and p-adic uniformization - L-functions : Special values and computational aspects - Representation Theory : Connections to automorphic forms Current Research - Drinfeld modular forms and their applications - p-adic automorphic forms and L-invariants - Computational methods for L-functions - Representation theory in arithmetic geometry Publications Dr. Perkins has published several papers on Drinfeld modular forms and p-adic automorphic forms, including work on Hecke-equivariant decompositions and L-invariants. Education - PhD in Mathematics (Heidelberg University) - Research focus: Drinfeld modular forms and p-adic automorphic forms Contact - Email: perkins@math.uni-heidelberg.de - Website: Personal Website - Office: Interdisciplinary Center for Scientific Computing (IWR), Heidelberg University  Dr. Rudolph Perkins perkins@math.uni-heidelberg.de Dr. Rudolph Perkins /assets/img/dr-rudolph-perkins.jpg Research focuses on Drinfeld modular forms, p-adic automorphic forms, and L-functions. Postdoctoral Researcher active https://rudolphperkins.wordpress.com/ dr-perkins .md","url":"/members/dr-perkins/","category":"member","description":"","tags":"","position":"","email":"perkins@math.uni-heidelberg.de","research_interests":"Research focuses on Drinfeld modular forms, p-adic automorphic forms, and L-functions.","status":"active","role":"Postdoctoral Researcher"},{"id":"member-Gebhard BÃ¶ckle","title":"Gebhard BÃ¶ckle","content":"Prof. Dr. Gebhard BÃ¶ckle is the head of the research group \"Computational Arithmetic Geometry\" at the Interdisciplinary Center for Scientific Computing (IWR) in Heidelberg. His research focuses on arithmetic geometry, modular forms, Galois representations, and computational number theory. Research Areas - Arithmetic Geometry : Study of geometric objects defined over number fields and their arithmetic properties - Modular Forms : Classical and Drinfeld modular forms, their L-functions and applications - Galois Representations : Deformation theory and modularity of Galois representations - Computational Number Theory : Algorithmic aspects of arithmetic geometry and number theory Current Projects - Computational aspects of Drinfeld modular forms - Deformation theory of Galois representations - Modularity lifting theorems - L-functions and special values Teaching Prof. BÃ¶ckle teaches various courses in arithmetic geometry, number theory, and related topics at Heidelberg University.  Gebhard BÃ¶ckle gebhard.boeckle@math.uni-heidelberg.de Gebhard BÃ¶ckle gebhard-boeckle /assets/img/gebhard-boeckle.jpg Research interests in arithmetic geometry, modular forms, Galois representations, and computational number theory. Professor & Group Leader active .md","url":"/members/gebhard-boeckle/","category":"member","description":"","tags":"","position":"","email":"gebhard.boeckle@math.uni-heidelberg.de","research_interests":"Research interests in arithmetic geometry, modular forms, Galois representations, and computational number theory.","status":"active","role":"Professor & Group Leader"},{"id":"member-Giacomo Hermes Ferraro","title":"Giacomo Hermes Ferraro","content":"title: {{ page.name }} Giacomo Hermes Ferraro is a member of the AG Computational Arithmetic Geometry research group at Heidelberg University.  Giacomo Hermes Ferraro Giacomo Hermes Ferraro arithgeo@iwr.uni-heidelberg.de Postdoctoral Researcher active /assets/img/giacomo-hermes-ferraro.jpg giacomo-hermes-ferraro .md","url":"/members/giacomo-hermes-ferraro/","category":"member","description":"","tags":"","position":"","email":"arithgeo@iwr.uni-heidelberg.de","research_interests":"","status":"active","role":"Postdoctoral Researcher"},{"id":"member-Juan CerviÃ±o","title":"Juan CerviÃ±o","content":"title: {{ page.name }}  Juan CerviÃ±o juan.cervino@math.uni-heidelberg.de Juan CerviÃ±o Alumni alumni /assets/img/juan-cerviÃ±o.jpg juan-cervino .md","url":"/members/?section=alumni","category":"member","description":"","tags":"","position":"","email":"juan.cervino@math.uni-heidelberg.de","research_interests":"","status":"alumni","role":"Alumni"},{"id":"member-Juan Marcos CerviÃ±o","title":"Juan Marcos CerviÃ±o","content":"title: {{ page.name }} Juan Marcos CerviÃ±o was a member of the AG Computational Arithmetic Geometry research group at the Heidelberg University.  Juan Marcos CerviÃ±o Juan Marcos CerviÃ±o arithgeo@iwr.uni-heidelberg.de Postdoctoral Researcher alumni /assets/img/juan-marcos-cerviÃ±o.jpg Former Member juan-marcos-cervino .md","url":"/members/?section=alumni","category":"member","description":"","tags":"","position":"","email":"arithgeo@iwr.uni-heidelberg.de","research_interests":"","status":"alumni","role":"Postdoctoral Researcher"},{"id":"member-Judith Ludwig","title":"Judith Ludwig","content":"title: {{ page.name }} Judith Ludwig was a member of the AG Computational Arithmetic Geometry research group at the Heidelberg University.  Judith Ludwig Judith Ludwig arithgeo@iwr.uni-heidelberg.de Professor alumni /assets/img/judith-ludwig.jpg Former Member judith-ludwig .md","url":"/members/?section=alumni","category":"member","description":"","tags":"","position":"","email":"arithgeo@iwr.uni-heidelberg.de","research_interests":"","status":"alumni","role":"Professor"},{"id":"member-Julian Quast","title":"Julian Quast","content":"title: {{ page.name }} Julian Quast was a member of the AG Computational Arithmetic Geometry research group at the Heidelberg University.  Julian Quast Julian Quast arithgeo@iwr.uni-heidelberg.de Postdoctoral Researcher alumni /assets/img/julian-quast.jpg Former Member julian-quast .md","url":"/members/?section=alumni","category":"member","description":"","tags":"","position":"","email":"arithgeo@iwr.uni-heidelberg.de","research_interests":"","status":"alumni","role":"Postdoctoral Researcher"},{"id":"member-Konrad Fischer","title":"Konrad Fischer","content":"title: {{ page.name }} Konrad Fischer was a member of the AG Computational Arithmetic Geometry research group at the Heidelberg University.  Konrad Fischer Konrad Fischer arithgeo@iwr.uni-heidelberg.de PhD Student alumni /assets/img/konrad-fischer.jpg Former Member konrad-fischer .md","url":"/members/?section=alumni","category":"member","description":"","tags":"","position":"","email":"arithgeo@iwr.uni-heidelberg.de","research_interests":"","status":"alumni","role":"PhD Student"},{"id":"member-Narasimha Kumar Cheraku","title":"Narasimha Kumar Cheraku","content":"title: {{ page.name }} Narasimha Kumar Cheraku was a member of the AG Computational Arithmetic Geometry research group at the Heidelberg University.  Narasimha Kumar Cheraku Narasimha Kumar Cheraku arithgeo@iwr.uni-heidelberg.de Postdoctoral Researcher alumni /assets/img/narasimha-kumar-cheraku.jpg Former Member narasimha-kumar-cheraku .md","url":"/members/?section=alumni","category":"member","description":"","tags":"","position":"","email":"arithgeo@iwr.uni-heidelberg.de","research_interests":"","status":"alumni","role":"Postdoctoral Researcher"},{"id":"member-Ãzge Ãlkem","title":"Ãzge Ãlkem","content":"title: {{ page.name }} Ãzge Ãlkem was a member of the AG Computational Arithmetic Geometry research group at the Heidelberg University.  Ãzge Ãlkem Ãzge Ãlkem arithgeo@iwr.uni-heidelberg.de Postdoctoral Researcher alumni /assets/img/oezge-uelkem.jpg Former Member oezge-uelkem .md","url":"/members/?section=alumni","category":"member","description":"","tags":"","position":"","email":"arithgeo@iwr.uni-heidelberg.de","research_interests":"","status":"alumni","role":"Postdoctoral Researcher"},{"id":"member-Oguz GezmiÅ","title":"Oguz GezmiÅ","content":"title: {{ page.name }} Oguz GezmiÅ was a member of the AG Computational Arithmetic Geometry research group at Heidelberg University.  Oguz GezmiÅ Oguz GezmiÅ arithgeo@iwr.uni-heidelberg.de Postdoctoral Researcher alumni /assets/img/oguz-gezmiÅ.jpg Former Member oguz-gezmis .md","url":"/members/?section=alumni","category":"member","description":"","tags":"","position":"","email":"arithgeo@iwr.uni-heidelberg.de","research_interests":"","status":"alumni","role":"Postdoctoral Researcher"},{"id":"member-Paola Chilla","title":"Paola Chilla","content":"title: {{ page.name }} Paola Chilla is a member of the AG Computational Arithmetic Geometry research group at the Heidelberg University.  Paola Chilla Paola Chilla arithgeo@iwr.uni-heidelberg.de PhD Student active /assets/img/paola-chilla.jpg paola-chilla .md","url":"/members/paola-chilla/","category":"member","description":"","tags":"","position":"","email":"arithgeo@iwr.uni-heidelberg.de","research_interests":"","status":"active","role":"PhD Student"},{"id":"member-Patrik Hubschmid","title":"Patrik Hubschmid","content":"title: {{ page.name }} Patrik Hubschmid was a member of the AG Computational Arithmetic Geometry research group at Heidelberg University.  Patrik Hubschmid Patrik Hubschmid arithgeo@iwr.uni-heidelberg.de Postdoctoral Researcher alumni /assets/img/patrik-hubschmid.jpg Former Member patrik-hubschmid .md","url":"/members/?section=alumni","category":"member","description":"","tags":"","position":"","email":"arithgeo@iwr.uni-heidelberg.de","research_interests":"","status":"alumni","role":"Postdoctoral Researcher"},{"id":"member-Peter GrÃ¤f","title":"Peter GrÃ¤f","content":"title: {{ page.name }} Peter GrÃ¤f was a member of the AG Computational Arithmetic Geometry research group at the Heidelberg University.  Peter GrÃ¤f Peter GrÃ¤f arithgeo@iwr.uni-heidelberg.de Postdoctoral Researcher alumni /assets/img/peter-graef.jpg Former Member peter-graef .md","url":"/members/?section=alumni","category":"member","description":"","tags":"","position":"","email":"arithgeo@iwr.uni-heidelberg.de","research_interests":"","status":"alumni","role":"Postdoctoral Researcher"},{"id":"member-Ralf Butenuth","title":"Ralf Butenuth","content":"title: {{ page.name }} Ralf Butenuth was a member of the AG Computational Arithmetic Geometry research group at the Heidelberg University.  Ralf Butenuth Ralf Butenuth arithgeo@iwr.uni-heidelberg.de Postdoctoral Researcher alumni /assets/img/ralf-butenuth.jpg Former Member ralf-butenuth .md","url":"/members/?section=alumni","category":"member","description":"","tags":"","position":"","email":"arithgeo@iwr.uni-heidelberg.de","research_interests":"","status":"alumni","role":"Postdoctoral Researcher"},{"id":"member-Rudolph Perkins","title":"Rudolph Perkins","content":"title: {{ page.name }} Rudolph Perkins was a member of the AG Computational Arithmetic Geometry research group at the Heidelberg University.  Rudolph Perkins Rudolph Perkins arithgeo@iwr.uni-heidelberg.de Postdoctoral Researcher alumni /assets/img/rudolph-perkins.jpg Former Member rudolph-perkins .md","url":"/members/?section=alumni","category":"member","description":"","tags":"","position":"","email":"arithgeo@iwr.uni-heidelberg.de","research_interests":"","status":"alumni","role":"Postdoctoral Researcher"},{"id":"member-Samuele Anni","title":"Samuele Anni","content":"title: {{ page.name }} Samuele Anni was a member of the AG Computational Arithmetic Geometry research group at the Heidelberg University.  Samuele Anni Samuele Anni arithgeo@iwr.uni-heidelberg.de Postdoctoral Researcher alumni /assets/img/samuele-anni.jpg Former Member samuele-anni .md","url":"/members/?section=alumni","category":"member","description":"","tags":"","position":"","email":"arithgeo@iwr.uni-heidelberg.de","research_interests":"","status":"alumni","role":"Postdoctoral Researcher"},{"id":"member-Sriram Chinthalagiri Venkata","title":"Sriram Chinthalagiri Venkata","content":"title: {{ page.name }} Sriram Chinthalagiri Venkata is a member of the AG Computational Arithmetic Geometry research group at Heidelberg University.  Sriram Chinthalagiri Venkata Sriram Chinthalagiri Venkata arithgeo@iwr.uni-heidelberg.de PhD Student active /assets/img/sriram-chinthalagiri-venkata.jpg sriram-chinthalagiri-venkata .md","url":"/members/sriram-chinthalagiri-venkata/","category":"member","description":"","tags":"","position":"","email":"arithgeo@iwr.uni-heidelberg.de","research_interests":"","status":"active","role":"PhD Student"},{"id":"member-Sundeep Balaji","title":"Sundeep Balaji","content":"title: {{ page.name }} Sundeep Balaji was a member of the AG Computational Arithmetic Geometry research group at Heidelberg University.  Sundeep Balaji Sundeep Balaji arithgeo@iwr.uni-heidelberg.de Postdoctoral Researcher alumni /assets/img/sundeep-balaji.jpg Former Member sundeep-balaji .md","url":"/members/?section=alumni","category":"member","description":"","tags":"","position":"","email":"arithgeo@iwr.uni-heidelberg.de","research_interests":"","status":"alumni","role":"Postdoctoral Researcher"},{"id":"member-Test User","title":"Test User","content":"Short bio for Test User used to verify that the member profile renders and that related publications and teaching sections are populated automatically.   Test User PhD Student active test.user@example.com /assets/img/gebhard-boeckle.jpg Testing PagesCMS integration across collections. Interested in verification,\ncontent workflows, and static site generation pipelines.\n Test User test-user .md","url":"/members/test-user/","category":"member","description":"","tags":"","position":"","email":"test.user@example.com","research_interests":"Testing PagesCMS integration across collections. Interested in verification,\ncontent workflows, and static site generation pipelines.\n","status":"active","role":"PhD Student"},{"id":"member-Theresa Kaiser","title":"Theresa Kaiser","content":"title: {{ page.name }} Theresa Kaiser is a member of the AG Computational Arithmetic Geometry research group at Heidelberg University.  Theresa Kaiser Theresa Kaiser arithgeo@iwr.uni-heidelberg.de PhD Student active /assets/img/theresa-kaiser.jpg theresa-kaiser .md","url":"/members/theresa-kaiser/","category":"member","description":"","tags":"","position":"","email":"arithgeo@iwr.uni-heidelberg.de","research_interests":"","status":"active","role":"PhD Student"},{"id":"member-Tommaso Centeleghe","title":"Tommaso Centeleghe","content":"title: {{ page.name }} Tommaso Centeleghe was a member of the AG Computational Arithmetic Geometry research group at the Heidelberg University.  Tommaso Centeleghe Tommaso Centeleghe arithgeo@iwr.uni-heidelberg.de Postdoctoral Researcher alumni /assets/img/tommaso-centeleghe.jpg Former Member tommaso-centeleghe .md","url":"/members/?section=alumni","category":"member","description":"","tags":"","position":"","email":"arithgeo@iwr.uni-heidelberg.de","research_interests":"","status":"alumni","role":"Postdoctoral Researcher"},{"id":"member-Yamidt Bermudez Tobon","title":"Yamidt Bermudez Tobon","content":"title: {{ page.name }} Yamidt Bermudez Tobon was a member of the AG Computational Arithmetic Geometry research group at the Heidelberg University.  Yamidt Bermudez Tobon Yamidt Bermudez Tobon arithgeo@iwr.uni-heidelberg.de Postdoctoral Researcher alumni /assets/img/yamidt-bermudez-tobon.jpg Former Member yamidt-bermudez-tobon .md","url":"/members/?section=alumni","category":"member","description":"","tags":"","position":"","email":"arithgeo@iwr.uni-heidelberg.de","research_interests":"","status":"alumni","role":"Postdoctoral Researcher"},{"id":"member-Yujia Qiu","title":"Yujia Qiu","content":"title: {{ page.name }} Yujia Qiu was a member of the AG Computational Arithmetic Geometry research group at the Heidelberg University.  Yujia Qiu Yujia Qiu arithgeo@iwr.uni-heidelberg.de Postdoctoral Researcher alumni /assets/img/yujia-qiu.jpg Former Member yujia-qiu .md","url":"/members/?section=alumni","category":"member","description":"","tags":"","position":"","email":"arithgeo@iwr.uni-heidelberg.de","research_interests":"","status":"alumni","role":"Postdoctoral Researcher"},{"id":"teaching-Teaching Documents","title":"Teaching Documents","content":"Teaching Documents This page contains course materials, syllabi, and other teaching documents. Course Materials Note: Course materials will be added here as they become available. Syllabi Note: Course syllabi will be posted here. Additional Resources Note: Additional teaching resources will be added here. --- For current teaching activities, please see the main Teaching page.   Teaching Documents index .md","url":"/teaching/?q=Teaching+Documents","category":"teaching","description":"","tags":"","semester":"","instructor":"","course_type":"","semester_year":"","semester_key":""},{"id":"teaching-Index","title":"Index","content":"Back to All Courses Filter by Type: All Courses Lectures Seminars Proseminars Hauptseminars Filter by Year: All Years {% assign teaching all = site.teaching | where: 'layout', 'teaching' %} {% assign years = teaching all | map: 'semester year' | compact | uniq | sort | reverse %} {% for y in years %} {% if y %} {{ y }} {% endif %} {% endfor %} Search Courses: {% assign teaching all = site.teaching | where: 'layout', 'teaching' %} {% assign teaching sorted = teaching all | sort: 'semester sort' | reverse %} Recent Teaching {% assign recent courses = teaching sorted | where exp: \"c\", \"c.semester key and c.semester key != ''\" %} {% assign recent by semester = recent courses | group by: 'semester key' %} {% for sem in recent by semester %} {% assign sample = sem.items | first %} {{ sample.semester key }} {% for course in sem.items %} {% assign type lower = course.course type | downcase %} {% if type lower == 'vorlesung' %} Lecture{% elsif type lower == 'hauptseminar' %} Advanced Seminar{% elsif type lower == 'proseminar' %} Proseminar{% else %} {{ course.course type }}{% endif %} {{ course.title }} {% if course.instructor %} ({{ course.instructor }}) {% endif %} {% assign has links = course.links.size %} {% assign has pdfs = course.pdfs.size %} {% comment %}Check if course has additional content beyond the title{% endcomment %} {% assign has expandable content = false %} {% if course.content %} {% assign content length = course.content | size %} {% assign title length = course.title | size %} {% comment %}If content is significantly longer than title, or contains subdomain content markers{% endcomment %} {% assign min length = title length | plus: 20 %} {% if content length > min length or course.content contains '--- Content from' %} {% assign has expandable content = true %} {% endif %} {% endif %} {% if has links or has pdfs or has expandable content %} {% for link in course.links %} {% if link.url %} {{ link.label | default: 'Link' }} {% endif %} {% endfor %} {% for pdf in course.pdfs %} {% if pdf.file %} {{ pdf.label | default: 'PDF' }} {% endif %} {% endfor %} {% endif %} {% comment %}Only show expand button if there's expandable content{% endcomment %} {% if has expandable content %} {% endif %} {% comment %}Only show course details if there's expandable content{% endcomment %} {% if has expandable content %} {% if course.content contains '--- Content from' %} {% comment %}Show only the subdomain content, not the original title{% endcomment %} {% assign subdomain start = course.content | split: '--- Content from' | last %} {% if subdomain start != course.content %} {{ subdomain start }} {% endif %} {% else %} {% comment %}Show the full content minus the title part{% endcomment %} {% assign content without title = course.content | remove: course.title | strip %} {% if content without title != \"\" and content without title != course.title %} {{ content without title }} {% endif %} {% endif %} {% endif %} {% endfor %} {% endfor %}   /assets/js/components/teaching-page.js Teaching overview with filters and recent courses Index index .md","url":"/teaching/?q=Index","category":"teaching","description":"Teaching overview with filters and recent courses","tags":"","semester":"","instructor":"","course_type":"","semester_year":"","semester_key":""},{"id":"teaching-Elliptische Kurven und Anwendungen in der Krytographie (Prof. Dr. BÃ¶ckle)","title":"Elliptische Kurven und Anwendungen in der Krytographie (Prof. Dr. BÃ¶ckle)","content":"Elliptische Kurven und Anwendungen in der Krytographie (Prof. Dr. BÃ¶ckle)   Elliptische Kurven und Anwendungen in der Krytographie (Prof. Dr. BÃ¶ckle) Summer term 2003 Prof. Dr. BÃ¶ckle Seminar SS SS2003 Prof. Dr. BÃ¶ckle Elliptische Kurven und Anwendungen in der Krytographie (Prof. Dr. BÃ¶ckle) ss2003-elliptische-kurven-und-anwendungen-in-der-krytogra .md","url":"/teaching/?q=Elliptische+Kurven+und+Anwendungen+in+der+Krytographie+%28Prof.+Dr.+B%C3%B6ckle%29","category":"teaching","description":"Elliptische Kurven und Anwendungen in der Krytographie (Prof. Dr. BÃ¶ckle)","tags":"","semester":"Summer term 2003","instructor":"Prof. Dr. BÃ¶ckle","course_type":"Seminar","semester_year":2003,"semester_key":"SS2003"},{"id":"teaching-Arbeitsgemeinschaft: KlassenkÃ¶rpertheorie (G. BÃ¶ckle, G. Frey, I. Bouw, C. Diem)","title":"Arbeitsgemeinschaft: KlassenkÃ¶rpertheorie (G. BÃ¶ckle, G. Frey, I. Bouw, C. Diem)","content":"Arbeitsgemeinschaft: KlassenkÃ¶rpertheorie (G. BÃ¶ckle, G. Frey, I. Bouw, C. Diem)   Arbeitsgemeinschaft: KlassenkÃ¶rpertheorie (G. BÃ¶ckle, G. Frey, I. Bouw, C. Diem) Summer term 2004 G. BÃ¶ckle, G. Frey, I. Bouw, C. Diem Arbeitsgemeinschaft SS SS2004 G. BÃ¶ckle, G. Frey, I. Bouw, C. Diem Arbeitsgemeinschaft: KlassenkÃ¶rpertheorie (G. BÃ¶ckle, G. Frey, I. Bouw, C. Diem) ss2004-arbeitsgemeinschaft-klassenkrpertheorie-g-bckle-g- .md","url":"/teaching/?q=Arbeitsgemeinschaft%3A+Klassenk%C3%B6rpertheorie+%28G.+B%C3%B6ckle%2C+G.+Frey%2C+I.+Bouw%2C+C.+Diem%29","category":"teaching","description":"Arbeitsgemeinschaft: KlassenkÃ¶rpertheorie (G. BÃ¶ckle, G. Frey, I. Bouw, C. Diem)","tags":"","semester":"Summer term 2004","instructor":"G. BÃ¶ckle, G. Frey, I. Bouw, C. Diem","course_type":"Arbeitsgemeinschaft","semester_year":2004,"semester_key":"SS2004"},{"id":"teaching-Drinfeld Moduln (Prof. Dr. BÃ¶ckle)","title":"Drinfeld Moduln (Prof. Dr. BÃ¶ckle)","content":"Drinfeld Moduln (Prof. Dr. BÃ¶ckle)   Drinfeld Moduln (Prof. Dr. BÃ¶ckle) Summer term 2004 Prof. Dr. BÃ¶ckle Seminar SS SS2004 Prof. Dr. BÃ¶ckle Drinfeld Moduln (Prof. Dr. BÃ¶ckle) ss2004-drinfeld-moduln-prof-dr-bckle .md","url":"/teaching/?q=Drinfeld+Moduln+%28Prof.+Dr.+B%C3%B6ckle%29","category":"teaching","description":"Drinfeld Moduln (Prof. Dr. BÃ¶ckle)","tags":"","semester":"Summer term 2004","instructor":"Prof. Dr. BÃ¶ckle","course_type":"Seminar","semester_year":2004,"semester_key":"SS2004"},{"id":"teaching-Seminar Elementare Algorithmen in der Zahlentheorie (Prof. Dr. BÃ¶ckle)","title":"Seminar Elementare Algorithmen in der Zahlentheorie (Prof. Dr. BÃ¶ckle)","content":"Seminar \"Elementare Algorithmen in der Zahlentheorie\" (Prof. Dr. BÃ¶ckle)   Seminar Elementare Algorithmen in der Zahlentheorie (Prof. Dr. BÃ¶ckle) Summer term 2004 Prof. Dr. BÃ¶ckle Seminar SS SS2004 Prof. Dr. BÃ¶ckle Seminar Elementare Algorithmen in der Zahlentheorie (Prof. Dr. BÃ¶ckle) ss2004-seminar-elementare-algorithmen-in-der-zahlentheori .md","url":"/teaching/?q=Seminar+Elementare+Algorithmen+in+der+Zahlentheorie+%28Prof.+Dr.+B%C3%B6ckle%29","category":"teaching","description":"Seminar Elementare Algorithmen in der Zahlentheorie (Prof. Dr. BÃ¶ckle)","tags":"","semester":"Summer term 2004","instructor":"Prof. Dr. BÃ¶ckle","course_type":"Seminar","semester_year":2004,"semester_key":"SS2004"},{"id":"teaching-Arbeitsgemeinschaft: Hilbertsche Modulformen (G. BÃ¶ckle, C. Diem, G. Frey, M. MÃ¶ller)","title":"Arbeitsgemeinschaft: Hilbertsche Modulformen (G. BÃ¶ckle, C. Diem, G. Frey, M. MÃ¶ller)","content":"Arbeitsgemeinschaft: Hilbertsche Modulformen (G. BÃ¶ckle, C. Diem, G. Frey, M. MÃ¶ller)   Arbeitsgemeinschaft: Hilbertsche Modulformen (G. BÃ¶ckle, C. Diem, G. Frey, M. MÃ¶ller) Summer term 2005 G. BÃ¶ckle, C. Diem, G. Frey, M. MÃ¶ller Arbeitsgemeinschaft SS SS2005 G. BÃ¶ckle, C. Diem, G. Frey, M. MÃ¶ller Arbeitsgemeinschaft: Hilbertsche Modulformen (G. BÃ¶ckle, C. Diem, G. Frey, M. MÃ¶ller) ss2005-arbeitsgemeinschaft-hilbertsche-modulformen-g-bckl .md","url":"/teaching/?q=Arbeitsgemeinschaft%3A+Hilbertsche+Modulformen+%28G.+B%C3%B6ckle%2C+C.+Diem%2C+G.+Frey%2C+M.+M%C3%B6ller%29","category":"teaching","description":"Arbeitsgemeinschaft: Hilbertsche Modulformen (G. BÃ¶ckle, C. Diem, G. Frey, M. MÃ¶ller)","tags":"","semester":"Summer term 2005","instructor":"G. BÃ¶ckle, C. Diem, G. Frey, M. MÃ¶ller","course_type":"Arbeitsgemeinschaft","semester_year":2005,"semester_key":"SS2005"},{"id":"teaching-Lineare Algebra 2 (Prof. Dr. BÃ¶ckle)","title":"Lineare Algebra 2 (Prof. Dr. BÃ¶ckle)","content":"Lineare Algebra 2 (Prof. Dr. BÃ¶ckle)   Lineare Algebra 2 (Prof. Dr. BÃ¶ckle) Summer term 2005 Prof. Dr. BÃ¶ckle Seminar SS SS2005 Prof. Dr. BÃ¶ckle Lineare Algebra 2 (Prof. Dr. BÃ¶ckle) ss2005-lineare-algebra-2-prof-dr-bckle .md","url":"/teaching/?q=Lineare+Algebra+2+%28Prof.+Dr.+B%C3%B6ckle%29","category":"teaching","description":"Lineare Algebra 2 (Prof. Dr. BÃ¶ckle)","tags":"","semester":"Summer term 2005","instructor":"Prof. Dr. BÃ¶ckle","course_type":"Seminar","semester_year":2005,"semester_key":"SS2005"},{"id":"teaching-Algebra 2 (Prof. BÃ¶ckle)","title":"Algebra 2 (Prof. BÃ¶ckle)","content":"Algebra 2 (Prof. BÃ¶ckle)   Algebra 2 (Prof. BÃ¶ckle) Summer term 2006 Prof. BÃ¶ckle Seminar SS SS2006 Prof. BÃ¶ckle Algebra 2 (Prof. BÃ¶ckle) ss2006-algebra-2-prof-bckle .md","url":"/teaching/?q=Algebra+2+%28Prof.+B%C3%B6ckle%29","category":"teaching","description":"Algebra 2 (Prof. BÃ¶ckle)","tags":"","semester":"Summer term 2006","instructor":"Prof. BÃ¶ckle","course_type":"Seminar","semester_year":2006,"semester_key":"SS2006"},{"id":"teaching-Arbeitsgemeinschaft: Ãber eine Vermutung von A.J. de Jong (G. BÃ¶ckle, H. Esnault, J. Heinloth)","title":"Arbeitsgemeinschaft: Ãber eine Vermutung von A.J. de Jong (G. BÃ¶ckle, H. Esnault, J. Heinloth)","content":"Arbeitsgemeinschaft: Ãber eine Vermutung von A.J. de Jong (G. BÃ¶ckle, H. Esnault, J. Heinloth)   Arbeitsgemeinschaft: Ãber eine Vermutung von A.J. de Jong (G. BÃ¶ckle, H. Esnault, J. Heinloth) Summer term 2006 G. BÃ¶ckle, H. Esnault, J. Heinloth Arbeitsgemeinschaft SS SS2006 G. BÃ¶ckle, H. Esnault, J. Heinloth Arbeitsgemeinschaft: Ãber eine Vermutung von A.J. de Jong (G. BÃ¶ckle, H. Esnault, J. Heinloth) ss2006-arbeitsgemeinschaft-ber-eine-vermutung-von-aj-de-j .md","url":"/teaching/?q=Arbeitsgemeinschaft%3A+%C3%9Cber+eine+Vermutung+von+A.J.+de+Jong+%28G.+B%C3%B6ckle%2C+H.+Esnault%2C+J.+Heinloth%29","category":"teaching","description":"Arbeitsgemeinschaft: Ãber eine Vermutung von A.J. de Jong (G. BÃ¶ckle, H. Esnault, J. Heinloth)","tags":"","semester":"Summer term 2006","instructor":"G. BÃ¶ckle, H. Esnault, J. Heinloth","course_type":"Arbeitsgemeinschaft","semester_year":2006,"semester_key":"SS2006"},{"id":"teaching-Proseminar Zahlentheorie (Prof. Dr. BÃ¶ckle)","title":"Proseminar Zahlentheorie (Prof. Dr. BÃ¶ckle)","content":"Proseminar \"Zahlentheorie\" (Prof. Dr. BÃ¶ckle)   Proseminar Zahlentheorie (Prof. Dr. BÃ¶ckle) Summer term 2006 Prof. Dr. BÃ¶ckle Seminar SS SS2006 Prof. Dr. BÃ¶ckle Proseminar Zahlentheorie (Prof. Dr. BÃ¶ckle) ss2006-proseminar-zahlentheorie-prof-dr-bckle .md","url":"/teaching/?q=Proseminar+Zahlentheorie+%28Prof.+Dr.+B%C3%B6ckle%29","category":"teaching","description":"Proseminar Zahlentheorie (Prof. Dr. BÃ¶ckle)","tags":"","semester":"Summer term 2006","instructor":"Prof. Dr. BÃ¶ckle","course_type":"Seminar","semester_year":2006,"semester_key":"SS2006"},{"id":"teaching-Algebraische Zahlentheorie 2 (Prof. Dr. BÃ¶ckle)","title":"Algebraische Zahlentheorie 2 (Prof. Dr. BÃ¶ckle)","content":"Algebraische Zahlentheorie 2 (Prof. Dr. BÃ¶ckle)   Algebraische Zahlentheorie 2 (Prof. Dr. BÃ¶ckle) Summer term 2007 Prof. Dr. BÃ¶ckle Seminar SS SS2007 Prof. Dr. BÃ¶ckle Algebraische Zahlentheorie 2 (Prof. Dr. BÃ¶ckle) ss2007-algebraische-zahlentheorie-2-prof-dr-bckle .md","url":"/teaching/?q=Algebraische+Zahlentheorie+2+%28Prof.+Dr.+B%C3%B6ckle%29","category":"teaching","description":"Algebraische Zahlentheorie 2 (Prof. Dr. BÃ¶ckle)","tags":"","semester":"Summer term 2007","instructor":"Prof. Dr. BÃ¶ckle","course_type":"Seminar","semester_year":2007,"semester_key":"SS2007"},{"id":"teaching-Arbeitsgemeinschaft: EinfÃ¼hrung in die Theorie der Automorphen Formen (P. Angel, G. BÃ¶ckle, J.-M. CerviÃ±o, G. Wiese)","title":"Arbeitsgemeinschaft: EinfÃ¼hrung in die Theorie der Automorphen Formen (P. Angel, G. BÃ¶ckle, J.-M. CerviÃ±o, G. Wiese)","content":"Arbeitsgemeinschaft: EinfÃ¼hrung in die Theorie der Automorphen Formen (P. Angel, G. BÃ¶ckle,Â J.-M. CerviÃ±o, G. Wiese)   Arbeitsgemeinschaft: EinfÃ¼hrung in die Theorie der Automorphen Formen (P. Angel, G. BÃ¶ckle, J.-M. CerviÃ±o, G. Wiese) Summer term 2007 P. Angel, G. BÃ¶ckle, J.-M. CerviÃ±o, G. Wiese Arbeitsgemeinschaft SS SS2007 P. Angel, G. BÃ¶ckle, J.-M. CerviÃ±o, G. Wiese Arbeitsgemeinschaft: EinfÃ¼hrung in die Theorie der Automorphen Formen (P. Angel, G. BÃ¶ckle, J.-M. CerviÃ±o, G. Wiese) ss2007-arbeitsgemeinschaft-einfhrung-in-die-theorie-der-a .md","url":"/teaching/?q=Arbeitsgemeinschaft%3A+Einf%C3%BChrung+in+die+Theorie+der+Automorphen+Formen+%28P.+Angel%2C+G.+B%C3%B6ckle%2C+J.-M.+Cervi%C3%B1o%2C+G.+Wiese%29","category":"teaching","description":"Arbeitsgemeinschaft: EinfÃ¼hrung in die Theorie der Automorphen Formen (P. Angel, G. BÃ¶ckle, J.-M. CerviÃ±o, G. Wiese)","tags":"","semester":"Summer term 2007","instructor":"P. Angel, G. BÃ¶ckle, J.-M. CerviÃ±o, G. Wiese","course_type":"Arbeitsgemeinschaft","semester_year":2007,"semester_key":"SS2007"},{"id":"teaching-Ãbungen zu Lineare Algebra II (Dr. CerviÃ±o)","title":"Ãbungen zu Lineare Algebra II (Dr. CerviÃ±o)","content":"Ãbungen zu \"Lineare Algebra II\" (Dr. CerviÃ±o)   Ãbungen zu Lineare Algebra II (Dr. CerviÃ±o) Summer term 2007 Dr. CerviÃ±o Ãbung SS SS2007 Dr. CerviÃ±o Ãbungen zu Lineare Algebra II (Dr. CerviÃ±o) ss2007-bungen-zu-lineare-algebra-ii-dr-cervio .md","url":"/teaching/?q=%C3%9Cbungen+zu+Lineare+Algebra+II+%28Dr.+Cervi%C3%B1o%29","category":"teaching","description":"Ãbungen zu Lineare Algebra II (Dr. CerviÃ±o)","tags":"","semester":"Summer term 2007","instructor":"Dr. CerviÃ±o","course_type":"Ãbung","semester_year":2007,"semester_key":"SS2007"},{"id":"teaching-Seminar Elliptische Kurven (Prof. Dr. BÃ¶ckle, Dr. CerviÃ±o)","title":"Seminar Elliptische Kurven (Prof. Dr. BÃ¶ckle, Dr. CerviÃ±o)","content":"Seminar \"Elliptische Kurven\" (Prof. Dr. BÃ¶ckle, Dr.Â CerviÃ±o)   Seminar Elliptische Kurven (Prof. Dr. BÃ¶ckle, Dr. CerviÃ±o) Summer term 2007 Prof. Dr. BÃ¶ckle, Dr.Â CerviÃ±o Seminar SS SS2007 Prof. Dr. BÃ¶ckle, Dr.Â CerviÃ±o Seminar Elliptische Kurven (Prof. Dr. BÃ¶ckle, Dr. CerviÃ±o) ss2007-seminar-elliptische-kurven-prof-dr-bckle-dr-cervio .md","url":"/teaching/?q=Seminar+Elliptische+Kurven+%28Prof.+Dr.+B%C3%B6ckle%2C+Dr.+Cervi%C3%B1o%29","category":"teaching","description":"Seminar Elliptische Kurven (Prof. Dr. BÃ¶ckle, Dr. CerviÃ±o)","tags":"","semester":"Summer term 2007","instructor":"Prof. Dr. BÃ¶ckle, Dr.Â CerviÃ±o","course_type":"Seminar","semester_year":2007,"semester_key":"SS2007"},{"id":"teaching-Arbeitsgemeinschaft: Eine kanonische Kompaktifizierung des Modulraums Abelscher VarietÃ¤ten (G. BÃ¶ckle, G. Hein)","title":"Arbeitsgemeinschaft: Eine kanonische Kompaktifizierung des Modulraums Abelscher VarietÃ¤ten (G. BÃ¶ckle, G. Hein)","content":"Arbeitsgemeinschaft: Eine kanonische Kompaktifizierung des Modulraums Abelscher VarietÃ¤ten (G. BÃ¶ckle, G. Hein)   Arbeitsgemeinschaft: Eine kanonische Kompaktifizierung des Modulraums Abelscher VarietÃ¤ten (G. BÃ¶ckle, G. Hein) Summer term 2008 G. BÃ¶ckle, G. Hein Arbeitsgemeinschaft SS SS2008 G. BÃ¶ckle, G. Hein Arbeitsgemeinschaft: Eine kanonische Kompaktifizierung des Modulraums Abelscher VarietÃ¤ten (G. BÃ¶ckle, G. Hein) ss2008-arbeitsgemeinschaft-eine-kanonische-kompaktifizier .md","url":"/teaching/?q=Arbeitsgemeinschaft%3A+Eine+kanonische+Kompaktifizierung+des+Modulraums+Abelscher+Variet%C3%A4ten+%28G.+B%C3%B6ckle%2C+G.+Hein%29","category":"teaching","description":"Arbeitsgemeinschaft: Eine kanonische Kompaktifizierung des Modulraums Abelscher VarietÃ¤ten (G. BÃ¶ckle, G. Hein)","tags":"","semester":"Summer term 2008","instructor":"G. BÃ¶ckle, G. Hein","course_type":"Arbeitsgemeinschaft","semester_year":2008,"semester_key":"SS2008"},{"id":"teaching-Arbeitsgemeinschaft: Quaternionenalgebren (G. BÃ¶ckle, J.-M. CerviÃ±o, G. Wiese)","title":"Arbeitsgemeinschaft: Quaternionenalgebren (G. BÃ¶ckle, J.-M. CerviÃ±o, G. Wiese)","content":"Arbeitsgemeinschaft: Quaternionenalgebren (G. BÃ¶ckle, J.-M. CerviÃ±o, G. Wiese)   Arbeitsgemeinschaft: Quaternionenalgebren (G. BÃ¶ckle, J.-M. CerviÃ±o, G. Wiese) Summer term 2008 G. BÃ¶ckle, J.-M. CerviÃ±o, G. Wiese Arbeitsgemeinschaft SS SS2008 G. BÃ¶ckle, J.-M. CerviÃ±o, G. Wiese Arbeitsgemeinschaft: Quaternionenalgebren (G. BÃ¶ckle, J.-M. CerviÃ±o, G. Wiese) ss2008-arbeitsgemeinschaft-quaternionenalgebren-g-bckle-j .md","url":"/teaching/?q=Arbeitsgemeinschaft%3A+Quaternionenalgebren+%28G.+B%C3%B6ckle%2C+J.-M.+Cervi%C3%B1o%2C+G.+Wiese%29","category":"teaching","description":"Arbeitsgemeinschaft: Quaternionenalgebren (G. BÃ¶ckle, J.-M. CerviÃ±o, G. Wiese)","tags":"","semester":"Summer term 2008","instructor":"G. BÃ¶ckle, J.-M. CerviÃ±o, G. Wiese","course_type":"Arbeitsgemeinschaft","semester_year":2008,"semester_key":"SS2008"},{"id":"teaching-Explizite KlassenkÃ¶rpertheorie (Prof. BÃ¶ckle)","title":"Explizite KlassenkÃ¶rpertheorie (Prof. BÃ¶ckle)","content":"Explizite KlassenkÃ¶rpertheorie (Prof. BÃ¶ckle)   Explizite KlassenkÃ¶rpertheorie (Prof. BÃ¶ckle) Summer term 2008 Prof. BÃ¶ckle Seminar SS SS2008 Prof. BÃ¶ckle Explizite KlassenkÃ¶rpertheorie (Prof. BÃ¶ckle) ss2008-explizite-klassenkrpertheorie-prof-bckle .md","url":"/teaching/?q=Explizite+Klassenk%C3%B6rpertheorie+%28Prof.+B%C3%B6ckle%29","category":"teaching","description":"Explizite KlassenkÃ¶rpertheorie (Prof. BÃ¶ckle)","tags":"","semester":"Summer term 2008","instructor":"Prof. BÃ¶ckle","course_type":"Seminar","semester_year":2008,"semester_key":"SS2008"},{"id":"teaching-Seminar Quadratische Formen (Prof. Dr. BÃ¶ckle, Dr. CerviÃ±o)","title":"Seminar Quadratische Formen (Prof. Dr. BÃ¶ckle, Dr. CerviÃ±o)","content":"Seminar \"Quadratische Formen\" (Prof. Dr. BÃ¶ckle, Dr.Â CerviÃ±o)   Seminar Quadratische Formen (Prof. Dr. BÃ¶ckle, Dr. CerviÃ±o) Summer term 2008 Prof. Dr. BÃ¶ckle, Dr.Â CerviÃ±o Seminar SS SS2008 Prof. Dr. BÃ¶ckle, Dr.Â CerviÃ±o Seminar Quadratische Formen (Prof. Dr. BÃ¶ckle, Dr. CerviÃ±o) ss2008-seminar-quadratische-formen-prof-dr-bckle-dr-cervi .md","url":"/teaching/?q=Seminar+Quadratische+Formen+%28Prof.+Dr.+B%C3%B6ckle%2C+Dr.+Cervi%C3%B1o%29","category":"teaching","description":"Seminar Quadratische Formen (Prof. Dr. BÃ¶ckle, Dr. CerviÃ±o)","tags":"","semester":"Summer term 2008","instructor":"Prof. Dr. BÃ¶ckle, Dr.Â CerviÃ±o","course_type":"Seminar","semester_year":2008,"semester_key":"SS2008"},{"id":"teaching-Arbeitsgemeinschaft: Study group on p-adic L-functions and the Mazur-Tate-Teitelbaum conjecture (G. BÃ¶ckle, G. Wiese)","title":"Arbeitsgemeinschaft: Study group on p-adic L-functions and the Mazur-Tate-Teitelbaum conjecture (G. BÃ¶ckle, G. Wiese)","content":"Arbeitsgemeinschaft: Study group on p-adic L-functions and the Mazur-Tate-Teitelbaum conjecture (G. BÃ¶ckle, G. Wiese)   Arbeitsgemeinschaft: Study group on p-adic L-functions and the Mazur-Tate-Teitelbaum conjecture (G. BÃ¶ckle, G. Wiese) Summer term 2009 G. BÃ¶ckle, G. Wiese Arbeitsgemeinschaft SS SS2009 G. BÃ¶ckle, G. Wiese Arbeitsgemeinschaft: Study group on p-adic L-functions and the Mazur-Tate-Teitelbaum conjecture (G. BÃ¶ckle, G. Wiese) ss2009-arbeitsgemeinschaft-study-group-on-p-adic-l-functi .md","url":"/teaching/?q=Arbeitsgemeinschaft%3A+Study+group+on+p-adic+L-functions+and+the+Mazur-Tate-Teitelbaum+conjecture+%28G.+B%C3%B6ckle%2C+G.+Wiese%29","category":"teaching","description":"Arbeitsgemeinschaft: Study group on p-adic L-functions and the Mazur-Tate-Teitelbaum conjecture (G. BÃ¶ckle, G. Wiese)","tags":"","semester":"Summer term 2009","instructor":"G. BÃ¶ckle, G. Wiese","course_type":"Arbeitsgemeinschaft","semester_year":2009,"semester_key":"SS2009"},{"id":"teaching-Arbeitsgemeinschaft: The Eigencurve (mit U. Goertz und G. Wiese)","title":"Arbeitsgemeinschaft: The Eigencurve (mit U. Goertz und G. Wiese)","content":"Arbeitsgemeinschaft: The Eigencurve (mit U. Goertz und G. Wiese)   Arbeitsgemeinschaft: The Eigencurve (mit U. Goertz und G. Wiese) <a href=../teaching.html title=Opens internal link in current window class=internal-link>Link to recent teaching at the University Heidelberg</a></h4><h2>Teaching at the University Duisburg-Essen</h2><h4>Winter term 2009/2010 mit U. Goertz und G. Wiese Arbeitsgemeinschaft SS SS2009 mit U. Goertz und G. Wiese Arbeitsgemeinschaft: The Eigencurve (mit U. Goertz und G. Wiese) ss2009-arbeitsgemeinschaft-the-eigencurve-mit-u-goertz-un .md","url":"/teaching/?q=Arbeitsgemeinschaft%3A+The+Eigencurve+%28mit+U.+Goertz+und+G.+Wiese%29","category":"teaching","description":"Arbeitsgemeinschaft: The Eigencurve (mit U. Goertz und G. Wiese)","tags":"","semester":"<a href=../teaching.html title=Opens internal link in current window class=internal-link>Link to recent teaching at the University Heidelberg</a></h4><h2>Teaching at the University Duisburg-Essen</h2><h4>Winter term 2009/2010","instructor":"mit U. Goertz und G. Wiese","course_type":"Arbeitsgemeinschaft","semester_year":2009,"semester_key":"SS2009"},{"id":"teaching-Mathematik fÃ¼r Biologen (Prof. Dr. BÃ¶ckle)","title":"Mathematik fÃ¼r Biologen (Prof. Dr. BÃ¶ckle)","content":"Mathematik fÃ¼r Biologen (Prof. Dr. BÃ¶ckle)   Mathematik fÃ¼r Biologen (Prof. Dr. BÃ¶ckle) Summer term 2009 Prof. Dr. BÃ¶ckle Seminar SS SS2009 Prof. Dr. BÃ¶ckle Mathematik fÃ¼r Biologen (Prof. Dr. BÃ¶ckle) ss2009-mathematik-fr-biologen-prof-dr-bckle .md","url":"/teaching/?q=Mathematik+f%C3%BCr+Biologen+%28Prof.+Dr.+B%C3%B6ckle%29","category":"teaching","description":"Mathematik fÃ¼r Biologen (Prof. Dr. BÃ¶ckle)","tags":"","semester":"Summer term 2009","instructor":"Prof. Dr. BÃ¶ckle","course_type":"Seminar","semester_year":2009,"semester_key":"SS2009"},{"id":"teaching-Mathematik Vorkurs (Dr. CerviÃ±o)","title":"Mathematik Vorkurs (Dr. CerviÃ±o)","content":"Mathematik Vorkurs (Dr. CerviÃ±o)   Mathematik Vorkurs (Dr. CerviÃ±o) <a href=../teaching.html title=Opens internal link in current window class=internal-link>Link to recent teaching at the University Heidelberg</a></h4><h2>Teaching at the University Duisburg-Essen</h2><h4>Winter term 2009/2010 Dr. CerviÃ±o Vorlesung SS SS2009 Dr. CerviÃ±o Mathematik Vorkurs (Dr. CerviÃ±o) ss2009-mathematik-vorkurs-dr-cervio .md","url":"/teaching/?q=Mathematik+Vorkurs+%28Dr.+Cervi%C3%B1o%29","category":"teaching","description":"Mathematik Vorkurs (Dr. CerviÃ±o)","tags":"","semester":"<a href=../teaching.html title=Opens internal link in current window class=internal-link>Link to recent teaching at the University Heidelberg</a></h4><h2>Teaching at the University Duisburg-Essen</h2><h4>Winter term 2009/2010","instructor":"Dr. CerviÃ±o","course_type":"Vorlesung","semester_year":2009,"semester_key":"SS2009"},{"id":"teaching-Exercise sessions for Elementary number theory (Ralf Butenuth)","title":"Exercise sessions for Elementary number theory (Ralf Butenuth)","content":"Exercise sessions for \"Elementary number theory\" (Ralf Butenuth)   Exercise sessions for Elementary number theory (Ralf Butenuth) Summer term 2011 Ralf Butenuth Ãbung SS SS2011 Ralf Butenuth Exercise sessions for Elementary number theory (Ralf Butenuth) {\"label\"=>\"Elementary number theory\", \"url\"=>\"http://www.iwr.uni-heidelberg.de/groups/arith-geom/butenuth/zahlentheorie/index.html\"} ss2011-exercise-sessions-for-elementary-number-theory-ral .md","url":"/teaching/?q=Exercise+sessions+for+Elementary+number+theory+%28Ralf+Butenuth%29","category":"teaching","description":"Exercise sessions for Elementary number theory (Ralf Butenuth)","tags":"","semester":"Summer term 2011","instructor":"Ralf Butenuth","course_type":"Ãbung","semester_year":2011,"semester_key":"SS2011"},{"id":"teaching-Linear Algebra 2 (Prof. Dr. BÃ¶ckle)","title":"Linear Algebra 2 (Prof. Dr. BÃ¶ckle)","content":"Linear Algebra 2 (Prof. Dr. BÃ¶ckle)   Linear Algebra 2 (Prof. Dr. BÃ¶ckle) Summer term 2011 Prof. Dr. BÃ¶ckle Seminar SS SS2011 Prof. Dr. BÃ¶ckle Linear Algebra 2 (Prof. Dr. BÃ¶ckle) {\"label\"=>\"Linear Algebra 2\", \"url\"=>\"http://www.ub.uni-heidelberg.de/helios/fachinfo/www/math/kvv/ss2011/g-3.htm\"} ss2011-linear-algebra-2-prof-dr-bckle .md","url":"/teaching/?q=Linear+Algebra+2+%28Prof.+Dr.+B%C3%B6ckle%29","category":"teaching","description":"Linear Algebra 2 (Prof. Dr. BÃ¶ckle)","tags":"","semester":"Summer term 2011","instructor":"Prof. Dr. BÃ¶ckle","course_type":"Seminar","semester_year":2011,"semester_key":"SS2011"},{"id":"teaching-Proseminar Fuchsian groups (Prof. Dr. BÃ¶ckle, Dr. Maurischat)","title":"Proseminar Fuchsian groups (Prof. Dr. BÃ¶ckle, Dr. Maurischat)","content":"Proseminar \"Fuchsian groups\" (Prof. Dr. BÃ¶ckle, Dr. Maurischat)   Proseminar Fuchsian groups (Prof. Dr. BÃ¶ckle, Dr. Maurischat) Summer term 2011 Prof. Dr. BÃ¶ckle, Dr. Maurischat Seminar SS SS2011 Prof. Dr. BÃ¶ckle, Dr. Maurischat Proseminar Fuchsian groups (Prof. Dr. BÃ¶ckle, Dr. Maurischat) {\"label\"=>\"Proseminar Fuchsian groups\", \"url\"=>\"http://www.ub.uni-heidelberg.de/helios/fachinfo/www/math/kvv/ss2011/v-2.htm\"} ss2011-proseminar-fuchsian-groups-prof-dr-bckle-dr-mauris .md","url":"/teaching/?q=Proseminar+Fuchsian+groups+%28Prof.+Dr.+B%C3%B6ckle%2C+Dr.+Maurischat%29","category":"teaching","description":"Proseminar Fuchsian groups (Prof. Dr. BÃ¶ckle, Dr. Maurischat)","tags":"","semester":"Summer term 2011","instructor":"Prof. Dr. BÃ¶ckle, Dr. Maurischat","course_type":"Seminar","semester_year":2011,"semester_key":"SS2011"},{"id":"teaching-Quadratic Forms (Dr. CerviÃ±o)","title":"Quadratic Forms (Dr. CerviÃ±o)","content":"Quadratic Forms (Dr. CerviÃ±o)   Quadratic Forms (Dr. CerviÃ±o) Summer term 2011 Dr. CerviÃ±o Seminar SS SS2011 Dr. CerviÃ±o Quadratic Forms (Dr. CerviÃ±o) ss2011-quadratic-forms-dr-cervio .md","url":"/teaching/?q=Quadratic+Forms+%28Dr.+Cervi%C3%B1o%29","category":"teaching","description":"Quadratic Forms (Dr. CerviÃ±o)","tags":"","semester":"Summer term 2011","instructor":"Dr. CerviÃ±o","course_type":"Seminar","semester_year":2011,"semester_key":"SS2011"},{"id":"teaching-Seminar L-functions after V. Lafforgue (Prof. Dr. BÃ¶ckle, Dr. Maurischat)","title":"Seminar L-functions after V. Lafforgue (Prof. Dr. BÃ¶ckle, Dr. Maurischat)","content":"Seminar \"L-functions after V. Lafforgue\" (Prof. Dr. BÃ¶ckle, Dr. Maurischat)   Seminar L-functions after V. Lafforgue (Prof. Dr. BÃ¶ckle, Dr. Maurischat) Summer term 2011 Prof. Dr. BÃ¶ckle, Dr. Maurischat Seminar SS SS2011 Prof. Dr. BÃ¶ckle, Dr. Maurischat Seminar L-functions after V. Lafforgue (Prof. Dr. BÃ¶ckle, Dr. Maurischat) {\"label\"=>\"Seminar L-functions after V. Lafforgue\", \"url\"=>\"http://www.ub.uni-heidelberg.de/helios/fachinfo/www/math/kvv/ss2011/s-4.htm\"} ss2011-seminar-l-functions-after-v-lafforgue-prof-dr-bckl .md","url":"/teaching/?q=Seminar+L-functions+after+V.+Lafforgue+%28Prof.+Dr.+B%C3%B6ckle%2C+Dr.+Maurischat%29","category":"teaching","description":"Seminar L-functions after V. Lafforgue (Prof. Dr. BÃ¶ckle, Dr. Maurischat)","tags":"","semester":"Summer term 2011","instructor":"Prof. Dr. BÃ¶ckle, Dr. Maurischat","course_type":"Seminar","semester_year":2011,"semester_key":"SS2011"},{"id":"teaching-Algebra 2 (Dr. CerviÃ±o)","title":"Algebra 2 (Dr. CerviÃ±o)","content":"Algebra 2 (Dr. CerviÃ±o)   Algebra 2 (Dr. CerviÃ±o) Summer term 2012 Dr. CerviÃ±o Seminar SS SS2012 Dr. CerviÃ±o Algebra 2 (Dr. CerviÃ±o) {\"label\"=>\"Algebra 2\", \"url\"=>\"http://www.ub.uni-heidelberg.de/helios/fachinfo/www/math/kvv/ss2012/g-9.htm\"} ss2012-algebra-2-dr-cervio .md","url":"/teaching/?q=Algebra+2+%28Dr.+Cervi%C3%B1o%29","category":"teaching","description":"Algebra 2 (Dr. CerviÃ±o)","tags":"","semester":"Summer term 2012","instructor":"Dr. CerviÃ±o","course_type":"Seminar","semester_year":2012,"semester_key":"SS2012"},{"id":"teaching-Exercise sessions for Computeralgebra (Dr. Maurischat)","title":"Exercise sessions for Computeralgebra (Dr. Maurischat)","content":"Exercise sessions for \"Computeralgebra\" (Dr. Maurischat)   Exercise sessions for Computeralgebra (Dr. Maurischat) Summer term 2012 Dr. Maurischat Ãbung SS SS2012 Dr. Maurischat Exercise sessions for Computeralgebra (Dr. Maurischat) {\"label\"=>\"Computeralgebra\", \"url\"=>\"http://www.iwr.uni-heidelberg.de/groups/arith-geom/maurischat/uebungen/compalg-ss2012/index.html\"} ss2012-exercise-sessions-for-computeralgebra-dr-maurischa .md","url":"/teaching/?q=Exercise+sessions+for+Computeralgebra+%28Dr.+Maurischat%29","category":"teaching","description":"Exercise sessions for Computeralgebra (Dr. Maurischat)","tags":"","semester":"Summer term 2012","instructor":"Dr. Maurischat","course_type":"Ãbung","semester_year":2012,"semester_key":"SS2012"},{"id":"teaching-Seminar Automorphic Forms and representations of GL2 (Dr. CerviÃ±o, Dr. Centeleghe)","title":"Seminar Automorphic Forms and representations of GL2 (Dr. CerviÃ±o, Dr. Centeleghe)","content":"Seminar \"Automorphic Forms and representations of GL2\" (Dr. CerviÃ±o, Dr. Centeleghe)   Seminar Automorphic Forms and representations of GL2 (Dr. CerviÃ±o, Dr. Centeleghe) Summer term 2012 Dr. CerviÃ±o, Dr. Centeleghe Seminar SS SS2012 Dr. CerviÃ±o, Dr. Centeleghe Seminar Automorphic Forms and representations of GL2 (Dr. CerviÃ±o, Dr. Centeleghe) ss2012-seminar-automorphic-forms-and-representations-of-g .md","url":"/teaching/?q=Seminar+Automorphic+Forms+and+representations+of+GL2+%28Dr.+Cervi%C3%B1o%2C+Dr.+Centeleghe%29","category":"teaching","description":"Seminar Automorphic Forms and representations of GL2 (Dr. CerviÃ±o, Dr. Centeleghe)","tags":"","semester":"Summer term 2012","instructor":"Dr. CerviÃ±o, Dr. Centeleghe","course_type":"Seminar","semester_year":2012,"semester_key":"SS2012"},{"id":"teaching-Algebraische Geometrie 2 (Prof. Dr. BÃ¶ckle)","title":"Algebraische Geometrie 2 (Prof. Dr. BÃ¶ckle)","content":"Algebraische Geometrie 2 (Prof. Dr. BÃ¶ckle)   Algebraische Geometrie 2 (Prof. Dr. BÃ¶ckle) Summer term 2013 Prof. Dr. BÃ¶ckle Seminar SS SS2013 Prof. Dr. BÃ¶ckle Algebraische Geometrie 2 (Prof. Dr. BÃ¶ckle) {\"label\"=>\"Algebraische Geometrie 2\", \"url\"=>\"http://elearning2.uni-heidelberg.de/course/view.php?id=1026\"} ss2013-algebraische-geometrie-2-prof-dr-bckle .md","url":"/teaching/?q=Algebraische+Geometrie+2+%28Prof.+Dr.+B%C3%B6ckle%29","category":"teaching","description":"Algebraische Geometrie 2 (Prof. Dr. BÃ¶ckle)","tags":"","semester":"Summer term 2013","instructor":"Prof. Dr. BÃ¶ckle","course_type":"Seminar","semester_year":2013,"semester_key":"SS2013"},{"id":"teaching-Exercise sessions for Lineare Algebra 2 (Dr. Maurischat)","title":"Exercise sessions for Lineare Algebra 2 (Dr. Maurischat)","content":"Exercise sessions for \"Lineare Algebra 2\" (Dr. Maurischat)   Exercise sessions for Lineare Algebra 2 (Dr. Maurischat) Summer term 2013 Dr. Maurischat Ãbung SS SS2013 Dr. Maurischat Exercise sessions for Lineare Algebra 2 (Dr. Maurischat) {\"label\"=>\"Lineare Algebra 2\", \"url\"=>\"http://www.iwr.uni-heidelberg.de/groups/arith-geom/maurischat/la2-ss2013/index.html\"} ss2013-exercise-sessions-for-lineare-algebra-2-dr-maurisc .md","url":"/teaching/?q=Exercise+sessions+for+Lineare+Algebra+2+%28Dr.+Maurischat%29","category":"teaching","description":"Exercise sessions for Lineare Algebra 2 (Dr. Maurischat)","tags":"","semester":"Summer term 2013","instructor":"Dr. Maurischat","course_type":"Ãbung","semester_year":2013,"semester_key":"SS2013"},{"id":"teaching-Group cohomology (Dr. CerviÃ±o)","title":"Group cohomology (Dr. CerviÃ±o)","content":"Group cohomology (Dr. CerviÃ±o)   Group cohomology (Dr. CerviÃ±o) Summer term 2013 Dr. CerviÃ±o Seminar SS SS2013 Dr. CerviÃ±o Group cohomology (Dr. CerviÃ±o) {\"label\"=>\"Group cohomology\", \"url\"=>\"http://www.rzuser.uni-heidelberg.de/~f25/kvv/ss2013/k-3.htm\"} ss2013-group-cohomology-dr-cervio .md","url":"/teaching/?q=Group+cohomology+%28Dr.+Cervi%C3%B1o%29","category":"teaching","description":"Group cohomology (Dr. CerviÃ±o)","tags":"","semester":"Summer term 2013","instructor":"Dr. CerviÃ±o","course_type":"Seminar","semester_year":2013,"semester_key":"SS2013"},{"id":"teaching-Seminar Torische VarietÃ¤ten (Prof. Dr. BÃ¶ckle)","title":"Seminar Torische VarietÃ¤ten (Prof. Dr. BÃ¶ckle)","content":"Seminar \"Torische VarietÃ¤ten\" (Prof. Dr. BÃ¶ckle) HomeMembersResearchPublicationsTeachingLinksContactInterna --> Uni Heidelberg > IWR > ARITHGEO > &nbsp;Members >&nbsp;Seminar on Toric Varieties [english]&nbsp;|&nbsp;[] &nbsp;Seminar \"Torische VarietÃ¤ten\" im Sommersemester 2013 Prof. Dr. Gebhard BÃ¶ckle, Konrad Fischer &nbsp;Ziel: Das Seminar wird Torische VarietÃ¤ten nach dem Buch von W. Fulton behandeln. Eine AnkÃ¼ndigung findet sich hier. Die detaillierte Vortragsliste ist hier zu finden. Zeit &amp; Ort: Dienstag 14-16Uhr in Raum 248, INF 368 Das Seminar startet erst in der 3. Woche des Semesters!Voraussetzungen: Algebraische Geometrie 1 Literatur: William Fulton - Introduction to Toric Varieties, Ann. of Math. Studies, PUC, 1993 Cox, Little, Schenck - Toric Varieties, Vol 124 AMS Graduate Studies &nbsp;Wenn Sie Interesse an einem Vortrag haben, schreiben Sie bitte Konrad Fischer eine Email.NummerDatum&nbsp;&nbsp; SprecherTitel130. AprilYujia QiuCones27. MaiYujia QiuAffine toric varieties314. MaiDamian GvirtzQuotient singularities421. MaiDamian GvirtzCompactness528. MaiKonrad FischerResolution of singularities(1)64. Juni-Kein Treffen--Kein Treffen-711. JuniKonrad FischerToric actions &amp; orbits818. Juni-Kein Treffen-925. JuniMax DanielDivisors and line bundles102. JuliMax DanielDivisors and line bundles 2119. Juli-Kein Treffen-1216. JuliBrandon WilliamsCohomology of line bundles1323. JuliBrandon WilliamsSerre Duality ( 13)&nbsp;(1) Additional material to this talk and the next can be found here and here. &nbsp;arithgeo@iwr.uni-heidelberg.deLast Update:&nbsp;25.10.2021 - 15:13 &copy; Copyright Universit&auml;t Heidelberg.&nbsp;Impressum.   Seminar Torische VarietÃ¤ten (Prof. Dr. BÃ¶ckle) Summer term 2013 Prof. Dr. BÃ¶ckle Seminar SS SS2013 Prof. Dr. BÃ¶ckle Seminar Torische VarietÃ¤ten (Prof. Dr. BÃ¶ckle) ss2013-seminar-torische-varietten-prof-dr-bckle .md","url":"/teaching/?q=Seminar+Torische+Variet%C3%A4ten+%28Prof.+Dr.+B%C3%B6ckle%29","category":"teaching","description":"Seminar Torische VarietÃ¤ten (Prof. Dr. BÃ¶ckle)","tags":"","semester":"Summer term 2013","instructor":"Prof. Dr. BÃ¶ckle","course_type":"Seminar","semester_year":2013,"semester_key":"SS2013"},{"id":"teaching-Seminar Trianguline Representations (Prof. Dr. BÃ¶ckle)","title":"Seminar Trianguline Representations (Prof. Dr. BÃ¶ckle)","content":"Seminar \"Trianguline Representations\" (Prof. Dr. BÃ¶ckle)   Seminar Trianguline Representations (Prof. Dr. BÃ¶ckle) Summer term 2013 Prof. Dr. BÃ¶ckle Seminar SS SS2013 Prof. Dr. BÃ¶ckle Seminar Trianguline Representations (Prof. Dr. BÃ¶ckle) ss2013-seminar-trianguline-representations-prof-dr-bckle .md","url":"/teaching/?q=Seminar+Trianguline+Representations+%28Prof.+Dr.+B%C3%B6ckle%29","category":"teaching","description":"Seminar Trianguline Representations (Prof. Dr. BÃ¶ckle)","tags":"","semester":"Summer term 2013","instructor":"Prof. Dr. BÃ¶ckle","course_type":"Seminar","semester_year":2013,"semester_key":"SS2013"},{"id":"teaching-Hauptseminar Arithmetik von Zahl- und FunktionenkÃ¶rpern: Shimura Varieties(Prof. Dr. BÃ¶ckle, Dr. CerviÃ±o, Fischer)","title":"Hauptseminar Arithmetik von Zahl- und FunktionenkÃ¶rpern: Shimura Varieties(Prof. Dr. BÃ¶ckle, Dr. CerviÃ±o, Fischer)","content":"Hauptseminar \"Arithmetik von Zahl- und FunktionenkÃ¶rpern: \"Shimura Varieties\"(Prof. Dr. BÃ¶ckle, Dr. CerviÃ±o, Fischer) --- Content from https://lsf.uni-heidelberg.de/qisserver/rds?state=verpublish&amp;status=init&amp;vmfile=no&amp;publishid=179737&amp;moduleCall=webInfo&amp;publishConfFile=webInfo&amp;publishSubDir=veranstaltung --- Zur Seitennavigation oder mit Tastenkombination fÃ¼r den accesskey-Taste und Taste 1&nbsp; Zum Seiteninhalt oder mit Tastenkombination fÃ¼r den accesskey und Taste 2&nbsp; &nbsp;&nbsp;&nbsp;&nbsp;&nbsp;&nbsp;&nbsp;&nbsp;&nbsp;&nbsp;&nbsp;&nbsp; LSF: Lehre, Studium und Forschung &nbsp;&nbsp;&nbsp;Informationssystem der Universit&auml;t Heidelberg Startseite &nbsp;&nbsp; Anmelden &nbsp;&nbsp; &nbsp; &nbsp;&nbsp;&nbsp;&nbsp; Veranstaltungen &nbsp;&nbsp;&nbsp;&nbsp; Einrichtungen &nbsp;&nbsp;&nbsp;&nbsp; RÃ¤ume und GebÃ¤ude &nbsp;&nbsp;&nbsp;&nbsp; Personen &nbsp;&nbsp;&nbsp;&nbsp; WiSe 2024/25 Sie sind hier: Hinweis Die angeforderte Auswertung ist zur Zeit nicht verfÃ¼gbar. Problembericht IncorrectObject-001 &nbsp;&nbsp; [TomcatLSF-C (histom17)] Â© Copyright UniversitÃ¤t Heidelberg&nbsp;|&nbsp;Kontakt / Impressum&nbsp;|&nbsp;DatenschutzerklÃ¤rung Zur&uuml;ck   Hauptseminar Arithmetik von Zahl- und FunktionenkÃ¶rpern: Shimura Varieties(Prof. Dr. BÃ¶ckle, Dr. CerviÃ±o, Fischer) Summer term 2014 Prof. Dr. BÃ¶ckle, Dr. CerviÃ±o, Fischer Seminar SS SS2014 Prof. Dr. BÃ¶ckle, Dr. CerviÃ±o, Fischer Hauptseminar Arithmetik von Zahl- und FunktionenkÃ¶rpern: Shimura Varieties(Prof. Dr. BÃ¶ckle, Dr. CerviÃ±o, Fischer) {\"label\"=>\"Arithmetik von Zahl- und FunktionenkÃ¶rpern: Shimura Varieties\", \"url\"=>\"https://lsf.uni-heidelberg.de/qisserver/rds?state=verpublish&amp;status=init&amp;vmfile=no&amp;publishid=179737&amp;moduleCall=webInfo&amp;publishConfFile=webInfo&amp;publishSubDir=veranstaltung\"} ss2014-hauptseminar-arithmetik-von-zahl-und-funktionenkrp .md","url":"/teaching/?q=Hauptseminar+Arithmetik+von+Zahl-+und+Funktionenk%C3%B6rpern%3A+Shimura+Varieties%28Prof.+Dr.+B%C3%B6ckle%2C+Dr.+Cervi%C3%B1o%2C+Fischer%29","category":"teaching","description":"Hauptseminar Arithmetik von Zahl- und FunktionenkÃ¶rpern: Shimura Varieties(Prof. Dr. BÃ¶ckle, Dr. CerviÃ±o, Fischer)","tags":"","semester":"Summer term 2014","instructor":"Prof. Dr. BÃ¶ckle, Dr. CerviÃ±o, Fischer","course_type":"Seminar","semester_year":2014,"semester_key":"SS2014"},{"id":"teaching-Seminar p-adische Geometrie (Prof. Dr. BÃ¶ckle, Juschka, Qiu)","title":"Seminar p-adische Geometrie (Prof. Dr. BÃ¶ckle, Juschka, Qiu)","content":"Seminar \"p-adische Geometrie\" (Prof. Dr. BÃ¶ckle, Juschka, Qiu) HomeMembersResearchPublicationsTeachingLinksContactInterna --> Uni Heidelberg > IWR > ARITHGEO > &nbsp;Members >&nbsp;Seminar zur p-adischen Geometrie [english]&nbsp;|&nbsp;[] Seminar zur p-adischen Geometrie Prof. Dr. Gebhard BÃ¶ckle, Ann-Kristin Juschka und Yujia Qiu Termin und OrtSeminarprogrammVortrÃ¤geLiteraturAnkÃ¼ndigung und Vorbesprechung Termin und Ort Dienstags 14:15-15:45 Uhr&nbsp;im Sommersemester 2014 im Raum 220, INF 368. Beginn: 22.04.2014 Bitte tragt euch im MÃ¼sli ein, wenn ihr am Seminar teilnehmen mÃ¶chtet. Seminarprogramm Das vorlÃ¤ufige Seminarprogramm befindet sich hier. VortrÃ¤ge Bei Interesse oder Fragen zu den VortrÃ¤gen wendet euch bitte an Ann-Kristin Juschka&nbsp;oder Yujia Qiu. &nbsp;Dies ist die vorlÃ¤ufige Liste der VortrÃ¤ge:Teil I&nbsp;&nbsp; Tates Affinoide RÃ¤ume, die lokalen Bausteine rigid-analytischer RÃ¤ume1.Die Tatealgebra&nbsp;22.04.2014&nbsp;2.Die Ringtheorie der Tatealgebra&nbsp;29.04.2014&nbsp;3.Affinoide Algebren und die Spektralnorm&nbsp;06.05.2014&nbsp;4.Affinoide RÃ¤ume&nbsp;13.05.2014&nbsp;Teil II &nbsp; Konstruktion von rigid-analytischen RÃ¤umen5.Affinoide Unterberreiche eines affinoiden Raumes&nbsp;20.05.2014&nbsp;6.Der Tatesche AzyklizitÃ¤tssatz&nbsp;27.05.2014&nbsp;7.Grothendiecktopologien&nbsp;03.06.2014&nbsp;8.Tates rigide&nbsp;RÃ¤ume&nbsp;10.06.2014&nbsp;(9.)Quasi-kohÃ¤rente Garben, deren Kohomologie und Kiehls Theorem A und B&nbsp;17.06.2014&nbsp;Teil III &nbsp; &nbsp;Beispiele rigid-analytischer RÃ¤umen10.Der ResiduenkalkÃ¼l fÃ¼r Teilmengen&nbsp;des projektiven Raums&nbsp;24.06.2014&nbsp;11.Die Tate elliptische Kurve&nbsp;01.07.2014&nbsp;12.Die Drinfeldsche obere Halbebene und ihre Quotienten&nbsp;08.07.2014Teil IV&nbsp; &nbsp;Ausblicke auf eine Theorie von Berkovich13.k-affinoide Algebren&nbsp;15.07.201414.Berkovichs k-analytische RÃ¤ume&nbsp;22.07.2014&nbsp;Da die VortrÃ¤ge noch angepasst werden, kÃ¶nnen sich die jeweiligen Termine noch um 1-2 Wochen Ã¤ndern. Literatur Dies sind die Hauptquellen, denen wir im Seminar folgen werde   Seminar p-adische Geometrie (Prof. Dr. BÃ¶ckle, Juschka, Qiu) Summer term 2014 Prof. Dr. BÃ¶ckle, Juschka, Qiu Seminar SS SS2014 Prof. Dr. BÃ¶ckle, Juschka, Qiu Seminar p-adische Geometrie (Prof. Dr. BÃ¶ckle, Juschka, Qiu) ss2014-seminar-p-adische-geometrie-prof-dr-bckle-juschka- .md","url":"/teaching/?q=Seminar+p-adische+Geometrie+%28Prof.+Dr.+B%C3%B6ckle%2C+Juschka%2C+Qiu%29","category":"teaching","description":"Seminar p-adische Geometrie (Prof. Dr. BÃ¶ckle, Juschka, Qiu)","tags":"","semester":"Summer term 2014","instructor":"Prof. Dr. BÃ¶ckle, Juschka, Qiu","course_type":"Seminar","semester_year":2014,"semester_key":"SS2014"},{"id":"teaching-Spezialvorlesung Abelsche VarietÃ¤ten II (Prof. Dr. BÃ¶ckle, Dr. Centeleghe)","title":"Spezialvorlesung Abelsche VarietÃ¤ten II (Prof. Dr. BÃ¶ckle, Dr. Centeleghe)","content":"Spezialvorlesung \"Abelsche VarietÃ¤ten II\" (Prof. Dr. BÃ¶ckle, Dr. Centeleghe) --- Content from https://lsf.uni-heidelberg.de/qisserver/rds?state=verpublish&amp;status=init&amp;vmfile=no&amp;publishid=182263&amp;moduleCall=webInfo&amp;publishConfFile=webInfo&amp;publishSubDir=veranstaltung --- Zur Seitennavigation oder mit Tastenkombination fÃ¼r den accesskey-Taste und Taste 1&nbsp; Zum Seiteninhalt oder mit Tastenkombination fÃ¼r den accesskey und Taste 2&nbsp; &nbsp;&nbsp;&nbsp;&nbsp;&nbsp;&nbsp;&nbsp;&nbsp;&nbsp;&nbsp;&nbsp;&nbsp; LSF: Lehre, Studium und Forschung &nbsp;&nbsp;&nbsp;Informationssystem der Universit&auml;t Heidelberg Startseite &nbsp;&nbsp; Anmelden &nbsp;&nbsp; &nbsp; &nbsp;&nbsp;&nbsp;&nbsp; Veranstaltungen &nbsp;&nbsp;&nbsp;&nbsp; Einrichtungen &nbsp;&nbsp;&nbsp;&nbsp; RÃ¤ume und GebÃ¤ude &nbsp;&nbsp;&nbsp;&nbsp; Personen &nbsp;&nbsp;&nbsp;&nbsp; WiSe 2024/25 Sie sind hier: Hinweis Die angeforderte Auswertung ist zur Zeit nicht verfÃ¼gbar. Problembericht IncorrectObject-001 &nbsp;&nbsp; [TomcatLSF-B (histom18)] Â© Copyright UniversitÃ¤t Heidelberg&nbsp;|&nbsp;Kontakt / Impressum&nbsp;|&nbsp;DatenschutzerklÃ¤rung Zur&uuml;ck   Spezialvorlesung Abelsche VarietÃ¤ten II (Prof. Dr. BÃ¶ckle, Dr. Centeleghe) Summer term 2014 Prof. Dr. BÃ¶ckle, Dr. Centeleghe Vorlesung SS SS2014 Prof. Dr. BÃ¶ckle, Dr. Centeleghe Spezialvorlesung Abelsche VarietÃ¤ten II (Prof. Dr. BÃ¶ckle, Dr. Centeleghe) {\"label\"=>\"Abelsche VarietÃ¤ten II\", \"url\"=>\"https://lsf.uni-heidelberg.de/qisserver/rds?state=verpublish&amp;status=init&amp;vmfile=no&amp;publishid=182263&amp;moduleCall=webInfo&amp;publishConfFile=webInfo&amp;publishSubDir=veranstaltung\"} ss2014-spezialvorlesung-abelsche-varietten-ii-prof-dr-bck .md","url":"/teaching/?q=Spezialvorlesung+Abelsche+Variet%C3%A4ten+II+%28Prof.+Dr.+B%C3%B6ckle%2C+Dr.+Centeleghe%29","category":"teaching","description":"Spezialvorlesung Abelsche VarietÃ¤ten II (Prof. Dr. BÃ¶ckle, Dr. Centeleghe)","tags":"","semester":"Summer term 2014","instructor":"Prof. Dr. BÃ¶ckle, Dr. Centeleghe","course_type":"Vorlesung","semester_year":2014,"semester_key":"SS2014"},{"id":"teaching-Vorlesung Algebraische Gruppen (Prof. Dr. BÃ¶ckle)","title":"Vorlesung Algebraische Gruppen (Prof. Dr. BÃ¶ckle)","content":"Vorlesung \"Algebraische Gruppen (Prof. Dr. BÃ¶ckle) --- Content from https://lsf.uni-heidelberg.de/qisserver/rds?state=verpublish&amp;status=init&amp;vmfile=no&amp;publishid=182260&amp;moduleCall=webInfo&amp;publishConfFile=webInfo&amp;publishSubDir=veranstaltung --- Zur Seitennavigation oder mit Tastenkombination fÃ¼r den accesskey-Taste und Taste 1&nbsp; Zum Seiteninhalt oder mit Tastenkombination fÃ¼r den accesskey und Taste 2&nbsp; &nbsp;&nbsp;&nbsp;&nbsp;&nbsp;&nbsp;&nbsp;&nbsp;&nbsp;&nbsp;&nbsp;&nbsp; LSF: Lehre, Studium und Forschung &nbsp;&nbsp;&nbsp;Informationssystem der Universit&auml;t Heidelberg Startseite &nbsp;&nbsp; Anmelden &nbsp;&nbsp; &nbsp; &nbsp;&nbsp;&nbsp;&nbsp; Veranstaltungen &nbsp;&nbsp;&nbsp;&nbsp; Einrichtungen &nbsp;&nbsp;&nbsp;&nbsp; RÃ¤ume und GebÃ¤ude &nbsp;&nbsp;&nbsp;&nbsp; Personen &nbsp;&nbsp;&nbsp;&nbsp; WiSe 2024/25 Sie sind hier: Hinweis Die angeforderte Auswertung ist zur Zeit nicht verfÃ¼gbar. Problembericht IncorrectObject-001 &nbsp;&nbsp; [TomcatLSF-A (histom17)] Â© Copyright UniversitÃ¤t Heidelberg&nbsp;|&nbsp;Kontakt / Impressum&nbsp;|&nbsp;DatenschutzerklÃ¤rung Zur&uuml;ck   Vorlesung Algebraische Gruppen (Prof. Dr. BÃ¶ckle) Summer term 2014 Prof. Dr. BÃ¶ckle Vorlesung SS SS2014 Prof. Dr. BÃ¶ckle Vorlesung Algebraische Gruppen (Prof. Dr. BÃ¶ckle) {\"label\"=>\"Algebraische Gruppen (Prof. Dr. BÃ¶ckle)\", \"url\"=>\"https://lsf.uni-heidelberg.de/qisserver/rds?state=verpublish&amp;status=init&amp;vmfile=no&amp;publishid=182260&amp;moduleCall=webInfo&amp;publishConfFile=webInfo&amp;publishSubDir=veranstaltung\"} ss2014-vorlesung-algebraische-gruppen-prof-dr-bckle .md","url":"/teaching/?q=Vorlesung+Algebraische+Gruppen+%28Prof.+Dr.+B%C3%B6ckle%29","category":"teaching","description":"Vorlesung Algebraische Gruppen (Prof. Dr. BÃ¶ckle)","tags":"","semester":"Summer term 2014","instructor":"Prof. Dr. BÃ¶ckle","course_type":"Vorlesung","semester_year":2014,"semester_key":"SS2014"},{"id":"teaching-Hauptseminar Arithmetik von Zahl- und FunktionenkÃ¶rpern: Lenny TaelmanÂ´s body of work on Drinfeld modules (Prof. Dr. BÃ¶ckle, Dr. Perkins, Dr. Hubschmid)","title":"Hauptseminar Arithmetik von Zahl- und FunktionenkÃ¶rpern: Lenny TaelmanÂ´s body of work on Drinfeld modules (Prof. Dr. BÃ¶ckle, Dr. Perkins, Dr. Hubschmid)","content":"Hauptseminar Arithmetik von Zahl- und FunktionenkÃ¶rpern: \"Lenny TaelmanÂ´s body of work on Drinfeld modules\" (Prof. Dr. BÃ¶ckle, Dr. Perkins, Dr. Hubschmid)   Hauptseminar Arithmetik von Zahl- und FunktionenkÃ¶rpern: Lenny TaelmanÂ´s body of work on Drinfeld modules (Prof. Dr. BÃ¶ckle, Dr. Perkins, Dr. Hubschmid) Summer term 2015 Prof. Dr. BÃ¶ckle, Dr. Perkins, Dr. Hubschmid Seminar SS SS2015 Prof. Dr. BÃ¶ckle, Dr. Perkins, Dr. Hubschmid Hauptseminar Arithmetik von Zahl- und FunktionenkÃ¶rpern: Lenny TaelmanÂ´s body of work on Drinfeld modules (Prof. Dr. BÃ¶ckle, Dr. Perkins, Dr. Hubschmid) ss2015-hauptseminar-arithmetik-von-zahl-und-funktionenkrp .md","url":"/teaching/?q=Hauptseminar+Arithmetik+von+Zahl-+und+Funktionenk%C3%B6rpern%3A+Lenny+Taelman%C2%B4s+body+of+work+on+Drinfeld+modules+%28Prof.+Dr.+B%C3%B6ckle%2C+Dr.+Perkins%2C+Dr.+Hubschmid%29","category":"teaching","description":"Hauptseminar Arithmetik von Zahl- und FunktionenkÃ¶rpern: Lenny TaelmanÂ´s body of work on Drinfeld modules (Prof. Dr. BÃ¶ckle, Dr. Perkins, Dr. Hubschmid)","tags":"","semester":"Summer term 2015","instructor":"Prof. Dr. BÃ¶ckle, Dr. Perkins, Dr. Hubschmid","course_type":"Seminar","semester_year":2015,"semester_key":"SS2015"},{"id":"teaching-Seminar Darstellungstheorie (Prof. Dr. BÃ¶ckle, Qiu), Seminardetails","title":"Seminar Darstellungstheorie (Prof. Dr. BÃ¶ckle, Qiu), Seminardetails","content":"Seminar \"Darstellungstheorie\" (Prof. Dr. BÃ¶ckle, Qiu), Seminardetails --- Content from https://lsf.uni-heidelberg.de/qisserver/rds?state=verpublish&amp;status=init&amp;vmfile=no&amp;moduleCall=webInfo&amp;publishConfFile=webInfo&amp;publishSubDir=veranstaltung&amp;veranstaltung.veranstid=204926 --- Zur Seitennavigation oder mit Tastenkombination fÃ¼r den accesskey-Taste und Taste 1&nbsp; Zum Seiteninhalt oder mit Tastenkombination fÃ¼r den accesskey und Taste 2&nbsp; &nbsp;&nbsp;&nbsp;&nbsp;&nbsp;&nbsp;&nbsp;&nbsp;&nbsp;&nbsp;&nbsp;&nbsp; LSF: Lehre, Studium und Forschung &nbsp;&nbsp;&nbsp;Informationssystem der Universit&auml;t Heidelberg Startseite &nbsp;&nbsp; Anmelden &nbsp;&nbsp; &nbsp; &nbsp;&nbsp;&nbsp;&nbsp; Veranstaltungen &nbsp;&nbsp;&nbsp;&nbsp; Einrichtungen &nbsp;&nbsp;&nbsp;&nbsp; RÃ¤ume und GebÃ¤ude &nbsp;&nbsp;&nbsp;&nbsp; Personen &nbsp;&nbsp;&nbsp;&nbsp; WiSe 2024/25 Sie sind hier: Hinweis Die angeforderte Auswertung ist zur Zeit nicht verfÃ¼gbar. Problembericht IncorrectObject-001 &nbsp;&nbsp; [TomcatLSF-B (histom18)] Â© Copyright UniversitÃ¤t Heidelberg&nbsp;|&nbsp;Kontakt / Impressum&nbsp;|&nbsp;DatenschutzerklÃ¤rung Zur&uuml;ck   Seminar Darstellungstheorie (Prof. Dr. BÃ¶ckle, Qiu), Seminardetails Summer term 2015 Prof. Dr. BÃ¶ckle, Qiu Seminar SS SS2015 Prof. Dr. BÃ¶ckle, Qiu Seminar Darstellungstheorie (Prof. Dr. BÃ¶ckle, Qiu), Seminardetails {\"label\"=>\"Darstellungstheorie\", \"url\"=>\"https://lsf.uni-heidelberg.de/qisserver/rds?state=verpublish&amp;status=init&amp;vmfile=no&amp;moduleCall=webInfo&amp;publishConfFile=webInfo&amp;publishSubDir=veranstaltung&amp;veranstaltung.veranstid=204926\"} {\"label\"=>\"Seminardetails\", \"url\"=>\"http://www1.iwr.uni-heidelberg.de/groups/arith-geom/home/members/yujia-qiu/dar-ss2015/\"} ss2015-seminar-darstellungstheorie-prof-dr-bckle-qiu-semi .md","url":"/teaching/?q=Seminar+Darstellungstheorie+%28Prof.+Dr.+B%C3%B6ckle%2C+Qiu%29%2C+Seminardetails","category":"teaching","description":"Seminar Darstellungstheorie (Prof. Dr. BÃ¶ckle, Qiu), Seminardetails","tags":"","semester":"Summer term 2015","instructor":"Prof. Dr. BÃ¶ckle, Qiu","course_type":"Seminar","semester_year":2015,"semester_key":"SS2015"},{"id":"teaching-Vorlesung Bruhat-Tits GebÃ¤ude (Prof. Dr. BÃ¶ckle), Modulbeschreibung","title":"Vorlesung Bruhat-Tits GebÃ¤ude (Prof. Dr. BÃ¶ckle), Modulbeschreibung","content":"Vorlesung \"Bruhat-Tits GebÃ¤ude\" (Prof. Dr. BÃ¶ckle), Modulbeschreibung   Vorlesung Bruhat-Tits GebÃ¤ude (Prof. Dr. BÃ¶ckle), Modulbeschreibung Summer term 2015 Prof. Dr. BÃ¶ckle Vorlesung SS SS2015 Prof. Dr. BÃ¶ckle Vorlesung Bruhat-Tits GebÃ¤ude (Prof. Dr. BÃ¶ckle), Modulbeschreibung {\"label\"=>\"Bruhat-Tits GebÃ¤ude\", \"url\"=>\"http://lsf.uni-heidelberg.de/qisserver/rds?state=verpublish&amp;status=init&amp;vmfile=no&amp;publishid=204923&amp;moduleCall=webInfo&amp;publishConfFile=webInfo&amp;publishSubDir=veranstaltung\"} ss2015-vorlesung-bruhat-tits-gebude-prof-dr-bckle-modulbe .md","url":"/teaching/?q=Vorlesung+Bruhat-Tits+Geb%C3%A4ude+%28Prof.+Dr.+B%C3%B6ckle%29%2C+Modulbeschreibung","category":"teaching","description":"Vorlesung Bruhat-Tits GebÃ¤ude (Prof. Dr. BÃ¶ckle), Modulbeschreibung","tags":"","semester":"Summer term 2015","instructor":"Prof. Dr. BÃ¶ckle","course_type":"Vorlesung","semester_year":2015,"semester_key":"SS2015"},{"id":"teaching-Vorlesung Darstellungen und Invarianten 2 (Dr. CerviÃ±o), Modulbeschreibung","title":"Vorlesung Darstellungen und Invarianten 2 (Dr. CerviÃ±o), Modulbeschreibung","content":"Vorlesung \"Darstellungen und Invarianten 2\" (Dr.Â CerviÃ±o), Modulbeschreibung --- Content from https://lsf.uni-heidelberg.de/qisserver/rds?state=verpublish&amp;status=init&amp;vmfile=no&amp;publishid=204925&amp;moduleCall=webInfo&amp;publishConfFile=webInfo&amp;publishSubDir=veranstaltung --- Zur Seitennavigation oder mit Tastenkombination fÃ¼r den accesskey-Taste und Taste 1&nbsp; Zum Seiteninhalt oder mit Tastenkombination fÃ¼r den accesskey und Taste 2&nbsp; &nbsp;&nbsp;&nbsp;&nbsp;&nbsp;&nbsp;&nbsp;&nbsp;&nbsp;&nbsp;&nbsp;&nbsp; LSF: Lehre, Studium und Forschung &nbsp;&nbsp;&nbsp;Informationssystem der Universit&auml;t Heidelberg Startseite &nbsp;&nbsp; Anmelden &nbsp;&nbsp; &nbsp; &nbsp;&nbsp;&nbsp;&nbsp; Veranstaltungen &nbsp;&nbsp;&nbsp;&nbsp; Einrichtungen &nbsp;&nbsp;&nbsp;&nbsp; RÃ¤ume und GebÃ¤ude &nbsp;&nbsp;&nbsp;&nbsp; Personen &nbsp;&nbsp;&nbsp;&nbsp; WiSe 2024/25 Sie sind hier: Hinweis Die angeforderte Auswertung ist zur Zeit nicht verfÃ¼gbar. Problembericht IncorrectObject-001 &nbsp;&nbsp; [TomcatLSF-C (histom19)] Â© Copyright UniversitÃ¤t Heidelberg&nbsp;|&nbsp;Kontakt / Impressum&nbsp;|&nbsp;DatenschutzerklÃ¤rung Zur&uuml;ck   Vorlesung Darstellungen und Invarianten 2 (Dr. CerviÃ±o), Modulbeschreibung Summer term 2015 Dr.Â CerviÃ±o Vorlesung SS SS2015 Dr.Â CerviÃ±o Vorlesung Darstellungen und Invarianten 2 (Dr. CerviÃ±o), Modulbeschreibung {\"label\"=>\"Darstellungen und Invarianten 2\", \"url\"=>\"https://lsf.uni-heidelberg.de/qisserver/rds?state=verpublish&amp;status=init&amp;vmfile=no&amp;publishid=204925&amp;moduleCall=webInfo&amp;publishConfFile=webInfo&amp;publishSubDir=veranstaltung\"} ss2015-vorlesung-darstellungen-und-invarianten-2-dr-cervi .md","url":"/teaching/?q=Vorlesung+Darstellungen+und+Invarianten+2+%28Dr.+Cervi%C3%B1o%29%2C+Modulbeschreibung","category":"teaching","description":"Vorlesung Darstellungen und Invarianten 2 (Dr. CerviÃ±o), Modulbeschreibung","tags":"","semester":"Summer term 2015","instructor":"Dr.Â CerviÃ±o","course_type":"Vorlesung","semester_year":2015,"semester_key":"SS2015"},{"id":"teaching-Hauptseminar Arithmetik von Zahl- und FunktionenkÃ¶rpern: p-adic Uniformization (Prof. Dr. BÃ¶ckle, Dr. Guiraud, Fischer, GrÃ¤f), Seminardetails","title":"Hauptseminar Arithmetik von Zahl- und FunktionenkÃ¶rpern: p-adic Uniformization (Prof. Dr. BÃ¶ckle, Dr. Guiraud, Fischer, GrÃ¤f), Seminardetails","content":"Hauptseminar Arithmetik von Zahl- und FunktionenkÃ¶rpern: \"p-adic Uniformization\" (Prof. Dr. BÃ¶ckle, Dr. Guiraud, Fischer, GrÃ¤f), Seminardetails HomeMembersResearchPublicationsTeachingLinksContactInterna --> Uni Heidelberg > IWR > ARITHGEO > &nbsp;Members >&nbsp;p-adic Uniformization SS16 [english]&nbsp;|&nbsp;[] Working group seminar: p-adic Uniformization Topic of the research seminar in summer 2016 is 'p-adic uniformization of Shimura curves'. &nbsp;The seminar meets every friday, 9am in Seminar room 3 of the Mathematikon, starting 22nd of April. &nbsp;The program with details to each talk can be found here: Program &nbsp;arithgeo@iwr.uni-heidelberg.deLast Update:&nbsp;25.10.2021 - 15:13 &copy; Copyright Universit&auml;t Heidelberg.&nbsp;Impressum.   Hauptseminar Arithmetik von Zahl- und FunktionenkÃ¶rpern: p-adic Uniformization (Prof. Dr. BÃ¶ckle, Dr. Guiraud, Fischer, GrÃ¤f), Seminardetails Summer term 2016 Prof. Dr. BÃ¶ckle, Dr. Guiraud, Fischer, GrÃ¤f Seminar SS SS2016 Prof. Dr. BÃ¶ckle, Dr. Guiraud, Fischer, GrÃ¤f Hauptseminar Arithmetik von Zahl- und FunktionenkÃ¶rpern: p-adic Uniformization (Prof. Dr. BÃ¶ckle, Dr. Guiraud, Fischer, GrÃ¤f), Seminardetails ss2016-hauptseminar-arithmetik-von-zahl-und-funktionenkrp .md","url":"/teaching/?q=Hauptseminar+Arithmetik+von+Zahl-+und+Funktionenk%C3%B6rpern%3A+p-adic+Uniformization+%28Prof.+Dr.+B%C3%B6ckle%2C+Dr.+Guiraud%2C+Fischer%2C+Gr%C3%A4f%29%2C+Seminardetails","category":"teaching","description":"Hauptseminar Arithmetik von Zahl- und FunktionenkÃ¶rpern: p-adic Uniformization (Prof. Dr. BÃ¶ckle, Dr. Guiraud, Fischer, GrÃ¤f), Seminardetails","tags":"","semester":"Summer term 2016","instructor":"Prof. Dr. BÃ¶ckle, Dr. Guiraud, Fischer, GrÃ¤f","course_type":"Seminar","semester_year":2016,"semester_key":"SS2016"},{"id":"teaching-Proseminar p-adische Analysis (Prof. Dr. BÃ¶ckle, GrÃ¤f), Seminardetails","title":"Proseminar p-adische Analysis (Prof. Dr. BÃ¶ckle, GrÃ¤f), Seminardetails","content":"Proseminar \"p-adische Analysis\" (Prof. Dr. BÃ¶ckle, GrÃ¤f), Seminardetails HomeMembersResearchPublicationsTeachingLinksContactInterna --> Uni Heidelberg > IWR > ARITHGEO > &nbsp;Members >&nbsp;p-adische Analysis [english]&nbsp;|&nbsp;[] Proseminar p-adische Analysis Prof. Dr. Gebhard BÃ¶ckle, Peter GrÃ¤f Termin und OrtAnkÃ¼ndigung und VorbesprechungSeminarprogrammVortrÃ¤geLiteratur Termin und Ort Dienstag 14.00 Uhr - 16.00 Uhr&nbsp;im Sommersemester 2016 im Seminarraum 3 in INF 205 (Mathematikon) Beginn: 19.04.2016 Bitte zusÃ¤tzlich im MÃSLI eintragen. AnkÃ¼ndigung und Vorbesprechung Die PDF-Version der AnkÃ¼ndigung findet sich hier. Die Vorbesprechung zum Proseminar ist am Dienstag, den 09.02.2016 um 11.00 Uhr c.t. in HS2, INF 288. Dort werden auch die Vortragsthemen vergeben. Seminarprogramm Das Seminarprogramm findet sich hier. VortrÃ¤ge Bei Interesse oder Fragen zu den VortrÃ¤gen wenden Sie sich bitte an Peter GrÃ¤f. &nbsp;Dies ist die Liste der VortrÃ¤ge: Teil I&nbsp;&nbsp; Die p-adischen Zahlen1.AbsolutbetrÃ¤ge auf KÃ¶rpern19.04.20162.Ultrametrische Topologie und Bewertungsringe26.04.20163.Der Satz von Ostrowski und die Produktformel03.05.20164.Die Konstruktion von Q p17.05.20165.Grundlegende Eigenschaften von Q p24.05.20166.Das Henselsche Lemma31.05.20167.Lokal-Global-Prinzipien07.06.2016Teil II &nbsp; p-adische Analysis8.Elementare Analysis in Q p14.06.20169.Potenzreihen I21.06.201610.Potenzreihen II28.06.201611.Der p-adische Logarithmus und die p-adische Exponentialfunktion05.07.201612.GleichmÃ¤Ãig stetige Funktionen12.07.201613.Interpolationsreihen19.07.201614.Die p-adische Gammafunktion26.07.2016 Literatur Dies sind die Hauptquellen, denen wir im Proseminar folgen werden: Gouvea, F.: p-adic Numbers: An Introduction (1997).&nbsp;Katok, S.: p-adic Analysis Compared with Real (2007).Koblitz, N.: p-adic Numbers, p-adic Analysis and Zeta-Functions (1984). &nbsp;arithgeo@iwr.uni-heidelberg.deLast Update:&nbsp;25.10.2021 - 15:14 &copy; Copyright Universit&auml;t Heidelberg.&nbsp;Impressum.   Proseminar p-adische Analysis (Prof. Dr. BÃ¶ckle, GrÃ¤f), Seminardetails Summer term 2016 Prof. Dr. BÃ¶ckle, GrÃ¤f Seminar SS SS2016 Prof. Dr. BÃ¶ckle, GrÃ¤f Proseminar p-adische Analysis (Prof. Dr. BÃ¶ckle, GrÃ¤f), Seminardetails ss2016-proseminar-p-adische-analysis-prof-dr-bckle-grf-se .md","url":"/teaching/?q=Proseminar+p-adische+Analysis+%28Prof.+Dr.+B%C3%B6ckle%2C+Gr%C3%A4f%29%2C+Seminardetails","category":"teaching","description":"Proseminar p-adische Analysis (Prof. Dr. BÃ¶ckle, GrÃ¤f), Seminardetails","tags":"","semester":"Summer term 2016","instructor":"Prof. Dr. BÃ¶ckle, GrÃ¤f","course_type":"Seminar","semester_year":2016,"semester_key":"SS2016"},{"id":"teaching-Vorlesung Lineare Algebra 2 (Prof. Dr. BÃ¶ckle), Modulbeschreibung","title":"Vorlesung Lineare Algebra 2 (Prof. Dr. BÃ¶ckle), Modulbeschreibung","content":"Vorlesung \"Lineare Algebra 2\" (Prof. Dr. BÃ¶ckle), Modulbeschreibung   Vorlesung Lineare Algebra 2 (Prof. Dr. BÃ¶ckle), Modulbeschreibung Summer term 2016 Prof. Dr. BÃ¶ckle Vorlesung SS SS2016 Prof. Dr. BÃ¶ckle Vorlesung Lineare Algebra 2 (Prof. Dr. BÃ¶ckle), Modulbeschreibung {\"label\"=>\"Lineare Algebra 2\", \"url\"=>\"http://www1.iwr.uni-heidelberg.de/groups/arith-geom/LA2-SS2016/LA2_index.html\"} ss2016-vorlesung-lineare-algebra-2-prof-dr-bckle-modulbes .md","url":"/teaching/?q=Vorlesung+Lineare+Algebra+2+%28Prof.+Dr.+B%C3%B6ckle%29%2C+Modulbeschreibung","category":"teaching","description":"Vorlesung Lineare Algebra 2 (Prof. Dr. BÃ¶ckle), Modulbeschreibung","tags":"","semester":"Summer term 2016","instructor":"Prof. Dr. BÃ¶ckle","course_type":"Vorlesung","semester_year":2016,"semester_key":"SS2016"},{"id":"teaching-Vorlesung Algebra 2 (Dr. Malte Witte, K. Fischer),","title":"Vorlesung Algebra 2 (Dr. Malte Witte, K. Fischer),","content":"Vorlesung \"Algebra 2\" (Dr. Malte Witte, K. Fischer), HomeMembersResearchPublicationsTeachingLinksContactInterna --> Uni Heidelberg > IWR > ARITHGEO > &nbsp;Members >&nbsp;Algebra 2 [english]&nbsp;|&nbsp;[] &nbsp;Algebra 2 im Sommersemester 2017Dozent: Dr. Malte WitteAssistent: Konrad Fischer &nbsp;Termine:Mittwoch 11-13h, SR C (INF 205)Freitag 9-11h, SR C (INF 205)Themenauswahl: Noethersche und Artinsche Ringe, Spektrum, Algebren, Tensorprodukt, Komplettierungen, abelsche Kategorien, homologische Algebra, Ext/Tor FÃ¼r weitere Informationen sei auf das Modulhandbuch verwiesen. &nbsp;Literaturempfehlungen: M. Atiyah, I. MacDonald: Introduction to Commutative Algebra D. Eisenbud: Commutative Algebra H. Matsumura: Commutative Ring Theory &nbsp;Erster Vorlesungstermin ist in der Woche nach Ostern (19.4.)Sobald der Dozent Ihnen das Passwort mitgeteilt hat, kÃ¶nnen Sie sich im elearning-Portal Moodle2 der UniversitÃ¤t fÃ¼r den Kurs eintragen. Dort werden Fragen beantwortet und weitere Materialien zur VerfÃ¼gung gestellt. Ãbungsbetrieb und PrÃ¼fung:Der Ãbungsgruppenleiter ist Alvaro Troya. Bitte melden Sie sich in MÃ¼sli fÃ¼r seine Ãbungsgruppe an. Die Ãbungsaufgaben kommen jeden Freitag in Moodle online und mÃ¼ssen bis 9:15 Uhr am Freitag der darauffolgenden Woche abgegeben werden. Der Zettelkasten ist im ersten Stock (INF 205). Zum Bestehen des Moduls \"Algebra 2\" muss eine der beiden Klausur bestanden werden. Voraussetzung zur Klausurzulassung ist regelmÃ¤Ãige Teilnahme an den Tutorien und erfolgreiche Bearbeitung der ÃbungsblÃ¤tter. Zur erfolgreiche Bearbeitung ist das Erreichen von 50% der mÃ¶glichen Ãbungspunkte (ohne Zusatzaufgaben) hinreichend. Doppelabgabe wird empfohlen. Es wird auch eine NachprÃ¼fung angeboten, die je nach Teilnehmerzahl als mÃ¼ndliche PrÃ¼fung stattfinden kann. Zur NachprÃ¼fung ist zugelassen, wer zur HauptprÃ¼fung zugelassen war, aber verhindert war oder nicht bestanden hat. Wichtig: Eine Klausuranmeldung ist nicht nÃ¶tig. Wer sich bis 14 Tage vor dem Klausurtermin nicht aus der Vorlesung abgemeldet hat, gilt als a   Vorlesung Algebra 2 (Dr. Malte Witte, K. Fischer), Summer term 2017 Dr. Malte Witte, K. Fischer Vorlesung SS SS2017 Dr. Malte Witte, K. Fischer Vorlesung Algebra 2 (Dr. Malte Witte, K. Fischer), ss2017-vorlesung-algebra-2-dr-malte-witte-k-fischer .md","url":"/teaching/?q=Vorlesung+Algebra+2+%28Dr.+Malte+Witte%2C+K.+Fischer%29%2C","category":"teaching","description":"Vorlesung Algebra 2 (Dr. Malte Witte, K. Fischer),","tags":"","semester":"Summer term 2017","instructor":"Dr. Malte Witte, K. Fischer","course_type":"Vorlesung","semester_year":2017,"semester_key":"SS2017"},{"id":"teaching-Hauptseminar Arithmetik von Zahl- und FunktionenkÃ¶rpern (Prof. Dr. BÃ¶ckle, Dr. Maurischat, Gazda)","title":"Hauptseminar Arithmetik von Zahl- und FunktionenkÃ¶rpern (Prof. Dr. BÃ¶ckle, Dr. Maurischat, Gazda)","content":"Hauptseminar Arithmetik von Zahl- und FunktionenkÃ¶rpern (Prof. Dr. BÃ¶ckle, Dr. Maurischat, Gazda) HomeMembersResearchPublicationsTeachingLinksContactInterna --> Uni Heidelberg > IWR > ARITHGEO > &nbsp;Members >&nbsp;Hauptseminar SS2018 [english]&nbsp;|&nbsp;[] Hauptseminar \"Arithmetik von Zahl- und FunktionenkÃ¶rpern\" (SS 2018)&nbsp; Topic: Shtuka cohomology and special values of Goss L-functions We meet thursdays 9-11 in Seminarraum 2. The first talk will take place on April 19. Seminar program &nbsp;arithgeo@iwr.uni-heidelberg.deLast Update:&nbsp;25.10.2021 - 15:08 &copy; Copyright Universit&auml;t Heidelberg.&nbsp;Impressum.   Hauptseminar Arithmetik von Zahl- und FunktionenkÃ¶rpern (Prof. Dr. BÃ¶ckle, Dr. Maurischat, Gazda) Summer term 2018 Prof. Dr. BÃ¶ckle, Dr. Maurischat, Gazda Seminar SS SS2018 Prof. Dr. BÃ¶ckle, Dr. Maurischat, Gazda Hauptseminar Arithmetik von Zahl- und FunktionenkÃ¶rpern (Prof. Dr. BÃ¶ckle, Dr. Maurischat, Gazda) ss2018-hauptseminar-arithmetik-von-zahl-und-funktionenkrp .md","url":"/teaching/?q=Hauptseminar+Arithmetik+von+Zahl-+und+Funktionenk%C3%B6rpern+%28Prof.+Dr.+B%C3%B6ckle%2C+Dr.+Maurischat%2C+Gazda%29","category":"teaching","description":"Hauptseminar Arithmetik von Zahl- und FunktionenkÃ¶rpern (Prof. Dr. BÃ¶ckle, Dr. Maurischat, Gazda)","tags":"","semester":"Summer term 2018","instructor":"Prof. Dr. BÃ¶ckle, Dr. Maurischat, Gazda","course_type":"Seminar","semester_year":2018,"semester_key":"SS2018"},{"id":"teaching-Seminar Lokale KlassenkÃ¶rpertheorie nach Lubin-Tate (Prof. Dr. BÃ¶ckle, Fischer),","title":"Seminar Lokale KlassenkÃ¶rpertheorie nach Lubin-Tate (Prof. Dr. BÃ¶ckle, Fischer),","content":"Seminar \"Lokale KlassenkÃ¶rpertheorie nach Lubin-Tate\" (Prof. Dr. BÃ¶ckle, Fischer), HomeMembersResearchPublicationsTeachingLinksContactInterna --> Uni Heidelberg > IWR > ARITHGEO > &nbsp;Members >&nbsp;Seminar Lubin-Tate Theorie [english]&nbsp;|&nbsp;[] &nbsp;Seminar \"Lubin-Tate Theorie\" im Sommersemester 2018 Prof. Dr. Gebhard BÃ¶ckle, Konrad Fischer &nbsp;Ziel: Das Seminar wird die Konstruktion lokaler KlassenkÃ¶rpertheorie mittels formaler Gruppen behandeln. &nbsp; Eine AnkÃ¼ndigung findet sich hier. Die detaillierte Vortragsliste gibt es hier: Programm. Zeit &amp; Ort: voraussichtlich Dienstag 14-16 Uhr; in EinzelfÃ¤llen auch mit DoppelvortrÃ¤gen bis 18 Uhr; Raumnummer wird noch bekannt gegeben. Erwartete Vorkenntnisse: Lokale KÃ¶rper und unendliche Galois-Theorie werden zu Beginn kurz wiederholt. Vorkenntnisse sind hier hilfreich. Anmeldung: Bitte melden Sie sich in MÃ¼sli an. Literatur: Hauptquelle: T. Yoshida - Skript \"Local class field theory via Lubin-Tate theory\" online Vorbesprechung: Wenn Sie Interesse an einem Vortrag haben, kommen Sie bitte zur Vorbesprechung am 6.2. um 14 c.t Uhr in SR 7 oder schreiben Sie Konrad Fischer eine Email. &nbsp;arithgeo@iwr.uni-heidelberg.deLast Update:&nbsp;25.10.2021 - 15:12 &copy; Copyright Universit&auml;t Heidelberg.&nbsp;Impressum.   Seminar Lokale KlassenkÃ¶rpertheorie nach Lubin-Tate (Prof. Dr. BÃ¶ckle, Fischer), Summer term 2018 Prof. Dr. BÃ¶ckle, Fischer Seminar SS SS2018 Prof. Dr. BÃ¶ckle, Fischer Seminar Lokale KlassenkÃ¶rpertheorie nach Lubin-Tate (Prof. Dr. BÃ¶ckle, Fischer), ss2018-seminar-lokale-klassenkrpertheorie-nach-lubin-tate .md","url":"/teaching/?q=Seminar+Lokale+Klassenk%C3%B6rpertheorie+nach+Lubin-Tate+%28Prof.+Dr.+B%C3%B6ckle%2C+Fischer%29%2C","category":"teaching","description":"Seminar Lokale KlassenkÃ¶rpertheorie nach Lubin-Tate (Prof. Dr. BÃ¶ckle, Fischer),","tags":"","semester":"Summer term 2018","instructor":"Prof. Dr. BÃ¶ckle, Fischer","course_type":"Seminar","semester_year":2018,"semester_key":"SS2018"},{"id":"teaching-Vorlesung Algebraische Zahlentheorie 2 (Prof. Dr. BÃ¶ckle, Dr. Conti),","title":"Vorlesung Algebraische Zahlentheorie 2 (Prof. Dr. BÃ¶ckle, Dr. Conti),","content":"Vorlesung \"Algebraische Zahlentheorie 2\" (Prof. Dr. BÃ¶ckle, Dr. Conti), HomeMembersResearchPublicationsTeachingLinksContactInterna --> Uni Heidelberg > IWR > ARITHGEO > &nbsp;Members >&nbsp;Algebraische Zahlentheorie 2 [english]&nbsp;|&nbsp;[] Vorlesung &quot;Algebraische Zahlentheorie 2&quot; (SS 2018) Dozent: Prof. Dr. Gebhard BÃ¶ckle Assistent: Dr. Andrea Conti &nbsp;Vorlesungen:Dienstags 11-13 Uhr, Seminarraum 4 Freitags 9-11 Uhr, Seminarraum 4 &nbsp;Sprechstunde:(Andrea Conti) Donnerstags 15:30-16:30, INF 205 / Raum 3/225 &nbsp;Ãbungen:Dienstags 16-18 Uhr, Seminarraum Statistik &nbsp;Die PrÃ¼fung wird am Dienstag, 31. Juli stattfinden. Eine ausreichende Beteiligung an der Ãbungen ist notwendig, um an der PrÃ¼fung teilzunehmen. &nbsp;Empfohlene Vorkenntnisse: Algebraische Zahlentheorie 1Literatur:R. Sharifi, Algebraic Number Theory, lecture notesG.J. Janusz, Algebraic Number Fields, Graduate Studies in Mathematics 7, AMS Publishing&nbsp;ÃbungsblÃ¤tter:Ãbungsblatt 1 (Besprechung: Di 24.04.2018) Ãbungsblatt 2 (Corrected version: the original statement of exercise 5 contained a mistake, as one should exclude the places above \\ell; Besprechung: Di 08.05.2018) Ãbungsblatt 3 (Besprechung: Di 15.05.2018) Ãbungsblatt 4 (The starred exercises are optional; Besprechung: Di 22.05.2018) Ãbungsblatt 5 (Corrected version: in the original introduction a condition was missing from the definition of extension of G by a G-module A; Besprechung: Di 29.05.2018) Ãbungsblatt 6 (Besprechung: Di 05.06.2018) Ãbungsblatt 7 (Besprechung: Di 12.06.2018) Ãbungsblatt 8 (Besprechung: Di 19.06.2018) Ãbungsblatt 9 (Besprechung: Di 26.06.2018) Ãbungsblatt 10-11 (Besprechung: Fr 13.07 und Di 17.07.2018) Ãbungsblatt 12 (Nicht in der Pruefung; Besprechung: Di 24.06.2018) &nbsp;arithgeo@iwr.uni-heidelberg.deLast Update:&nbsp;25.10.2021 - 15:06 &copy; Copyright Universit&auml;t Heidelberg.&nbsp;Impressum.   Vorlesung Algebraische Zahlentheorie 2 (Prof. Dr. BÃ¶ckle, Dr. Conti), Summer term 2018 Prof. Dr. BÃ¶ckle, Dr. Conti Vorlesung SS SS2018 Prof. Dr. BÃ¶ckle, Dr. Conti Vorlesung Algebraische Zahlentheorie 2 (Prof. Dr. BÃ¶ckle, Dr. Conti), ss2018-vorlesung-algebraische-zahlentheorie-2-prof-dr-bck .md","url":"/teaching/?q=Vorlesung+Algebraische+Zahlentheorie+2+%28Prof.+Dr.+B%C3%B6ckle%2C+Dr.+Conti%29%2C","category":"teaching","description":"Vorlesung Algebraische Zahlentheorie 2 (Prof. Dr. BÃ¶ckle, Dr. Conti),","tags":"","semester":"Summer term 2018","instructor":"Prof. Dr. BÃ¶ckle, Dr. Conti","course_type":"Vorlesung","semester_year":2018,"semester_key":"SS2018"},{"id":"teaching-Vorlesung Galois representations and their deformations (Dr. Conti),","title":"Vorlesung Galois representations and their deformations (Dr. Conti),","content":"Vorlesung \"Galois representations and their deformations\" (Dr. Conti), HomeMembersResearchPublicationsTeachingLinksContactInterna --> Uni Heidelberg > IWR > ARITHGEO > &nbsp;Members >&nbsp;Galois representations and their deformations [english]&nbsp;|&nbsp;[] Vorlesung &quot;Galois representations and their deformations&quot; (SS 2018) Dozent: Dr. Andrea Conti Die Hauptwebseite fÃ¼r die Vorlesung ist hier. Hier ist der Course Outline. &nbsp;Vorlesungen: Mittwochs 14-16 Uhr, Seminarraum 11 &nbsp;Sprechstunde: Donnerstags 15:30-16:30, INF 205 / Raum 3/225 &nbsp;Empfohlene Vorkenntnisse: Algebraische Zahlentheorie 1Literatur:F. GoÃ»vea, Lecture notes for the course \"Deformations of Galois Representations\", PDFA. M\u0013ezard, Lecture notes for the course \"D\u0013eformations de repr\u0013esentations galoisiennes\", in French, PDFG. BÃ¶ckle, Lecture notes for the course \"Deformations of Galois Representations\", PDFB. Mazur, \"Deforming Galois representations\", in \"Galois groups over Q\", M.S.R.I. Publications. Springer-Verlag, 1989, PDF &nbsp;arithgeo@iwr.uni-heidelberg.deLast Update:&nbsp;25.10.2021 - 15:05 &copy; Copyright Universit&auml;t Heidelberg.&nbsp;Impressum.   Vorlesung Galois representations and their deformations (Dr. Conti), Summer term 2018 Dr. Conti Vorlesung SS SS2018 Dr. Conti Vorlesung Galois representations and their deformations (Dr. Conti), ss2018-vorlesung-galois-representations-and-their-deforma .md","url":"/teaching/?q=Vorlesung+Galois+representations+and+their+deformations+%28Dr.+Conti%29%2C","category":"teaching","description":"Vorlesung Galois representations and their deformations (Dr. Conti),","tags":"","semester":"Summer term 2018","instructor":"Dr. Conti","course_type":"Vorlesung","semester_year":2018,"semester_key":"SS2018"},{"id":"teaching-Hauptseminar Arithmetik von Zahl- und FunktionenkÃ¶rpern (Prof. Dr. BÃ¶ckle, Dr. Ludwig)","title":"Hauptseminar Arithmetik von Zahl- und FunktionenkÃ¶rpern (Prof. Dr. BÃ¶ckle, Dr. Ludwig)","content":"HauptseminarÂ Arithmetik von Zahl- und FunktionenkÃ¶rpernÂ (Prof. Dr. BÃ¶ckle, Dr. Ludwig)   Hauptseminar Arithmetik von Zahl- und FunktionenkÃ¶rpern (Prof. Dr. BÃ¶ckle, Dr. Ludwig) Summer term 2019 Prof. Dr. BÃ¶ckle, Dr. Ludwig Seminar SS SS2019 Prof. Dr. BÃ¶ckle, Dr. Ludwig Hauptseminar Arithmetik von Zahl- und FunktionenkÃ¶rpern (Prof. Dr. BÃ¶ckle, Dr. Ludwig) ss2019-hauptseminar-arithmetik-von-zahl-und-funktionenkrp .md","url":"/teaching/?q=Hauptseminar+Arithmetik+von+Zahl-+und+Funktionenk%C3%B6rpern+%28Prof.+Dr.+B%C3%B6ckle%2C+Dr.+Ludwig%29","category":"teaching","description":"Hauptseminar Arithmetik von Zahl- und FunktionenkÃ¶rpern (Prof. Dr. BÃ¶ckle, Dr. Ludwig)","tags":"","semester":"Summer term 2019","instructor":"Prof. Dr. BÃ¶ckle, Dr. Ludwig","course_type":"Seminar","semester_year":2019,"semester_key":"SS2019"},{"id":"teaching-Proseminar Bilinearformen und klassische Gruppen (Prof. Dr. BÃ¶ckle, Quast)","title":"Proseminar Bilinearformen und klassische Gruppen (Prof. Dr. BÃ¶ckle, Quast)","content":"Proseminar \"Bilinearformen und klassische Gruppen\" (Prof. Dr. BÃ¶ckle, Quast) Uni Heidelberg > IWR > ARITHGEO > &nbsp;Members >&nbsp;Proseminar Bilinearformen und Klassische Gruppen   Proseminar Bilinearformen und klassische Gruppen (Prof. Dr. BÃ¶ckle, Quast) Summer term 2019 Prof. Dr. BÃ¶ckle, Quast Seminar SS SS2019 Prof. Dr. BÃ¶ckle, Quast Proseminar Bilinearformen und klassische Gruppen (Prof. Dr. BÃ¶ckle, Quast) ss2019-proseminar-bilinearformen-und-klassische-gruppen-p .md","url":"/teaching/?q=Proseminar+Bilinearformen+und+klassische+Gruppen+%28Prof.+Dr.+B%C3%B6ckle%2C+Quast%29","category":"teaching","description":"Proseminar Bilinearformen und klassische Gruppen (Prof. Dr. BÃ¶ckle, Quast)","tags":"","semester":"Summer term 2019","instructor":"Prof. Dr. BÃ¶ckle, Quast","course_type":"Seminar","semester_year":2019,"semester_key":"SS2019"},{"id":"teaching-Vorlesung Kompatible Systeme von Galoisdarstellungen (Prof. Dr. BÃ¶ckle, Dr. Conti)","title":"Vorlesung Kompatible Systeme von Galoisdarstellungen (Prof. Dr. BÃ¶ckle, Dr. Conti)","content":"Vorlesung \"Kompatible Systeme von Galoisdarstellungen\" (Prof. Dr. BÃ¶ckle, Dr. Conti) HomeMembersResearchPublicationsTeachingLinksContactInterna --> Uni Heidelberg > IWR > ARITHGEO > &nbsp;Members >&nbsp;Kompatible Systeme von Galoisdarstellungen [english]&nbsp;|&nbsp;[] Vorlesung &quot;Kompatible Systeme von Galoisdarstellungen&quot; (SS 2018) Dozent: Prof. Dr. Gebhard BÃ¶ckleAssistent: Dr. Andrea Conti&nbsp;Hier ist die VorlesungsankÃ¼ndigung.&nbsp;Vorlesungen:Dienstags 11-13 Uhr, Seminarraum 4Donnerstags 9-11 Uhr, Seminarraum 4&nbsp;Ãbungen:Dienstags 16-18 Uhr, Seminarraum 2&nbsp;Sprechstunde: nach Vereinbarung&nbsp;Empfohlene Vorkenntnisse: Algebraische Zahlentheorie 1, Algebraische Geometrie&nbsp;Literatur:Elliptische Kurven: Silverman, Arithmetic of Elliptic CurvesAlgebraische Geometrie: Hartshorne, Algebraic Geometry - GÃ¶rtz-Wedhorn, Algebraic Geometry ITannakakategorien: Simental, Notes on Tannakian Categories - Deligne, CatÃ©gories Tannakiennes (in The Grothendieck Festschrift, Vol. II) - Deligne, Tannakian Categories (LNM 900)&nbsp;Die ÃbungsblÃ¤tter finden Sie im Moodle. &nbsp;arithgeo@iwr.uni-heidelberg.deLast Update:&nbsp;25.10.2021 - 15:06 &copy; Copyright Universit&auml;t Heidelberg.&nbsp;Impressum.   Vorlesung Kompatible Systeme von Galoisdarstellungen (Prof. Dr. BÃ¶ckle, Dr. Conti) Summer term 2019 Prof. Dr. BÃ¶ckle, Dr. Conti Vorlesung SS SS2019 Prof. Dr. BÃ¶ckle, Dr. Conti Vorlesung Kompatible Systeme von Galoisdarstellungen (Prof. Dr. BÃ¶ckle, Dr. Conti) ss2019-vorlesung-kompatible-systeme-von-galoisdarstellung .md","url":"/teaching/?q=Vorlesung+Kompatible+Systeme+von+Galoisdarstellungen+%28Prof.+Dr.+B%C3%B6ckle%2C+Dr.+Conti%29","category":"teaching","description":"Vorlesung Kompatible Systeme von Galoisdarstellungen (Prof. Dr. BÃ¶ckle, Dr. Conti)","tags":"","semester":"Summer term 2019","instructor":"Prof. Dr. BÃ¶ckle, Dr. Conti","course_type":"Vorlesung","semester_year":2019,"semester_key":"SS2019"},{"id":"teaching-Vorlesung p-divisible Gruppen (Dr. Ludwig)","title":"Vorlesung p-divisible Gruppen (Dr. Ludwig)","content":"Vorlesung \"p-divisible Gruppen\" (Dr. Ludwig)   Vorlesung p-divisible Gruppen (Dr. Ludwig) Summer term 2019 Dr. Ludwig Vorlesung SS SS2019 Dr. Ludwig Vorlesung p-divisible Gruppen (Dr. Ludwig) ss2019-vorlesung-p-divisible-gruppen-dr-ludwig .md","url":"/teaching/?q=Vorlesung+p-divisible+Gruppen+%28Dr.+Ludwig%29","category":"teaching","description":"Vorlesung p-divisible Gruppen (Dr. Ludwig)","tags":"","semester":"Summer term 2019","instructor":"Dr. Ludwig","course_type":"Vorlesung","semester_year":2019,"semester_key":"SS2019"},{"id":"teaching-Vorlesung Adische RÃ¤ume II (Dr. Ludwig)","title":"Vorlesung Adische RÃ¤ume II (Dr. Ludwig)","content":"Vorlesung \"Adische RÃ¤ume II\" (Dr. Ludwig) HomeMembersResearchPublicationsTeachingLinksContactInterna --> Uni Heidelberg > IWR > ARITHGEO > &nbsp;Members >&nbsp;AdischeRaeumeII [english]&nbsp;|&nbsp;[] Vorlesung Adische RÃ¤ume II (Sommersemester 2020) Dozent: Dr. Judith Ludwig&nbsp;Beginn: 21.04.20Die Vorlesung startet als digitaler Kurs in Moodle. Immer dienstags zwischen 14-16 Uhr findet eine Webex-Sitzung statt um das Skript zu diskutieren, Ãbungen zu besprechen und Fragen zu beantworten. Zur besseren Organisation bitte ich alle Interessenten sich bald mÃ¶glichst im MÃ¼sli in die Vorlesung einzutragen oder sich per E-Mail an mich zu wenden.&nbsp; &nbsp; Kursinhalt: Die Vorlesung fÃ¼hrt die Vorlesung von Prof. Venjakob aus dem Wintersemester fort. Es werden zunÃ¤chst weitere Grundlagen der Theorie der adischen RÃ¤ume entwickelt, z.B. wichtige Eigenschaften von Morphismen studiert und grundlegende Konzepte wie z.B. Faserprodukte diskutiert. Ziel des Kurses ist dann eine moderne Entwicklung der sogenannten EigenvarietÃ¤ten-Maschine. Mit dieser Maschine kann man die Spektraltheorie eines kompakten Operators auf einer Familie von nicht-archimedischen BanachrÃ¤umen geometrisch verstehen. Um sie zu konstruieren werden wir auch einen Einblick in die p-adische Funktionalanalysis bekommen. Die EigenvarietÃ¤ten-Maschine wird in der Praxis mit RÃ¤umen von p-adischen Modulformen gefÃ¼ttert und produziert einen adischen Raum, die sogenannte EigenvarietÃ¤t, welcher Eigenwerte von interessanten Operatoren (sogenannte Hecke-Operatoren) auf diesen RÃ¤umen parametrisiert. Die Maschine kann aber ohne Kenntnisse Ã¼ber Modulformen gebaut werden, insbesondere werden solche Kenntnisse nicht vorausgesetzt. &nbsp;Erforderliche Vorkenntnisse: Inhalt der Vorlesung Adische RÃ¤ume I. &nbsp;Literatur:zu adischen RÃ¤umen:[Hu] Roland Huber, Ãtale Cohomology of Rigid Analytic Varieties and Adic Spaces, Aspects of Math., E30, Vieweg, 1996.[Hu1] Roland Huber, Continuous valuations, Math. Zeitschrift 212, pp 445-477, 1993.&nbsp;[Hu2] Roland Huber, A general   Vorlesung Adische RÃ¤ume II (Dr. Ludwig) Summer term 2020 Dr. Ludwig Vorlesung SS SS2020 Dr. Ludwig Vorlesung Adische RÃ¤ume II (Dr. Ludwig) ss2020-vorlesung-adische-rume-ii-dr-ludwig .md","url":"/teaching/?q=Vorlesung+Adische+R%C3%A4ume+II+%28Dr.+Ludwig%29","category":"teaching","description":"Vorlesung Adische RÃ¤ume II (Dr. Ludwig)","tags":"","semester":"Summer term 2020","instructor":"Dr. Ludwig","course_type":"Vorlesung","semester_year":2020,"semester_key":"SS2020"},{"id":"teaching-Vorlesung Algebra 2 (Prof. Dr. BÃ¶ckle, Quast)","title":"Vorlesung Algebra 2 (Prof. Dr. BÃ¶ckle, Quast)","content":"Vorlesung \"Algebra 2\" (Prof. Dr. BÃ¶ckle, Quast) Algebra 2 Sommersemester 2020 Organisation Dozent: Prof. Dr. Gebhard B&ouml;ckle Assistent: Julian Quast Vorlesung Dienstag 09-11 Uhr in INF 205 / SR B Donnerstag 09-11 Uhr in INF 205 / SR B Erste Vorlesung: 21.04.2020, asynchron via Moodle Plenar&uuml;bung Dozent: Dr. Judith Ludwig Mo 14-16 Uhr in INF 205 (Mathematikon) / HS Erste Plenar&uuml;bung: 21.10.2019 --> &Uuml;bungsbetrieb Organisation &uuml;ber M&Uuml;SLI. Bitte dort anmelden. Donnerstag 16-18 Uhr in INF 205 / SR 3, zur Zeit nur online Freitag 11-13 Uhr in INF 205 / SR 3, zur Zeit nur online Erste &Uuml;bungen: 23.04. bzw. 24.04.2020   Vorlesung Algebra 2 (Prof. Dr. BÃ¶ckle, Quast) Summer term 2020 Prof. Dr. BÃ¶ckle, Quast Vorlesung SS SS2020 Prof. Dr. BÃ¶ckle, Quast Vorlesung Algebra 2 (Prof. Dr. BÃ¶ckle, Quast) ss2020-vorlesung-algebra-2-prof-dr-bckle-quast .md","url":"/teaching/?q=Vorlesung+Algebra+2+%28Prof.+Dr.+B%C3%B6ckle%2C+Quast%29","category":"teaching","description":"Vorlesung Algebra 2 (Prof. Dr. BÃ¶ckle, Quast)","tags":"","semester":"Summer term 2020","instructor":"Prof. Dr. BÃ¶ckle, Quast","course_type":"Vorlesung","semester_year":2020,"semester_key":"SS2020"},{"id":"teaching-Hauptseminar Arithmetik von Zahl- und FunktionenkÃ¶rpern: Higher Hida Theory (Dr. GrÃ¤f, Dr. Ludwig)","title":"Hauptseminar Arithmetik von Zahl- und FunktionenkÃ¶rpern: Higher Hida Theory (Dr. GrÃ¤f, Dr. Ludwig)","content":"Hauptseminar Arithmetik von Zahl- und FunktionenkÃ¶rpern: \"Higher Hida Theory\" (Dr. GrÃ¤f, Dr. Ludwig)   Hauptseminar Arithmetik von Zahl- und FunktionenkÃ¶rpern: Higher Hida Theory (Dr. GrÃ¤f, Dr. Ludwig) Summer term 2021 Dr. GrÃ¤f, Dr. Ludwig Seminar SS SS2021 Dr. GrÃ¤f, Dr. Ludwig Hauptseminar Arithmetik von Zahl- und FunktionenkÃ¶rpern: Higher Hida Theory (Dr. GrÃ¤f, Dr. Ludwig) ss2021-hauptseminar-arithmetik-von-zahl-und-funktionenkrp .md","url":"/teaching/?q=Hauptseminar+Arithmetik+von+Zahl-+und+Funktionenk%C3%B6rpern%3A+Higher+Hida+Theory+%28Dr.+Gr%C3%A4f%2C+Dr.+Ludwig%29","category":"teaching","description":"Hauptseminar Arithmetik von Zahl- und FunktionenkÃ¶rpern: Higher Hida Theory (Dr. GrÃ¤f, Dr. Ludwig)","tags":"","semester":"Summer term 2021","instructor":"Dr. GrÃ¤f, Dr. Ludwig","course_type":"Seminar","semester_year":2021,"semester_key":"SS2021"},{"id":"teaching-Seminar Derivierte Kategorien und Algebraische Geometrie (Prof. Dr. BÃ¶ckle, Dr. Ludwig)","title":"Seminar Derivierte Kategorien und Algebraische Geometrie (Prof. Dr. BÃ¶ckle, Dr. Ludwig)","content":"Seminar \"Derivierte Kategorien und Algebraische Geometrie\" (Prof. Dr. BÃ¶ckle, Dr. Ludwig) HomeMembersResearchPublicationsTeachingLinksContactInterna --> Uni Heidelberg > IWR > ARITHGEO > &nbsp;Members >&nbsp;deriviertekategorien [english]&nbsp;|&nbsp;[] Seminar Derivierte Kategorien und Algebraische Geometrie (SoSe 2021) Dozent: Prof. Dr. BÃ¶ckle, Dr. Judith Ludwig&nbsp;Beginn: 13.04.21Zeit: Dienstags 14-16 UhrFormat: Online, via Webex.Zur besseren Organisation bitten wir alle Interessenten sich bald mÃ¶glichst im MÃ¼sli in die Sammelgruppe des Seminars einzutragen oder sich per E-Mail an Dr. Ludwig zu wenden. Am 22.02. um 10:00 Uhr (s.t.) wird es online eine Vorbesprechung geben, die Koordinaten werden Ã¼ber die MÃ¼sli-Gruppe bekannt gegeben. Thema: Das Seminar bietet eine EinfÃ¼hrung in das Thema Derivierte Kategorien mit Anwendungen in der Algebraischen Geometrie. Derivierte Kategorien sind ein wichtiges Konzept der modernen Mathematik, genauer der Kategorientheorie. EingefÃ¼hrt von Grothendieck und Verdier in den 60er Jahren fanden sie zunÃ¤chst in der algebraischen Geometrie ihre Anwendung. Mittlerweile sind sie aber auch in vielen anderen Bereichen der Mathematik, beispielsweise der Darstellungstheorie oder der Homotopietheorie, sowie in der mathematischen Physik zu finden. In diesem Seminar lernen wir das Konzept der Derivierten Kategorie einer abelschen Kategorie kennen. Unser Ziel ist es zunÃ¤chst den abstrakten Formalismus zu erlernen und anschlieÃend in einem konkreten Beispiel aus der algebraischen Geometrie anzuwenden. Genauer wollen wir die derivierte Kategorie der Kategorie der kohÃ¤renten Garben auf einer glatten projektiven VarietÃ¤t verstehen. Diese bildet eine wichtige Invariante der VarietÃ¤t und wir werden unter anderem studieren inwieweit die derivierte Kategorie die VarietÃ¤t schon festlegt. &nbsp; ProgrammTipps fÃ¼r gute SeminarvortrÃ¤ge &nbsp;Erforlderliche Vorkenntnisse: FÃ¼r den ersten Teil sollten Sie Grundkenntnisse der Kategorientheorie haben und etwas homologische Algebra kennen. FÃ¼r den zweiten Teil sollten Sie bereits Grundlagen der Alge   Seminar Derivierte Kategorien und Algebraische Geometrie (Prof. Dr. BÃ¶ckle, Dr. Ludwig) Summer term 2021 Prof. Dr. BÃ¶ckle, Dr. Ludwig Seminar SS SS2021 Prof. Dr. BÃ¶ckle, Dr. Ludwig Seminar Derivierte Kategorien und Algebraische Geometrie (Prof. Dr. BÃ¶ckle, Dr. Ludwig) ss2021-seminar-derivierte-kategorien-und-algebraische-geo .md","url":"/teaching/?q=Seminar+Derivierte+Kategorien+und+Algebraische+Geometrie+%28Prof.+Dr.+B%C3%B6ckle%2C+Dr.+Ludwig%29","category":"teaching","description":"Seminar Derivierte Kategorien und Algebraische Geometrie (Prof. Dr. BÃ¶ckle, Dr. Ludwig)","tags":"","semester":"Summer term 2021","instructor":"Prof. Dr. BÃ¶ckle, Dr. Ludwig","course_type":"Seminar","semester_year":2021,"semester_key":"SS2021"},{"id":"teaching-Vorlesung Algebraische Geometrie 2 (Prof. Dr. BÃ¶ckle, Chilla, Quast)","title":"Vorlesung Algebraische Geometrie 2 (Prof. Dr. BÃ¶ckle, Chilla, Quast)","content":"Vorlesung \"Algebraische Geometrie 2\" (Prof. Dr. BÃ¶ckle, Chilla, Quast) Algebraische Geometrie 2 Sommersemester 2021 Organisation Dozent: Prof. Dr. Gebhard B&ouml;ckle Assistent: Paola Chilla, Julian Quast Vorlesung Dienstag 09-11 Uhr asynchron via Moodle Donnerstag 11-13 Uhr asynchron via Moodle Erste Vorlesung: Dienstag, den 13.04.2021, asynchron via Moodle Sprechstunde Wir bieten zus&auml;tzlich zur Vorlesung eine synchrone Sprechstunde an. Hier k&ouml;nnten uneingeschr&auml;nkt Fragen zum gesamten Vorlesungsstoff gestellt werden. Donnerstag 12:00-13:00 Uhr synchron via Heiconf &Uuml;bungsbetrieb Organisation &uuml;ber M&Uuml;SLI. Bitte dort anmelden. Montag 14:00-16:00 Uhr, synchron via Webex Mittwoch 14:15-15:45 Uhr synchron via Webex --> Erste &Uuml;bung: Montag, den 19.04.2021   Vorlesung Algebraische Geometrie 2 (Prof. Dr. BÃ¶ckle, Chilla, Quast) Summer term 2021 Prof. Dr. BÃ¶ckle, Chilla, Quast Vorlesung SS SS2021 Prof. Dr. BÃ¶ckle, Chilla, Quast Vorlesung Algebraische Geometrie 2 (Prof. Dr. BÃ¶ckle, Chilla, Quast) ss2021-vorlesung-algebraische-geometrie-2-prof-dr-bckle-c .md","url":"/teaching/?q=Vorlesung+Algebraische+Geometrie+2+%28Prof.+Dr.+B%C3%B6ckle%2C+Chilla%2C+Quast%29","category":"teaching","description":"Vorlesung Algebraische Geometrie 2 (Prof. Dr. BÃ¶ckle, Chilla, Quast)","tags":"","semester":"Summer term 2021","instructor":"Prof. Dr. BÃ¶ckle, Chilla, Quast","course_type":"Vorlesung","semester_year":2021,"semester_key":"SS2021"},{"id":"teaching-Proseminar Prime numbers and Cryptography (Dr. Banwait, C. V. Sriram)","title":"Proseminar Prime numbers and Cryptography (Dr. Banwait, C. V. Sriram)","content":"Proseminar \"Prime numbers and Cryptography\" (Dr. Banwait, C. V. Sriram) HomeMembersResearchPublicationsTeachingLinksContactInterna --> Uni Heidelberg > IWR > ARITHGEO > &nbsp;Members >&nbsp;deriviertekategorien [english]&nbsp;|&nbsp;[] Prime numbers and cryptography (Proseminar/Seminar SS 2022) Dozent: Dr. Barinder Banwait, C. V. Sriram&nbsp;Termine: April 11-14 2022Wo: SR8 and onlineFormat: Block SeminarAnnouncement: click hereProgram: click hereVorbesprechung slides: click here Thema:This seminar will develop some of the theory that lies behind these real-world applications, via a hands-on, algorithmic approach: Fast arithmetic in Z/nZ, complexity analysis, and probabilistic methods will be treated along with the number field sieve, a technique arising from algebraic number theory. The analogues of these in the elliptic curve setting will also be seen.See the course announcement and program (linked above) for more information.&nbsp; &nbsp;TalksGrey indicates that the talk is also suitable for a Seminar talk.TitleSpeakerDateTimeHandoutPrime numbers and Complexity analysisEtienne Stock11.4.202209:15click hereFast arithmetic I : Fourier Transform AlgorithmsJonas HÃ¶cht11.4.202211:00click herePseudoprimes and the Miller-Rabin testPhilipp Nazari11.4.202214:15click hereThe Theorem of Agrawal-Kayal-Saxena ICarola Behr12.4.202209:15click hereThe Theorem of Agrawal-Kayal-Saxena IISaif Mandour12.4.202211:00click hereBrief overview of Algebraic number theoryVincent Zahlen12.4.202214:15click hereFactorisation III - The number field sieveC. V. Sriram12.4.202216:00click hereBrief overview of elliptic curvesMarcel Eichberg13.4.202209:15click herePublic-key cryptographyAkin Yilmaz13.4.202211:00click hereLenstra's elliptic curve method and elliptic curve primality provingMona Scheerer14.4.202209:15click herePost-quantum cryptography, and the Supersingular Isogeny Diffie-Hellman protocolB. S. Banwait14.4.202211:00click here&nbsp; &nbsp;arithgeo@iwr.uni-heidelberg.deLast Update:&nbsp;13.04.2022 - 22:52 &copy; Copyright Universit&auml;t Heidelberg.&nbsp;I   Proseminar Prime numbers and Cryptography (Dr. Banwait, C. V. Sriram) Summer term 2022 Dr. Banwait, C. V. Sriram Seminar SS SS2022 Dr. Banwait, C. V. Sriram Proseminar Prime numbers and Cryptography (Dr. Banwait, C. V. Sriram) ss2022-proseminar-prime-numbers-and-cryptography-dr-banwa .md","url":"/teaching/?q=Proseminar+Prime+numbers+and+Cryptography+%28Dr.+Banwait%2C+C.+V.+Sriram%29","category":"teaching","description":"Proseminar Prime numbers and Cryptography (Dr. Banwait, C. V. Sriram)","tags":"","semester":"Summer term 2022","instructor":"Dr. Banwait, C. V. Sriram","course_type":"Seminar","semester_year":2022,"semester_key":"SS2022"},{"id":"teaching-Hauptseminar Arithmetik von Zahl- und FunktionenkÃ¶rpern: Vectorial Drinfeld modular forms over Tate algebras (Prof. Dr. BÃ¶ckle, Dr. GezmiÅ)","title":"Hauptseminar Arithmetik von Zahl- und FunktionenkÃ¶rpern: Vectorial Drinfeld modular forms over Tate algebras (Prof. Dr. BÃ¶ckle, Dr. GezmiÅ)","content":"Hauptseminar Arithmetik von Zahl- und FunktionenkÃ¶rpern: \"Vectorial Drinfeld modular forms over Tate algebras\" (Prof. Dr. BÃ¶ckle, Dr. GezmiÅ)   Hauptseminar Arithmetik von Zahl- und FunktionenkÃ¶rpern: Vectorial Drinfeld modular forms over Tate algebras (Prof. Dr. BÃ¶ckle, Dr. GezmiÅ) Summer term 2023 Prof. Dr. BÃ¶ckle, Dr. GezmiÅ Seminar SS SS2023 Prof. Dr. BÃ¶ckle, Dr. GezmiÅ Hauptseminar Arithmetik von Zahl- und FunktionenkÃ¶rpern: Vectorial Drinfeld modular forms over Tate algebras (Prof. Dr. BÃ¶ckle, Dr. GezmiÅ) {\"label\"=>\"Vectorial Drinfeld modular forms over Tate algebras\", \"url\"=>\"https://crc326gaus.de/wp-content/uploads/2023/03/VectorialDrinfeldModForms.pdf\", \"file\"=>\"/assets/uploads/VectorialDrinfeldModForms.pdf\"} ss2023-hauptseminar-arithmetik-von-zahl-und-funktionenkrp .md","url":"/teaching/?q=Hauptseminar+Arithmetik+von+Zahl-+und+Funktionenk%C3%B6rpern%3A+Vectorial+Drinfeld+modular+forms+over+Tate+algebras+%28Prof.+Dr.+B%C3%B6ckle%2C+Dr.+Gezmi%C5%9F%29","category":"teaching","description":"Hauptseminar Arithmetik von Zahl- und FunktionenkÃ¶rpern: Vectorial Drinfeld modular forms over Tate algebras (Prof. Dr. BÃ¶ckle, Dr. GezmiÅ)","tags":"","semester":"Summer term 2023","instructor":"Prof. Dr. BÃ¶ckle, Dr. GezmiÅ","course_type":"Seminar","semester_year":2023,"semester_key":"SS2023"},{"id":"teaching-Proseminar p-adic numbers (Dr. BÃ¶ckle, C. V. Sriram)","title":"Proseminar p-adic numbers (Dr. BÃ¶ckle, C. V. Sriram)","content":"Proseminar \"p-adic numbers\" (Dr. BÃ¶ckle, C. V. Sriram) HomeMembersResearchPublicationsTeachingLinksContactInterna --> Uni Heidelberg > IWR > ARITHGEO > &nbsp;Members >&nbsp;p adic numbers [english]&nbsp;|&nbsp;[] Proseminar on p-adic numbers Summer semester 2023 Prof. Dr. BÃ¶ckle, C. V. Sriram Welcome to the proseminar on p-adic numbers! Here you will find the announcement and useful resources to prepare your talks.The Vorbesprechung will be held on February 14, 2022 at 11:30 AM(s.t.); SR3, INF 205The announcement of the proseminar: Announcement.A detailed description of the talks and also the practicalities can be found hereThe proseminar also requires its participants to prepare handouts for their own talks. A possible template(Latex file) for the same is available here (There are two ways of compiling this file :-(i) using the online editor https://www.overleaf.com/&nbsp; or (ii) downloading a LaTeX editor and compiler. There are loads of them available online(for free). One could download editor https://www.xm1math.net/texmaker/ and compiler https://miktex.org/download).For more info :- sriram.chinthalagiri@iwr.uni-heidelberg.de&nbsp; &nbsp;arithgeo@iwr.uni-heidelberg.deLast Update:&nbsp;12.07.2023 - 11:35 &copy; Copyright Universit&auml;t Heidelberg.&nbsp;Impressum.   Proseminar p-adic numbers (Dr. BÃ¶ckle, C. V. Sriram) Summer term 2023 Dr. BÃ¶ckle, C. V. Sriram Seminar SS SS2023 Dr. BÃ¶ckle, C. V. Sriram Proseminar p-adic numbers (Dr. BÃ¶ckle, C. V. Sriram) ss2023-proseminar-p-adic-numbers-dr-bckle-c-v-sriram .md","url":"/teaching/?q=Proseminar+p-adic+numbers+%28Dr.+B%C3%B6ckle%2C+C.+V.+Sriram%29","category":"teaching","description":"Proseminar p-adic numbers (Dr. BÃ¶ckle, C. V. Sriram)","tags":"","semester":"Summer term 2023","instructor":"Dr. BÃ¶ckle, C. V. Sriram","course_type":"Seminar","semester_year":2023,"semester_key":"SS2023"},{"id":"teaching-Vorlesung Lineare Algebra 2 (Prof. Dr. BÃ¶ckle, Dr. Ludwig)","title":"Vorlesung Lineare Algebra 2 (Prof. Dr. BÃ¶ckle, Dr. Ludwig)","content":"Vorlesung \"Lineare Algebra 2\" (Prof. Dr. BÃ¶ckle, Dr. Ludwig) Lineare Algebra II Vorlesung im Sommersemester 2023 an der Universit&auml;t Heidelberg Personen: Dozent: &nbsp; Prof. Dr. Gebhard BÃ¶ckle Assistentin: &nbsp; Dr. Judith Ludwig Termine: Vorlesung: &nbsp; Dienstags und Donnerstags von 9:20 - 10:50 Uhr im groÃen HÃ¶rsaal der Chemie, INF 252 (erster Termin: 18.4.). PlenarÃ¼bung: &nbsp; Montags von 14:15 - 15:45 Uhr im groÃen HÃ¶rsaal der Chemie, INF 252 (erster Termin: 24.4.). Tutorien: &nbsp; Die Tutorien finden an verschiedenen Terminen statt, siehe MÃSLI (Beginn 2. Vorlesungswoche). 1. Klausur: &nbsp; 25.07.23, 10:00 - 12:00 Uhr. 2. Klausur: &nbsp; 09.10.23, 13:00 - 15:00 Uhr. AuÃer den beiden Klausuren wird es keine weiteren PrÃ¼fungen geben. Organisatorisches: FÃ¼r die Zulassung zur Modulklausur ist die erfolgreiche Teilnahme am Ãbungsbetrieb erforderlich. Es wird in der Regel jeden Donnerstag gegen 11 Uhr ein Ãbungsblatt auf MaMpf (s.u.) hochgeladen werden. Das erste Ãbungsblatt erscheint bereits am Dienstag, den 18.04. Werfen Sie bitte Ihre LÃ¶sungsvorschlÃ¤ge fÃ¼r das Ãbungsblatt jeweils am Donnerstag der Folgewoche bis 9:00 Uhr in die dafÃ¼r vorgesehenen EinwurfkÃ¤sten im Mathematikon, Im Neuenheimer Feld 205, 1. Etage, ein. Zum Besprechen der LÃ¶sungen und fÃ¼r Fragen zum aktuellen Stoff gibt es Tutorien, fÃ¼r die man sich via MÃSLI (s.u.) anmeldet. Die Anmeldung ist per Direktanmeldung ab dem 18.04., 11 Uhr mÃ¶glich. Bis Freitag, den 28.04. ist es gestattet, die Ãbungsgruppe zu wechseln, falls ein anderer Termin fÃ¼r Sie vorteilhafter ist und es noch freie PlÃ¤tze gibt. Dies kÃ¶nnen Sie selbst im MÃSLI tun. Die Tutorien starten in der zweiten Vorlesungswoche. Die Abgabe der Ãbungsaufgaben findet in Zweierteams statt, welche zu Beginn des Semesters innerhalb der Tutorien gebildet werden. Wiederholerregelung: Sollten Sie die Klausurzulassung fÃ¼r die Lineare Algebra 2 bereits im Sommersemester 2022 erworben haben (LA2/22), so empfehlen wir dennoch, dass Sie in diesem Semester nochmals aktiv am Ãbungsbetrieb teilnehmen. Melden Sie   Vorlesung Lineare Algebra 2 (Prof. Dr. BÃ¶ckle, Dr. Ludwig) Summer term 2023 Prof. Dr. BÃ¶ckle, Dr. Ludwig Vorlesung SS SS2023 Prof. Dr. BÃ¶ckle, Dr. Ludwig Vorlesung Lineare Algebra 2 (Prof. Dr. BÃ¶ckle, Dr. Ludwig) ss2023-vorlesung-lineare-algebra-2-prof-dr-bckle-dr-ludwi .md","url":"/teaching/?q=Vorlesung+Lineare+Algebra+2+%28Prof.+Dr.+B%C3%B6ckle%2C+Dr.+Ludwig%29","category":"teaching","description":"Vorlesung Lineare Algebra 2 (Prof. Dr. BÃ¶ckle, Dr. Ludwig)","tags":"","semester":"Summer term 2023","instructor":"Prof. Dr. BÃ¶ckle, Dr. Ludwig","course_type":"Vorlesung","semester_year":2023,"semester_key":"SS2023"},{"id":"teaching-Hauptseminar Arithmetik von Zahl- und FunktionenkÃ¶rpern: Shtukas for reductive groups and global Langlands correspondence after Vincent Lafforgue (Prof. Dr. BÃ¶ckle, Dr. GezmiÅ, Shavali, C.V. Sriram)","title":"Hauptseminar Arithmetik von Zahl- und FunktionenkÃ¶rpern: Shtukas for reductive groups and global Langlands correspondence after Vincent Lafforgue (Prof. Dr. BÃ¶ckle, Dr. GezmiÅ, Shavali, C.V. Sriram)","content":"Hauptseminar Arithmetik von Zahl- und FunktionenkÃ¶rpern: \"Shtukas for reductive groups and global Langlands correspondence after Vincent Lafforgue\" (Prof. Dr. BÃ¶ckle, Dr. GezmiÅ, Shavali, C.V. Sriram)   Hauptseminar Arithmetik von Zahl- und FunktionenkÃ¶rpern: Shtukas for reductive groups and global Langlands correspondence after Vincent Lafforgue (Prof. Dr. BÃ¶ckle, Dr. GezmiÅ, Shavali, C.V. Sriram) Summer term 2024 Prof. Dr. BÃ¶ckle, Dr. GezmiÅ, Shavali, C.V. Sriram Seminar SS SS2024 Prof. Dr. BÃ¶ckle, Dr. GezmiÅ, Shavali, C.V. Sriram Hauptseminar Arithmetik von Zahl- und FunktionenkÃ¶rpern: Shtukas for reductive groups and global Langlands correspondence after Vincent Lafforgue (Prof. Dr. BÃ¶ckle, Dr. GezmiÅ, Shavali, C.V. Sriram) ss2024-hauptseminar-arithmetik-von-zahl-und-funktionenkrp .md","url":"/teaching/?q=Hauptseminar+Arithmetik+von+Zahl-+und+Funktionenk%C3%B6rpern%3A+Shtukas+for+reductive+groups+and+global+Langlands+correspondence+after+Vincent+Lafforgue+%28Prof.+Dr.+B%C3%B6ckle%2C+Dr.+Gezmi%C5%9F%2C+Shavali%2C+C.V.+Sriram%29","category":"teaching","description":"Hauptseminar Arithmetik von Zahl- und FunktionenkÃ¶rpern: Shtukas for reductive groups and global Langlands correspondence after Vincent Lafforgue (Prof. Dr. BÃ¶ckle, Dr. GezmiÅ, Shavali, C.V. Sriram)","tags":"","semester":"Summer term 2024","instructor":"Prof. Dr. BÃ¶ckle, Dr. GezmiÅ, Shavali, C.V. Sriram","course_type":"Seminar","semester_year":2024,"semester_key":"SS2024"},{"id":"teaching-Seminar on Representation theory of finite groups (Prof. Dr. BÃ¶ckle, Chilla, Dr. GezmiÅ)","title":"Seminar on Representation theory of finite groups (Prof. Dr. BÃ¶ckle, Chilla, Dr. GezmiÅ)","content":"Seminar on \"Representation theory of finite groups\" (Prof. Dr. BÃ¶ckle, Chilla, Dr. GezmiÅ) Uni Heidelberg > IWR > ARITHGEO > &nbsp;Members >&nbsp;Seminar on Representation theory of finite groups (Summer Semester 2024)   Seminar on Representation theory of finite groups (Prof. Dr. BÃ¶ckle, Chilla, Dr. GezmiÅ) Summer term 2024 Prof. Dr. BÃ¶ckle, Chilla, Dr. GezmiÅ Seminar SS SS2024 Prof. Dr. BÃ¶ckle, Chilla, Dr. GezmiÅ Seminar on Representation theory of finite groups (Prof. Dr. BÃ¶ckle, Chilla, Dr. GezmiÅ) ss2024-seminar-on-representation-theory-of-finite-groups- .md","url":"/teaching/?q=Seminar+on+Representation+theory+of+finite+groups+%28Prof.+Dr.+B%C3%B6ckle%2C+Chilla%2C+Dr.+Gezmi%C5%9F%29","category":"teaching","description":"Seminar on Representation theory of finite groups (Prof. Dr. BÃ¶ckle, Chilla, Dr. GezmiÅ)","tags":"","semester":"Summer term 2024","instructor":"Prof. Dr. BÃ¶ckle, Chilla, Dr. GezmiÅ","course_type":"Seminar","semester_year":2024,"semester_key":"SS2024"},{"id":"teaching-Vorlesung Algebra 2 (Prof. Dr. BÃ¶ckle, Shavali)","title":"Vorlesung Algebra 2 (Prof. Dr. BÃ¶ckle, Shavali)","content":"Vorlesung \"Algebra 2\" (Prof. Dr. BÃ¶ckle, Shavali) Algebra 2 Lecture in the summer semester 2024 at the University of Heidelberg Lecturer: &nbsp; Prof. Dr. Gebhard BÃ¶ckle Assistant: &nbsp; Alireza Shavali Kohshor Events: Lecture: &nbsp; Wednesday and Friday from 11:00 - 13:00 in SR B, Mathematikon, INF 205 (first session: 17.04.). Tutorials: &nbsp; The tutorials take place every Monday afternoon (14-16 and 16-18) starting from 22.04, see MÃSLI Exams: &nbsp; First Exam: Wednesday 24.07.2024 from 15:00 to 17:00 in SR A and B. &nbsp; Second Exam: Monday 07.10.2024 from 9:00 to 11:00 in the HÃ¶rsaal. The language of the lectures will be English. You can hand in your solution to exercises either in English or German. Organizational Details: In order to be admitted to the final exam of the module (ModulprÃ¼fung), successful participation in the accompanying discussion sessions (tutorials) is required; This includes, in particular, to work out solutions of the weekly homework assignments. A new sheet of homework assignments will be provided on MaMpf every Friday around 13:00. Please hand in your solutions to these by 11:00 a.m. on the Friday of the following week via the drop boxes provided in the Mathematikon, INF 205, 1st floor; Your tutor may allow other ways of handing in the solution sets. The homework assignments are to be submitted in teams of two, which are formed in the first tutorial session of the semester. To discuss the solutions and questions about the course material, there are weekly tutorials for which you need to register via MÃSLI (see below). Enrollment is possible from Monday, April 22, 11 a.m. until Friday, May 3. The tutorials are offered at two time periods. As long as the sessions are not completely filled you may change from one time period to the other. You can do this yourself in MÃSLI. Rules for repeaters (Wiederholer): If you have already acquired admission to the Algebra 2 exam in the summer semester of 2023, and if you failed the exam then, you may participate in the exams for the present cour   Vorlesung Algebra 2 (Prof. Dr. BÃ¶ckle, Shavali) Summer term 2024 Prof. Dr. BÃ¶ckle, Shavali Vorlesung SS SS2024 Prof. Dr. BÃ¶ckle, Shavali Vorlesung Algebra 2 (Prof. Dr. BÃ¶ckle, Shavali) ss2024-vorlesung-algebra-2-prof-dr-bckle-shavali .md","url":"/teaching/?q=Vorlesung+Algebra+2+%28Prof.+Dr.+B%C3%B6ckle%2C+Shavali%29","category":"teaching","description":"Vorlesung Algebra 2 (Prof. Dr. BÃ¶ckle, Shavali)","tags":"","semester":"Summer term 2024","instructor":"Prof. Dr. BÃ¶ckle, Shavali","course_type":"Vorlesung","semester_year":2024,"semester_key":"SS2024"},{"id":"teaching-Seminar on Homological Algebra (Prof. Dr. BÃ¶ckle, Dr. Ferraro)","title":"Seminar on Homological Algebra (Prof. Dr. BÃ¶ckle, Dr. Ferraro)","content":"Seminar on \"Homological Algebra\" (Prof. Dr. BÃ¶ckle, Dr. Ferraro) Uni Heidelberg > IWR > ARITHGEO > &nbsp;Members >&nbsp;Seminar on Homological Algebra (Summer Semester 2025)   Seminar on Homological Algebra (Prof. Dr. BÃ¶ckle, Dr. Ferraro) Summer term 2025 Prof. Dr. BÃ¶ckle, Dr. Ferraro Seminar SS SS2025 Prof. Dr. BÃ¶ckle, Dr. Ferraro Seminar on Homological Algebra (Prof. Dr. BÃ¶ckle, Dr. Ferraro) ss2025-seminar-on-homological-algebra-prof-dr-bckle-dr-fe .md","url":"/teaching/?q=Seminar+on+Homological+Algebra+%28Prof.+Dr.+B%C3%B6ckle%2C+Dr.+Ferraro%29","category":"teaching","description":"Seminar on Homological Algebra (Prof. Dr. BÃ¶ckle, Dr. Ferraro)","tags":"","semester":"Summer term 2025","instructor":"Prof. Dr. BÃ¶ckle, Dr. Ferraro","course_type":"Seminar","semester_year":2025,"semester_key":"SS2025"},{"id":"teaching-Anwendungsorientierte Zahlentheorie und Algebra (Prof. Dr. BÃ¶ckle)","title":"Anwendungsorientierte Zahlentheorie und Algebra (Prof. Dr. BÃ¶ckle)","content":"Anwendungsorientierte Zahlentheorie und Algebra (Prof. Dr. BÃ¶ckle)   Anwendungsorientierte Zahlentheorie und Algebra (Prof. Dr. BÃ¶ckle) Winter term 2003/04 Prof. Dr. BÃ¶ckle Seminar WS WS2003 Prof. Dr. BÃ¶ckle Anwendungsorientierte Zahlentheorie und Algebra (Prof. Dr. BÃ¶ckle) ws2003-anwendungsorientierte-zahlentheorie-und-algebra-pr .md","url":"/teaching/?q=Anwendungsorientierte+Zahlentheorie+und+Algebra+%28Prof.+Dr.+B%C3%B6ckle%29","category":"teaching","description":"Anwendungsorientierte Zahlentheorie und Algebra (Prof. Dr. BÃ¶ckle)","tags":"","semester":"Winter term 2003/04","instructor":"Prof. Dr. BÃ¶ckle","course_type":"Seminar","semester_year":2003,"semester_key":"WS2003"},{"id":"teaching-Schwerpunktseminar Zahlentheorie: Pointcounting over finite fields (G. BÃ¶ckle, G. Frey, I. Bouw, C. Diem)","title":"Schwerpunktseminar Zahlentheorie: Pointcounting over finite fields (G. BÃ¶ckle, G. Frey, I. Bouw, C. Diem)","content":"Schwerpunktseminar Zahlentheorie: Pointcounting over finite fields (G. BÃ¶ckle, G. Frey, I. Bouw, C. Diem)   Schwerpunktseminar Zahlentheorie: Pointcounting over finite fields (G. BÃ¶ckle, G. Frey, I. Bouw, C. Diem) Winter term 2003/04 G. BÃ¶ckle, G. Frey, I. Bouw, C. Diem Seminar WS WS2003 G. BÃ¶ckle, G. Frey, I. Bouw, C. Diem Schwerpunktseminar Zahlentheorie: Pointcounting over finite fields (G. BÃ¶ckle, G. Frey, I. Bouw, C. Diem) ws2003-schwerpunktseminar-zahlentheorie-pointcounting-ove .md","url":"/teaching/?q=Schwerpunktseminar+Zahlentheorie%3A+Pointcounting+over+finite+fields+%28G.+B%C3%B6ckle%2C+G.+Frey%2C+I.+Bouw%2C+C.+Diem%29","category":"teaching","description":"Schwerpunktseminar Zahlentheorie: Pointcounting over finite fields (G. BÃ¶ckle, G. Frey, I. Bouw, C. Diem)","tags":"","semester":"Winter term 2003/04","instructor":"G. BÃ¶ckle, G. Frey, I. Bouw, C. Diem","course_type":"Seminar","semester_year":2003,"semester_key":"WS2003"},{"id":"teaching-Arithmetik von Modulformen (Prof. Dr. BÃ¶ckle)","title":"Arithmetik von Modulformen (Prof. Dr. BÃ¶ckle)","content":"Arithmetik von Modulformen (Prof. Dr. BÃ¶ckle)   Arithmetik von Modulformen (Prof. Dr. BÃ¶ckle) Winter term 2004/05 Prof. Dr. BÃ¶ckle Seminar WS WS2004 Prof. Dr. BÃ¶ckle Arithmetik von Modulformen (Prof. Dr. BÃ¶ckle) ws2004-arithmetik-von-modulformen-prof-dr-bckle .md","url":"/teaching/?q=Arithmetik+von+Modulformen+%28Prof.+Dr.+B%C3%B6ckle%29","category":"teaching","description":"Arithmetik von Modulformen (Prof. Dr. BÃ¶ckle)","tags":"","semester":"Winter term 2004/05","instructor":"Prof. Dr. BÃ¶ckle","course_type":"Seminar","semester_year":2004,"semester_key":"WS2004"},{"id":"teaching-Lineare Algebra 1 (Prof. Dr. BÃ¶ckle)","title":"Lineare Algebra 1 (Prof. Dr. BÃ¶ckle)","content":"Lineare Algebra 1 (Prof. Dr. BÃ¶ckle)   Lineare Algebra 1 (Prof. Dr. BÃ¶ckle) Winter term 2004/05 Prof. Dr. BÃ¶ckle Seminar WS WS2004 Prof. Dr. BÃ¶ckle Lineare Algebra 1 (Prof. Dr. BÃ¶ckle) ws2004-lineare-algebra-1-prof-dr-bckle .md","url":"/teaching/?q=Lineare+Algebra+1+%28Prof.+Dr.+B%C3%B6ckle%29","category":"teaching","description":"Lineare Algebra 1 (Prof. Dr. BÃ¶ckle)","tags":"","semester":"Winter term 2004/05","instructor":"Prof. Dr. BÃ¶ckle","course_type":"Seminar","semester_year":2004,"semester_key":"WS2004"},{"id":"teaching-Algebra 1 (Prof. BÃ¶ckle)","title":"Algebra 1 (Prof. BÃ¶ckle)","content":"Algebra 1 (Prof. BÃ¶ckle)   Algebra 1 (Prof. BÃ¶ckle) Winter term 2005/06 Prof. BÃ¶ckle Seminar WS WS2005 Prof. BÃ¶ckle Algebra 1 (Prof. BÃ¶ckle) ws2005-algebra-1-prof-bckle .md","url":"/teaching/?q=Algebra+1+%28Prof.+B%C3%B6ckle%29","category":"teaching","description":"Algebra 1 (Prof. BÃ¶ckle)","tags":"","semester":"Winter term 2005/06","instructor":"Prof. BÃ¶ckle","course_type":"Seminar","semester_year":2005,"semester_key":"WS2005"},{"id":"teaching-Arbeitsgemeinschaft: Galoisdarstellungen zu Modulformen (G. BÃ¶ckle, G. Frey, M. MÃ¶ller)","title":"Arbeitsgemeinschaft: Galoisdarstellungen zu Modulformen (G. BÃ¶ckle, G. Frey, M. MÃ¶ller)","content":"Arbeitsgemeinschaft: Galoisdarstellungen zu Modulformen (G. BÃ¶ckle, G. Frey, M. MÃ¶ller)   Arbeitsgemeinschaft: Galoisdarstellungen zu Modulformen (G. BÃ¶ckle, G. Frey, M. MÃ¶ller) Winter term 2005/06 G. BÃ¶ckle, G. Frey, M. MÃ¶ller Arbeitsgemeinschaft WS WS2005 G. BÃ¶ckle, G. Frey, M. MÃ¶ller Arbeitsgemeinschaft: Galoisdarstellungen zu Modulformen (G. BÃ¶ckle, G. Frey, M. MÃ¶ller) ws2005-arbeitsgemeinschaft-galoisdarstellungen-zu-modulfo .md","url":"/teaching/?q=Arbeitsgemeinschaft%3A+Galoisdarstellungen+zu+Modulformen+%28G.+B%C3%B6ckle%2C+G.+Frey%2C+M.+M%C3%B6ller%29","category":"teaching","description":"Arbeitsgemeinschaft: Galoisdarstellungen zu Modulformen (G. BÃ¶ckle, G. Frey, M. MÃ¶ller)","tags":"","semester":"Winter term 2005/06","instructor":"G. BÃ¶ckle, G. Frey, M. MÃ¶ller","course_type":"Arbeitsgemeinschaft","semester_year":2005,"semester_key":"WS2005"},{"id":"teaching-Proseminar Aspekte zum Thema Zahlen (Prof. Dr. BÃ¶ckle)","title":"Proseminar Aspekte zum Thema Zahlen (Prof. Dr. BÃ¶ckle)","content":"Proseminar \"Aspekte zum Thema Zahlen\" (Prof. Dr. BÃ¶ckle)   Proseminar Aspekte zum Thema Zahlen (Prof. Dr. BÃ¶ckle) Winter term 2005/06 Prof. Dr. BÃ¶ckle Seminar WS WS2005 Prof. Dr. BÃ¶ckle Proseminar Aspekte zum Thema Zahlen (Prof. Dr. BÃ¶ckle) ws2005-proseminar-aspekte-zum-thema-zahlen-prof-dr-bckle .md","url":"/teaching/?q=Proseminar+Aspekte+zum+Thema+Zahlen+%28Prof.+Dr.+B%C3%B6ckle%29","category":"teaching","description":"Proseminar Aspekte zum Thema Zahlen (Prof. Dr. BÃ¶ckle)","tags":"","semester":"Winter term 2005/06","instructor":"Prof. Dr. BÃ¶ckle","course_type":"Seminar","semester_year":2005,"semester_key":"WS2005"},{"id":"teaching-Algebraische Zahlentheorie 1 (Prof. Dr. BÃ¶ckle)","title":"Algebraische Zahlentheorie 1 (Prof. Dr. BÃ¶ckle)","content":"Algebraische Zahlentheorie 1 (Prof. Dr. BÃ¶ckle)   Algebraische Zahlentheorie 1 (Prof. Dr. BÃ¶ckle) Winter term 2006/07 Prof. Dr. BÃ¶ckle Seminar WS WS2006 Prof. Dr. BÃ¶ckle Algebraische Zahlentheorie 1 (Prof. Dr. BÃ¶ckle) ws2006-algebraische-zahlentheorie-1-prof-dr-bckle .md","url":"/teaching/?q=Algebraische+Zahlentheorie+1+%28Prof.+Dr.+B%C3%B6ckle%29","category":"teaching","description":"Algebraische Zahlentheorie 1 (Prof. Dr. BÃ¶ckle)","tags":"","semester":"Winter term 2006/07","instructor":"Prof. Dr. BÃ¶ckle","course_type":"Seminar","semester_year":2006,"semester_key":"WS2006"},{"id":"teaching-Ãbungen zu Mathematik fÃ¼r Ingenieure (Dr. CerviÃ±o)","title":"Ãbungen zu Mathematik fÃ¼r Ingenieure (Dr. CerviÃ±o)","content":"Ãbungen zu \"Mathematik fÃ¼r Ingenieure\" (Dr. CerviÃ±o)   Ãbungen zu Mathematik fÃ¼r Ingenieure (Dr. CerviÃ±o) Winter term 2006/07 Dr. CerviÃ±o Ãbung WS WS2006 Dr. CerviÃ±o Ãbungen zu Mathematik fÃ¼r Ingenieure (Dr. CerviÃ±o) ws2006-bungen-zu-mathematik-fr-ingenieure-dr-cervio .md","url":"/teaching/?q=%C3%9Cbungen+zu+Mathematik+f%C3%BCr+Ingenieure+%28Dr.+Cervi%C3%B1o%29","category":"teaching","description":"Ãbungen zu Mathematik fÃ¼r Ingenieure (Dr. CerviÃ±o)","tags":"","semester":"Winter term 2006/07","instructor":"Dr. CerviÃ±o","course_type":"Ãbung","semester_year":2006,"semester_key":"WS2006"},{"id":"teaching-Seminar Homologische Algebra (Prof. Dr. BÃ¶ckle, Dr. CerviÃ±o)","title":"Seminar Homologische Algebra (Prof. Dr. BÃ¶ckle, Dr. CerviÃ±o)","content":"Seminar \"Homologische Algebra\" (Prof. Dr. BÃ¶ckle, Dr. CerviÃ±o)   Seminar Homologische Algebra (Prof. Dr. BÃ¶ckle, Dr. CerviÃ±o) Winter term 2006/07 Prof. Dr. BÃ¶ckle, Dr. CerviÃ±o Seminar WS WS2006 Prof. Dr. BÃ¶ckle, Dr. CerviÃ±o Seminar Homologische Algebra (Prof. Dr. BÃ¶ckle, Dr. CerviÃ±o) ws2006-seminar-homologische-algebra-prof-dr-bckle-dr-cerv .md","url":"/teaching/?q=Seminar+Homologische+Algebra+%28Prof.+Dr.+B%C3%B6ckle%2C+Dr.+Cervi%C3%B1o%29","category":"teaching","description":"Seminar Homologische Algebra (Prof. Dr. BÃ¶ckle, Dr. CerviÃ±o)","tags":"","semester":"Winter term 2006/07","instructor":"Prof. Dr. BÃ¶ckle, Dr. CerviÃ±o","course_type":"Seminar","semester_year":2006,"semester_key":"WS2006"},{"id":"teaching-Arbeitsgemeinschaft: Kolyvagin's Euler system for elliptic curves (G. BÃ¶ckle, G. Frey)","title":"Arbeitsgemeinschaft: Kolyvagin's Euler system for elliptic curves (G. BÃ¶ckle, G. Frey)","content":"Arbeitsgemeinschaft: Kolyvagin's Euler system for elliptic curves (G. BÃ¶ckle, G. Frey)   Arbeitsgemeinschaft: Kolyvagin's Euler system for elliptic curves (G. BÃ¶ckle, G. Frey) Winter term 2007/08 G. BÃ¶ckle, G. Frey Arbeitsgemeinschaft WS WS2007 G. BÃ¶ckle, G. Frey Arbeitsgemeinschaft: Kolyvagin's Euler system for elliptic curves (G. BÃ¶ckle, G. Frey) ws2007-arbeitsgemeinschaft-kolyvagins-euler-system-for-el .md","url":"/teaching/?q=Arbeitsgemeinschaft%3A+Kolyvagin%27s+Euler+system+for+elliptic+curves+%28G.+B%C3%B6ckle%2C+G.+Frey%29","category":"teaching","description":"Arbeitsgemeinschaft: Kolyvagin's Euler system for elliptic curves (G. BÃ¶ckle, G. Frey)","tags":"","semester":"Winter term 2007/08","instructor":"G. BÃ¶ckle, G. Frey","course_type":"Arbeitsgemeinschaft","semester_year":2007,"semester_key":"WS2007"},{"id":"teaching-Mathematik Vorkurs (Dr. CerviÃ±o)","title":"Mathematik Vorkurs (Dr. CerviÃ±o)","content":"Mathematik Vorkurs (Dr.Â CerviÃ±o)   Mathematik Vorkurs (Dr. CerviÃ±o) Winter term 2007/08 Dr.Â CerviÃ±o Vorlesung WS WS2007 Dr.Â CerviÃ±o Mathematik Vorkurs (Dr. CerviÃ±o) ws2007-mathematik-vorkurs-dr-cervio .md","url":"/teaching/?q=Mathematik+Vorkurs+%28Dr.+Cervi%C3%B1o%29","category":"teaching","description":"Mathematik Vorkurs (Dr. CerviÃ±o)","tags":"","semester":"Winter term 2007/08","instructor":"Dr.Â CerviÃ±o","course_type":"Vorlesung","semester_year":2007,"semester_key":"WS2007"},{"id":"teaching-sabbatical term","title":"sabbatical term","content":"sabbatical term   sabbatical term Winter term 2007/08 Seminar WS WS2007 sabbatical term ws2007-sabbatical-term .md","url":"/teaching/?q=sabbatical+term","category":"teaching","description":"sabbatical term","tags":"","semester":"Winter term 2007/08","instructor":"","course_type":"Seminar","semester_year":2007,"semester_key":"WS2007"},{"id":"teaching-Anwendungsoriente Algebra und Zahlentheorie (Prof. Dr. BÃ¶ckle)","title":"Anwendungsoriente Algebra und Zahlentheorie (Prof. Dr. BÃ¶ckle)","content":"Anwendungsoriente Algebra und Zahlentheorie (Prof. Dr. BÃ¶ckle)   Anwendungsoriente Algebra und Zahlentheorie (Prof. Dr. BÃ¶ckle) Winter term 2008/09 Prof. Dr. BÃ¶ckle Seminar WS WS2008 Prof. Dr. BÃ¶ckle Anwendungsoriente Algebra und Zahlentheorie (Prof. Dr. BÃ¶ckle) ws2008-anwendungsoriente-algebra-und-zahlentheorie-prof-d .md","url":"/teaching/?q=Anwendungsoriente+Algebra+und+Zahlentheorie+%28Prof.+Dr.+B%C3%B6ckle%29","category":"teaching","description":"Anwendungsoriente Algebra und Zahlentheorie (Prof. Dr. BÃ¶ckle)","tags":"","semester":"Winter term 2008/09","instructor":"Prof. Dr. BÃ¶ckle","course_type":"Seminar","semester_year":2008,"semester_key":"WS2008"},{"id":"teaching-Arbeitsgemeinschaft: p-adische Galoisdarstellungen (G. BÃ¶ckle, G. Wiese)","title":"Arbeitsgemeinschaft: p-adische Galoisdarstellungen (G. BÃ¶ckle, G. Wiese)","content":"Arbeitsgemeinschaft: p-adische Galoisdarstellungen (G. BÃ¶ckle, G. Wiese)   Arbeitsgemeinschaft: p-adische Galoisdarstellungen (G. BÃ¶ckle, G. Wiese) Winter term 2008/09 G. BÃ¶ckle, G. Wiese Arbeitsgemeinschaft WS WS2008 G. BÃ¶ckle, G. Wiese Arbeitsgemeinschaft: p-adische Galoisdarstellungen (G. BÃ¶ckle, G. Wiese) ws2008-arbeitsgemeinschaft-p-adische-galoisdarstellungen- .md","url":"/teaching/?q=Arbeitsgemeinschaft%3A+p-adische+Galoisdarstellungen+%28G.+B%C3%B6ckle%2C+G.+Wiese%29","category":"teaching","description":"Arbeitsgemeinschaft: p-adische Galoisdarstellungen (G. BÃ¶ckle, G. Wiese)","tags":"","semester":"Winter term 2008/09","instructor":"G. BÃ¶ckle, G. Wiese","course_type":"Arbeitsgemeinschaft","semester_year":2008,"semester_key":"WS2008"},{"id":"teaching-Mathematik Vorkurs (Dr. CerviÃ±o)","title":"Mathematik Vorkurs (Dr. CerviÃ±o)","content":"Mathematik Vorkurs (Dr. CerviÃ±o)   Mathematik Vorkurs (Dr. CerviÃ±o) Winter term 2008/09 Dr. CerviÃ±o Vorlesung WS WS2008 Dr. CerviÃ±o Mathematik Vorkurs (Dr. CerviÃ±o) ws2008-mathematik-vorkurs-dr-cervio .md","url":"/teaching/?q=Mathematik+Vorkurs+%28Dr.+Cervi%C3%B1o%29","category":"teaching","description":"Mathematik Vorkurs (Dr. CerviÃ±o)","tags":"","semester":"Winter term 2008/09","instructor":"Dr. CerviÃ±o","course_type":"Vorlesung","semester_year":2008,"semester_key":"WS2008"},{"id":"teaching-Riemannsche FlÃ¤chen 1 (Prof. Dr. BÃ¶ckle)","title":"Riemannsche FlÃ¤chen 1 (Prof. Dr. BÃ¶ckle)","content":"Riemannsche FlÃ¤chen 1 (Prof. Dr. BÃ¶ckle)   Riemannsche FlÃ¤chen 1 (Prof. Dr. BÃ¶ckle) Winter term 2008/09 Prof. Dr. BÃ¶ckle Seminar WS WS2008 Prof. Dr. BÃ¶ckle Riemannsche FlÃ¤chen 1 (Prof. Dr. BÃ¶ckle) ws2008-riemannsche-flchen-1-prof-dr-bckle .md","url":"/teaching/?q=Riemannsche+Fl%C3%A4chen+1+%28Prof.+Dr.+B%C3%B6ckle%29","category":"teaching","description":"Riemannsche FlÃ¤chen 1 (Prof. Dr. BÃ¶ckle)","tags":"","semester":"Winter term 2008/09","instructor":"Prof. Dr. BÃ¶ckle","course_type":"Seminar","semester_year":2008,"semester_key":"WS2008"},{"id":"teaching-Algebraic groups and buildings (Prof. Dr. BÃ¶ckle, Dr. CerviÃ±o)","title":"Algebraic groups and buildings (Prof. Dr. BÃ¶ckle, Dr. CerviÃ±o)","content":"Algebraic groups and buildings (Prof. Dr. BÃ¶ckle, Dr. CerviÃ±o)   Algebraic groups and buildings (Prof. Dr. BÃ¶ckle, Dr. CerviÃ±o) Winter term 2010/11 Prof. Dr. BÃ¶ckle, Dr. CerviÃ±o Seminar WS WS2010 Prof. Dr. BÃ¶ckle, Dr. CerviÃ±o Algebraic groups and buildings (Prof. Dr. BÃ¶ckle, Dr. CerviÃ±o) {\"label\"=>\"Algebraic groups and buildings\", \"url\"=>\"http://www.ub.uni-heidelberg.de/helios/fachinfo/www/math/kvv/ws2010/x-2.htm\"} ws2010-algebraic-groups-and-buildings-prof-dr-bckle-dr-ce .md","url":"/teaching/?q=Algebraic+groups+and+buildings+%28Prof.+Dr.+B%C3%B6ckle%2C+Dr.+Cervi%C3%B1o%29","category":"teaching","description":"Algebraic groups and buildings (Prof. Dr. BÃ¶ckle, Dr. CerviÃ±o)","tags":"","semester":"Winter term 2010/11","instructor":"Prof. Dr. BÃ¶ckle, Dr. CerviÃ±o","course_type":"Seminar","semester_year":2010,"semester_key":"WS2010"},{"id":"teaching-Exercise sessions for Introduction to elementary geometry (Ralf Butenuth)","title":"Exercise sessions for Introduction to elementary geometry (Ralf Butenuth)","content":"Exercise sessions for \"Introduction to elementary geometry\" (Ralf Butenuth)   Exercise sessions for Introduction to elementary geometry (Ralf Butenuth) Winter term 2010/11 Ralf Butenuth Ãbung WS WS2010 Ralf Butenuth Exercise sessions for Introduction to elementary geometry (Ralf Butenuth) {\"label\"=>\"Introduction to elementary geometry\", \"url\"=>\"http://www.iwr.uni-heidelberg.de/groups/arith-geom/butenuth/geometrie/index.html\"} ws2010-exercise-sessions-for-introduction-to-elementary-g .md","url":"/teaching/?q=Exercise+sessions+for+Introduction+to+elementary+geometry+%28Ralf+Butenuth%29","category":"teaching","description":"Exercise sessions for Introduction to elementary geometry (Ralf Butenuth)","tags":"","semester":"Winter term 2010/11","instructor":"Ralf Butenuth","course_type":"Ãbung","semester_year":2010,"semester_key":"WS2010"},{"id":"teaching-Linear Algebra 1 (Prof. Dr. BÃ¶ckle)","title":"Linear Algebra 1 (Prof. Dr. BÃ¶ckle)","content":"Linear Algebra 1 (Prof. Dr. BÃ¶ckle)   Linear Algebra 1 (Prof. Dr. BÃ¶ckle) Winter term 2010/11 Prof. Dr. BÃ¶ckle Seminar WS WS2010 Prof. Dr. BÃ¶ckle Linear Algebra 1 (Prof. Dr. BÃ¶ckle) {\"label\"=>\"Linear Algebra 1\", \"url\"=>\"http://www.ub.uni-heidelberg.de/helios/fachinfo/www/math/kvv/ws2010/g-5.htm\"} ws2010-linear-algebra-1-prof-dr-bckle .md","url":"/teaching/?q=Linear+Algebra+1+%28Prof.+Dr.+B%C3%B6ckle%29","category":"teaching","description":"Linear Algebra 1 (Prof. Dr. BÃ¶ckle)","tags":"","semester":"Winter term 2010/11","instructor":"Prof. Dr. BÃ¶ckle","course_type":"Seminar","semester_year":2010,"semester_key":"WS2010"},{"id":"teaching-Seminar Hecke operators and their algorithmic (Prof. Dr. BÃ¶ckle, Dr. Centeleghe)","title":"Seminar Hecke operators and their algorithmic (Prof. Dr. BÃ¶ckle, Dr. Centeleghe)","content":"Seminar \"Hecke operators and their algorithmic\" (Prof. Dr. BÃ¶ckle, Dr. Centeleghe)   Seminar Hecke operators and their algorithmic (Prof. Dr. BÃ¶ckle, Dr. Centeleghe) Winter term 2010/11 Prof. Dr. BÃ¶ckle, Dr. Centeleghe Seminar WS WS2010 Prof. Dr. BÃ¶ckle, Dr. Centeleghe Seminar Hecke operators and their algorithmic (Prof. Dr. BÃ¶ckle, Dr. Centeleghe) {\"label\"=>\"Seminar Hecke operators and their algorithmic\", \"url\"=>\"http://www.ub.uni-heidelberg.de/helios/fachinfo/www/math/kvv/ws2010/s-6.htm\"} ws2010-seminar-hecke-operators-and-their-algorithmic-prof .md","url":"/teaching/?q=Seminar+Hecke+operators+and+their+algorithmic+%28Prof.+Dr.+B%C3%B6ckle%2C+Dr.+Centeleghe%29","category":"teaching","description":"Seminar Hecke operators and their algorithmic (Prof. Dr. BÃ¶ckle, Dr. Centeleghe)","tags":"","semester":"Winter term 2010/11","instructor":"Prof. Dr. BÃ¶ckle, Dr. Centeleghe","course_type":"Seminar","semester_year":2010,"semester_key":"WS2010"},{"id":"teaching-Algebra 1 (Prof. Dr. BÃ¶ckle)","title":"Algebra 1 (Prof. Dr. BÃ¶ckle)","content":"Algebra 1 (Prof. Dr. BÃ¶ckle)   Algebra 1 (Prof. Dr. BÃ¶ckle) Winter term 2011/12 Prof. Dr. BÃ¶ckle Seminar WS WS2011 Prof. Dr. BÃ¶ckle Algebra 1 (Prof. Dr. BÃ¶ckle) {\"label\"=>\"Algebra 1\", \"url\"=>\"http://www.iwr.uni-heidelberg.de/groups/arith-geom/maurischat/algebra1-ws2011/index.html\"} ws2011-algebra-1-prof-dr-bckle .md","url":"/teaching/?q=Algebra+1+%28Prof.+Dr.+B%C3%B6ckle%29","category":"teaching","description":"Algebra 1 (Prof. Dr. BÃ¶ckle)","tags":"","semester":"Winter term 2011/12","instructor":"Prof. Dr. BÃ¶ckle","course_type":"Seminar","semester_year":2011,"semester_key":"WS2011"},{"id":"teaching-Proseminar Bilinear forms and classical groups (Prof. Dr. BÃ¶ckle, Dr. Maurischat)","title":"Proseminar Bilinear forms and classical groups (Prof. Dr. BÃ¶ckle, Dr. Maurischat)","content":"Proseminar \"Bilinear forms and classical groups\" (Prof. Dr. BÃ¶ckle, Dr. Maurischat)   Proseminar Bilinear forms and classical groups (Prof. Dr. BÃ¶ckle, Dr. Maurischat) Winter term 2011/12 Prof. Dr. BÃ¶ckle, Dr. Maurischat Seminar WS WS2011 Prof. Dr. BÃ¶ckle, Dr. Maurischat Proseminar Bilinear forms and classical groups (Prof. Dr. BÃ¶ckle, Dr. Maurischat) {\"label\"=>\"Proseminar Bilinear forms and classical groups\", \"url\"=>\"http://www.iwr.uni-heidelberg.de/groups/arith-geom/maurischat/uebungen/bilinearformen.html\"} ws2011-proseminar-bilinear-forms-and-classical-groups-pro .md","url":"/teaching/?q=Proseminar+Bilinear+forms+and+classical+groups+%28Prof.+Dr.+B%C3%B6ckle%2C+Dr.+Maurischat%29","category":"teaching","description":"Proseminar Bilinear forms and classical groups (Prof. Dr. BÃ¶ckle, Dr. Maurischat)","tags":"","semester":"Winter term 2011/12","instructor":"Prof. Dr. BÃ¶ckle, Dr. Maurischat","course_type":"Seminar","semester_year":2011,"semester_key":"WS2011"},{"id":"teaching-Seminar Borcherds Products (Prof. Dr. BÃ¶ckle, Dr. CerviÃ±o)","title":"Seminar Borcherds Products (Prof. Dr. BÃ¶ckle, Dr. CerviÃ±o)","content":"Seminar \"Borcherds Products\" (Prof. Dr. BÃ¶ckle, Dr. CerviÃ±o)   Seminar Borcherds Products (Prof. Dr. BÃ¶ckle, Dr. CerviÃ±o) Winter term 2011/12 Prof. Dr. BÃ¶ckle, Dr. CerviÃ±o Seminar WS WS2011 Prof. Dr. BÃ¶ckle, Dr. CerviÃ±o Seminar Borcherds Products (Prof. Dr. BÃ¶ckle, Dr. CerviÃ±o) ws2011-seminar-borcherds-products-prof-dr-bckle-dr-cervio .md","url":"/teaching/?q=Seminar+Borcherds+Products+%28Prof.+Dr.+B%C3%B6ckle%2C+Dr.+Cervi%C3%B1o%29","category":"teaching","description":"Seminar Borcherds Products (Prof. Dr. BÃ¶ckle, Dr. CerviÃ±o)","tags":"","semester":"Winter term 2011/12","instructor":"Prof. Dr. BÃ¶ckle, Dr. CerviÃ±o","course_type":"Seminar","semester_year":2011,"semester_key":"WS2011"},{"id":"teaching-Seminar Ikeda-Lift (Dr. Bouganis, Dr. CerviÃ±o, Dr. Kasten)","title":"Seminar Ikeda-Lift (Dr. Bouganis, Dr. CerviÃ±o, Dr. Kasten)","content":"Seminar \"Ikeda-Lift\" (Dr. Bouganis, Dr. CerviÃ±o, Dr. Kasten)   Seminar Ikeda-Lift (Dr. Bouganis, Dr. CerviÃ±o, Dr. Kasten) Winter term 2011/12 Dr. Bouganis, Dr. CerviÃ±o, Dr. Kasten Seminar WS WS2011 Dr. Bouganis, Dr. CerviÃ±o, Dr. Kasten Seminar Ikeda-Lift (Dr. Bouganis, Dr. CerviÃ±o, Dr. Kasten) ws2011-seminar-ikeda-lift-dr-bouganis-dr-cervio-dr-kasten .md","url":"/teaching/?q=Seminar+Ikeda-Lift+%28Dr.+Bouganis%2C+Dr.+Cervi%C3%B1o%2C+Dr.+Kasten%29","category":"teaching","description":"Seminar Ikeda-Lift (Dr. Bouganis, Dr. CerviÃ±o, Dr. Kasten)","tags":"","semester":"Winter term 2011/12","instructor":"Dr. Bouganis, Dr. CerviÃ±o, Dr. Kasten","course_type":"Seminar","semester_year":2011,"semester_key":"WS2011"},{"id":"teaching-Algebraische Geometrie 1 (Prof. Dr. BÃ¶ckle)","title":"Algebraische Geometrie 1 (Prof. Dr. BÃ¶ckle)","content":"Algebraische Geometrie 1 (Prof. Dr. BÃ¶ckle) HomeMembersResearchPublicationsTeachingLinksContactInterna --> Uni Heidelberg > IWR > ARITHGEO > &nbsp;Members >&nbsp;Algebraische Geometrie 1 [english]&nbsp;|&nbsp;[] Algebraische Geometrie 1 Updates: NÃ¤chstes Semester wird es ein Seminar zur Algebraischen Geometrie 2 geben. Beachten Sie die entsprechende AnkÃ¼ndigung. Die AbschlussprÃ¼fung des Moduls wird eine mÃ¼ndliche PrÃ¼fung am Montag, den 11. Februar sein. Sollten Sie im Zweifel sein, ob ihre Ãbungspunkte ausreichend fÃ¼r eine Zulassung sind, schreiben Sie uns bitte eine Email. FÃ¼r die Terminvergabe und alles Weitere beachten Sie den entsprechenden moodle-Kurs. In der Woche 26.-30.11. ist keine Vorlesung. Ãbung und ZentralÃ¼bung finden statt. Es wird aber kein Ãbungsblatt und folglich keine Ãbungsgruppe am 10.12. geben. Die ZentralÃ¼bung am 11.12. findet statt.In Moodle wurden die ersten Kursmaterialien verfÃ¼gbar gemacht. Die Zettel-Abgabe erfolgt neben dem Seifertraum in INF 288. Die Ãbung findet Montags, 9-11 Uhr in HS2 von INF288 statt. &nbsp;Erster Vorlesungstermin ist Mittwoch, 17. Oktober. Sobald der Dozent Ihnen das Passwort mitgeteilt hat, kÃ¶nnen Sie sich im elearning-Portal Moodle2 der UniversitÃ¤t fÃ¼r den Kurs eintragen. Dort werden Fragen beantwortet und weitere Materialien zur VerfÃ¼gung gestellt. Eine Ãbersicht der Themen und Literatur findet sich in der KVV-AnkÃ¼ndigung der Vorlesung. Ãbungsbetrieb: Der Ãbungsgruppenleiter ist Nithi Rungtanapirom. Bitte melden Sie sich in MÃ¼sli fÃ¼r seine Ãbungsgruppe an. Die Ãbungsaufgaben kommen jeden Freitag auf dieser Seite online und mÃ¼ssen bis 9:15 Uhr am Freitag der darauffolgenden Woche abgegeben werden.&nbsp; Zulassungsbedingung zur AbschlussprÃ¼fung fÃ¼r das Modul ist der Erwerb von 50% der Zettelpunkte (ohne Zusatzaufgaben). AuÃerdem sind Extraaufgaben geplant, die in einer ZentralÃ¼bung besprochen werden. Diese wird Dienstags 16-18h im GebÃ¤ude INF 288, HS 2, stattfinden. FÃ¼r symbolische Berechnungen am Computer gibt es verschiedene Programme:&nbsp;SAGE ist ein fr   Algebraische Geometrie 1 (Prof. Dr. BÃ¶ckle) Winter term 2012/2013 Prof. Dr. BÃ¶ckle Seminar WS WS2012 Prof. Dr. BÃ¶ckle Algebraische Geometrie 1 (Prof. Dr. BÃ¶ckle) ws2012-algebraische-geometrie-1-prof-dr-bckle .md","url":"/teaching/?q=Algebraische+Geometrie+1+%28Prof.+Dr.+B%C3%B6ckle%29","category":"teaching","description":"Algebraische Geometrie 1 (Prof. Dr. BÃ¶ckle)","tags":"","semester":"Winter term 2012/2013","instructor":"Prof. Dr. BÃ¶ckle","course_type":"Seminar","semester_year":2012,"semester_key":"WS2012"},{"id":"teaching-Exercise sessions for Analytic number theory (Qiu)","title":"Exercise sessions for Analytic number theory (Qiu)","content":"Exercise sessions for \"Analytic number theory\" (Qiu) HomeMembersResearchPublicationsTeachingLinksContactInterna --> Uni Heidelberg > IWR > ARITHGEO > &nbsp;Members >&nbsp; [english]&nbsp;|&nbsp;[] Analytische Zahlentheorie I bei Prof. Dr. BÃ¶ge, WS 2012/2013 Bitte melden Sie sich in Muesli an! Vorlesung: Di, Fr 11:00-13:00; Beginn: Di, 16.10.12; &nbsp;&nbsp;&nbsp; &nbsp; &nbsp; &nbsp; &nbsp; &nbsp; &nbsp; &nbsp;&nbsp; ab jetzt (bis auf weiteres) im Hoersaal 4ï¼ï¼ï¼&nbsp;&nbsp;Ãbungen: &nbsp;Mittwochs 14-16 Uhr&nbsp; &nbsp; &nbsp; &nbsp; &nbsp; &nbsp; &nbsp; &nbsp; &nbsp; &nbsp; in den Hoersaal 1 im Mathematischen Institut. &nbsp;&nbsp; &nbsp; &nbsp; &nbsp; &nbsp; &nbsp;AUSSER am Mi. 21.11. &nbsp;&nbsp; &nbsp; &nbsp; &nbsp; &nbsp; &nbsp;Treffen wir am Fr. 23.11. in den Seminarraum 532 in IWR um 16-18 Uhr Skript fÃ¼r den Kurs hier&nbsp;updated: 21.03.2013 Aufgaben Aufgaben 12&nbsp;Wiederholungszettel&nbsp; zu eroertern in der Uebungsstunde am 30.01. &nbsp;Aufgaben 11&nbsp;&nbsp;Aufgaben 10&nbsp;Aufgaben 9&nbsp;Aufgaben&nbsp; 8&nbsp;Aufgaben 7&nbsp;Aufgaben 6&nbsp;Aufgaben 5&nbsp;Aufgaben 4 &nbsp;Aufgaben 3&nbsp;Aufgaben 2&nbsp;&nbsp;Aufgaben 1&nbsp;Bitte geben vor 13 Uhr Freitags ins Postfach neben Hoersaal 2 ab! &nbsp;updated: 25.01.2013 &nbsp;arithgeo@iwr.uni-heidelberg.deLast Update:&nbsp;25.10.2021 - 15:17 &copy; Copyright Universit&auml;t Heidelberg.&nbsp;Impressum.   Exercise sessions for Analytic number theory (Qiu) Winter term 2012/2013 Qiu Ãbung WS WS2012 Qiu Exercise sessions for Analytic number theory (Qiu) ws2012-exercise-sessions-for-analytic-number-theory-qiu .md","url":"/teaching/?q=Exercise+sessions+for+Analytic+number+theory+%28Qiu%29","category":"teaching","description":"Exercise sessions for Analytic number theory (Qiu)","tags":"","semester":"Winter term 2012/2013","instructor":"Qiu","course_type":"Ãbung","semester_year":2012,"semester_key":"WS2012"},{"id":"teaching-Exercise sessions for Lineare Algebra 1 (Dr. Maurischat)","title":"Exercise sessions for Lineare Algebra 1 (Dr. Maurischat)","content":"Exercise sessions for \"Lineare Algebra 1\" (Dr. Maurischat)   Exercise sessions for Lineare Algebra 1 (Dr. Maurischat) Winter term 2012/2013 Dr. Maurischat Ãbung WS WS2012 Dr. Maurischat Exercise sessions for Lineare Algebra 1 (Dr. Maurischat) {\"label\"=>\"Lineare Algebra 1\", \"url\"=>\"http://www.iwr.uni-heidelberg.de/groups/arith-geom/maurischat/la1-ws2012/index.html\"} ws2012-exercise-sessions-for-lineare-algebra-1-dr-maurisc .md","url":"/teaching/?q=Exercise+sessions+for+Lineare+Algebra+1+%28Dr.+Maurischat%29","category":"teaching","description":"Exercise sessions for Lineare Algebra 1 (Dr. Maurischat)","tags":"","semester":"Winter term 2012/2013","instructor":"Dr. Maurischat","course_type":"Ãbung","semester_year":2012,"semester_key":"WS2012"},{"id":"teaching-Seminar Affine algebraische Gruppen (Prof. Dr. BÃ¶ckle, Dr. CerviÃ±o)","title":"Seminar Affine algebraische Gruppen (Prof. Dr. BÃ¶ckle, Dr. CerviÃ±o)","content":"Seminar \"Affine algebraische Gruppen\" (Prof. Dr. BÃ¶ckle, Dr. CerviÃ±o)   Seminar Affine algebraische Gruppen (Prof. Dr. BÃ¶ckle, Dr. CerviÃ±o) Winter term 2012/2013 Prof. Dr. BÃ¶ckle, Dr. CerviÃ±o Seminar WS WS2012 Prof. Dr. BÃ¶ckle, Dr. CerviÃ±o Seminar Affine algebraische Gruppen (Prof. Dr. BÃ¶ckle, Dr. CerviÃ±o) ws2012-seminar-affine-algebraische-gruppen-prof-dr-bckle- .md","url":"/teaching/?q=Seminar+Affine+algebraische+Gruppen+%28Prof.+Dr.+B%C3%B6ckle%2C+Dr.+Cervi%C3%B1o%29","category":"teaching","description":"Seminar Affine algebraische Gruppen (Prof. Dr. BÃ¶ckle, Dr. CerviÃ±o)","tags":"","semester":"Winter term 2012/2013","instructor":"Prof. Dr. BÃ¶ckle, Dr. CerviÃ±o","course_type":"Seminar","semester_year":2012,"semester_key":"WS2012"},{"id":"teaching-Seminar Transcendence theory in positive characteristic (Prof. Dr. BÃ¶ckle, Dr. Hubschmid)","title":"Seminar Transcendence theory in positive characteristic (Prof. Dr. BÃ¶ckle, Dr. Hubschmid)","content":"Seminar \"Transcendence theory in positive characteristic\" (Prof. Dr. BÃ¶ckle, Dr. Hubschmid)   Seminar Transcendence theory in positive characteristic (Prof. Dr. BÃ¶ckle, Dr. Hubschmid) Winter term 2012/2013 Prof. Dr. BÃ¶ckle, Dr. Hubschmid Seminar WS WS2012 Prof. Dr. BÃ¶ckle, Dr. Hubschmid Seminar Transcendence theory in positive characteristic (Prof. Dr. BÃ¶ckle, Dr. Hubschmid) ws2012-seminar-transcendence-theory-in-positive-character .md","url":"/teaching/?q=Seminar+Transcendence+theory+in+positive+characteristic+%28Prof.+Dr.+B%C3%B6ckle%2C+Dr.+Hubschmid%29","category":"teaching","description":"Seminar Transcendence theory in positive characteristic (Prof. Dr. BÃ¶ckle, Dr. Hubschmid)","tags":"","semester":"Winter term 2012/2013","instructor":"Prof. Dr. BÃ¶ckle, Dr. Hubschmid","course_type":"Seminar","semester_year":2012,"semester_key":"WS2012"},{"id":"teaching-Hauptseminar Arithmetik von Zahl- und FunktionenkÃ¶rpern: Recent results towards the BSD conjecture for elliptic curves over Q (Prof. Dr. BÃ¶ckle, Dr. CerviÃ±o, Dr. Hubschmid)","title":"Hauptseminar Arithmetik von Zahl- und FunktionenkÃ¶rpern: Recent results towards the BSD conjecture for elliptic curves over Q (Prof. Dr. BÃ¶ckle, Dr. CerviÃ±o, Dr. Hubschmid)","content":"Hauptseminar Arithmetik von Zahl- und FunktionenkÃ¶rpern: \"Recent results towards the BSD conjecture for elliptic curves over Q\" (Prof. Dr. BÃ¶ckle, Dr. CerviÃ±o, Dr. Hubschmid)   Hauptseminar Arithmetik von Zahl- und FunktionenkÃ¶rpern: Recent results towards the BSD conjecture for elliptic curves over Q (Prof. Dr. BÃ¶ckle, Dr. CerviÃ±o, Dr. Hubschmid) </h4><h4>Winter term 2014/15 Prof. Dr. BÃ¶ckle, Dr. CerviÃ±o, Dr. Hubschmid Seminar WS WS2014 Prof. Dr. BÃ¶ckle, Dr. CerviÃ±o, Dr. Hubschmid Hauptseminar Arithmetik von Zahl- und FunktionenkÃ¶rpern: Recent results towards the BSD conjecture for elliptic curves over Q (Prof. Dr. BÃ¶ckle, Dr. CerviÃ±o, Dr. Hubschmid) ws2014-hauptseminar-arithmetik-von-zahl-und-funktionenkrp .md","url":"/teaching/?q=Hauptseminar+Arithmetik+von+Zahl-+und+Funktionenk%C3%B6rpern%3A+Recent+results+towards+the+BSD+conjecture+for+elliptic+curves+over+Q+%28Prof.+Dr.+B%C3%B6ckle%2C+Dr.+Cervi%C3%B1o%2C+Dr.+Hubschmid%29","category":"teaching","description":"Hauptseminar Arithmetik von Zahl- und FunktionenkÃ¶rpern: Recent results towards the BSD conjecture for elliptic curves over Q (Prof. Dr. BÃ¶ckle, Dr. CerviÃ±o, Dr. Hubschmid)","tags":"","semester":"</h4><h4>Winter term 2014/15","instructor":"Prof. Dr. BÃ¶ckle, Dr. CerviÃ±o, Dr. Hubschmid","course_type":"Seminar","semester_year":2014,"semester_key":"WS2014"},{"id":"teaching-Seminar KlassenkÃ¶rpertheorie Ã¼ber FunktionenkÃ¶rpern und Drinfeld Moduln (Prof. Dr. BÃ¶ckle, Qiu), Seminardetails","title":"Seminar KlassenkÃ¶rpertheorie Ã¼ber FunktionenkÃ¶rpern und Drinfeld Moduln (Prof. Dr. BÃ¶ckle, Qiu), Seminardetails","content":"Seminar \"KlassenkÃ¶rpertheorie Ã¼ber FunktionenkÃ¶rpern und Drinfeld Moduln\" (Prof. Dr. BÃ¶ckle, Qiu), Seminardetails --- Content from https://lsf.uni-heidelberg.de/qisserver/rds?state=verpublish&amp;status=init&amp;vmfile=no&amp;publishid=193882&amp;moduleCall=webInfo&amp;publishConfFile=webInfo&amp;publishSubDir=veranstaltung --- Zur Seitennavigation oder mit Tastenkombination fÃ¼r den accesskey-Taste und Taste 1&nbsp; Zum Seiteninhalt oder mit Tastenkombination fÃ¼r den accesskey und Taste 2&nbsp; &nbsp;&nbsp;&nbsp;&nbsp;&nbsp;&nbsp;&nbsp;&nbsp;&nbsp;&nbsp;&nbsp;&nbsp; LSF: Lehre, Studium und Forschung &nbsp;&nbsp;&nbsp;Informationssystem der Universit&auml;t Heidelberg Startseite &nbsp;&nbsp; Anmelden &nbsp;&nbsp; &nbsp; &nbsp;&nbsp;&nbsp;&nbsp; Veranstaltungen &nbsp;&nbsp;&nbsp;&nbsp; Einrichtungen &nbsp;&nbsp;&nbsp;&nbsp; RÃ¤ume und GebÃ¤ude &nbsp;&nbsp;&nbsp;&nbsp; Personen &nbsp;&nbsp;&nbsp;&nbsp; WiSe 2024/25 Sie sind hier: Hinweis Die angeforderte Auswertung ist zur Zeit nicht verfÃ¼gbar. Problembericht IncorrectObject-001 &nbsp;&nbsp; [TomcatLSF-C (histom18)] Â© Copyright UniversitÃ¤t Heidelberg&nbsp;|&nbsp;Kontakt / Impressum&nbsp;|&nbsp;DatenschutzerklÃ¤rung Zur&uuml;ck HomeMembersResearchPublicationsTeachingLinksContactInterna --> Uni Heidelberg > IWR > ARITHGEO > &nbsp;Members >&nbsp;ws2014-kkt-und-dm [english]&nbsp;|&nbsp;[] Seminar zur KlassenkÃ¶rpertheorie Ã¼ber FunktionenkÃ¶rpern und Drinfeld Moduln Prof. Dr. Gebhard BÃ¶ckle und Yujia Qiu Termin und OrtSeminarprogrammVortrÃ¤geLiteraturAnkÃ¼ndigung und Vorbesprechung Termin und Ort Dienstags 16:15-17:45 Uhr&nbsp;im Wintersemester 2014/2015 im Raum 220, INF 368. Beginn:&nbsp; 14.10.14 Seminarprogramm Das vorlÃ¤ufige Seminarprogramm befindet sich hier. VortrÃ¤ge Bei Interesse oder Fragen zu den VortrÃ¤gen wendet euch bitte an Yujia Qiu. &nbsp;Dies ist die vorlÃ¤ufige Liste der VortrÃ¤ge: &nbsp;Teil I. Skew Polynomial Rings1Skew polynomial rings and q-linear polynomials14.10.142The Moore determinant and zeros of q-linear polynomials21.10.14Teil II. Analysis of Nonarchimedean Valued Fields3Valuations and Hensel's lemma28.10.144Extensions of valuations and Newton polygons04.11.145Analytic functions and normed vector spaces11.11.146Review of Dedekind rings18.11.14Teil III. Drinfeld Modules7Analytic theory I: lattices25.11.148Analytic theory II: Carlitz exponential02.12.149Algebraic theory I: basic notions, torsion and special characteristic09.12.1410Algebraic theory II: homomorphisms and the action of ideals16.12.14Teil IV. Explicit Class Field Theory over Function Fields11Overview of class field theory over global fields13.01.1512Sign normalization and field of definition20.01.1513The sign-normalized Drinfeld modules and reduction27.01.1514Explicit CFT and division fields of Drinfeld-Hayes modules03.02.15Da die VortrÃ¤ge noch angepasst werden, kÃ¶nnen sich die jeweiligen Termine noch um 1-2 Wochen Ã¤ndern. Literatur Dies sind die Hauptquellen, denen wir im Seminar folgen werden:David Goss, Basic Structures of Function Field Arithmetic, Band 35, Ergebnisse der Mathematik und ihrer Grenzgebeite. 3. Folge. Springer Berlin Heidelberg, 1998Richard Pink, Lectures on Drinfeld Modules. 2012Imke Rust and   Seminar KlassenkÃ¶rpertheorie Ã¼ber FunktionenkÃ¶rpern und Drinfeld Moduln (Prof. Dr. BÃ¶ckle, Qiu), Seminardetails </h4><h4>Winter term 2014/15 Prof. Dr. BÃ¶ckle, Qiu Seminar WS WS2014 Prof. Dr. BÃ¶ckle, Qiu Seminar KlassenkÃ¶rpertheorie Ã¼ber FunktionenkÃ¶rpern und Drinfeld Moduln (Prof. Dr. BÃ¶ckle, Qiu), Seminardetails {\"label\"=>\"KlassenkÃ¶rpertheorie Ã¼ber FunktionenkÃ¶rpern und Drinfeld Moduln\", \"url\"=>\"https://lsf.uni-heidelberg.de/qisserver/rds?state=verpublish&amp;status=init&amp;vmfile=no&amp;publishid=193882&amp;moduleCall=webInfo&amp;publishConfFile=webInfo&amp;publishSubDir=veranstaltung\"} ws2014-seminar-klassenkrpertheorie-ber-funktionenkrpern-u .md","url":"/teaching/?q=Seminar+Klassenk%C3%B6rpertheorie+%C3%BCber+Funktionenk%C3%B6rpern+und+Drinfeld+Moduln+%28Prof.+Dr.+B%C3%B6ckle%2C+Qiu%29%2C+Seminardetails","category":"teaching","description":"Seminar KlassenkÃ¶rpertheorie Ã¼ber FunktionenkÃ¶rpern und Drinfeld Moduln (Prof. Dr. BÃ¶ckle, Qiu), Seminardetails","tags":"","semester":"</h4><h4>Winter term 2014/15","instructor":"Prof. Dr. BÃ¶ckle, Qiu","course_type":"Seminar","semester_year":2014,"semester_key":"WS2014"},{"id":"teaching-Vorlesung Automorphe Formen (Prof. Dr. BÃ¶ckle), Modulbeschreibung","title":"Vorlesung Automorphe Formen (Prof. Dr. BÃ¶ckle), Modulbeschreibung","content":"Vorlesung \"Automorphe Formen\" (Prof. Dr. BÃ¶ckle), Modulbeschreibung --- Content from https://lsf.uni-heidelberg.de/qisserver/rds?state=verpublish&amp;status=init&amp;vmfile=no&amp;publishid=193880&amp;moduleCall=webInfo&amp;publishConfFile=webInfo&amp;publishSubDir=veranstaltung --- Zur Seitennavigation oder mit Tastenkombination fÃ¼r den accesskey-Taste und Taste 1&nbsp; Zum Seiteninhalt oder mit Tastenkombination fÃ¼r den accesskey und Taste 2&nbsp; &nbsp;&nbsp;&nbsp;&nbsp;&nbsp;&nbsp;&nbsp;&nbsp;&nbsp;&nbsp;&nbsp;&nbsp; LSF: Lehre, Studium und Forschung &nbsp;&nbsp;&nbsp;Informationssystem der Universit&auml;t Heidelberg Startseite &nbsp;&nbsp; Anmelden &nbsp;&nbsp; &nbsp; &nbsp;&nbsp;&nbsp;&nbsp; Veranstaltungen &nbsp;&nbsp;&nbsp;&nbsp; Einrichtungen &nbsp;&nbsp;&nbsp;&nbsp; RÃ¤ume und GebÃ¤ude &nbsp;&nbsp;&nbsp;&nbsp; Personen &nbsp;&nbsp;&nbsp;&nbsp; WiSe 2024/25 Sie sind hier: Hinweis Die angeforderte Auswertung ist zur Zeit nicht verfÃ¼gbar. Problembericht IncorrectObject-001 &nbsp;&nbsp; [TomcatLSF-A (histom18)] Â© Copyright UniversitÃ¤t Heidelberg&nbsp;|&nbsp;Kontakt / Impressum&nbsp;|&nbsp;DatenschutzerklÃ¤rung Zur&uuml;ck   Vorlesung Automorphe Formen (Prof. Dr. BÃ¶ckle), Modulbeschreibung </h4><h4>Winter term 2014/15 Prof. Dr. BÃ¶ckle Vorlesung WS WS2014 Prof. Dr. BÃ¶ckle Vorlesung Automorphe Formen (Prof. Dr. BÃ¶ckle), Modulbeschreibung {\"label\"=>\"Automorphe Formen\", \"url\"=>\"https://lsf.uni-heidelberg.de/qisserver/rds?state=verpublish&amp;status=init&amp;vmfile=no&amp;publishid=193880&amp;moduleCall=webInfo&amp;publishConfFile=webInfo&amp;publishSubDir=veranstaltung\"} ws2014-vorlesung-automorphe-formen-prof-dr-bckle-modulbes .md","url":"/teaching/?q=Vorlesung+Automorphe+Formen+%28Prof.+Dr.+B%C3%B6ckle%29%2C+Modulbeschreibung","category":"teaching","description":"Vorlesung Automorphe Formen (Prof. Dr. BÃ¶ckle), Modulbeschreibung","tags":"","semester":"</h4><h4>Winter term 2014/15","instructor":"Prof. Dr. BÃ¶ckle","course_type":"Vorlesung","semester_year":2014,"semester_key":"WS2014"},{"id":"teaching-Vorlesung Darstellungen und Invarianten (Dr. CerviÃ±o), Modulbeschreibung","title":"Vorlesung Darstellungen und Invarianten (Dr. CerviÃ±o), Modulbeschreibung","content":"Vorlesung \"Darstellungen und Invarianten\" (Dr.Â CerviÃ±o), Modulbeschreibung   Vorlesung Darstellungen und Invarianten (Dr. CerviÃ±o), Modulbeschreibung </h4><h4>Winter term 2014/15 Dr.Â CerviÃ±o Vorlesung WS WS2014 Dr.Â CerviÃ±o Vorlesung Darstellungen und Invarianten (Dr. CerviÃ±o), Modulbeschreibung {\"label\"=>\"Darstellungen und Invarianten\", \"url\"=>\"https://jmcrv.org/?page_id=253\"} ws2014-vorlesung-darstellungen-und-invarianten-dr-cervio- .md","url":"/teaching/?q=Vorlesung+Darstellungen+und+Invarianten+%28Dr.+Cervi%C3%B1o%29%2C+Modulbeschreibung","category":"teaching","description":"Vorlesung Darstellungen und Invarianten (Dr. CerviÃ±o), Modulbeschreibung","tags":"","semester":"</h4><h4>Winter term 2014/15","instructor":"Dr.Â CerviÃ±o","course_type":"Vorlesung","semester_year":2014,"semester_key":"WS2014"},{"id":"teaching-Hauptseminar Arithmetik von Zahl- und FunktionenkÃ¶rpern: Hodge-Pink structures (Prof. Dr. BÃ¶ckle, Dr. Perkins, Dr. Juan Cervino)","title":"Hauptseminar Arithmetik von Zahl- und FunktionenkÃ¶rpern: Hodge-Pink structures (Prof. Dr. BÃ¶ckle, Dr. Perkins, Dr. Juan Cervino)","content":"Hauptseminar Arithmetik von Zahl- und FunktionenkÃ¶rpern: \"Hodge-Pink structures\" (Prof. Dr. BÃ¶ckle, Dr. Perkins, Dr. Juan Cervino)   Hauptseminar Arithmetik von Zahl- und FunktionenkÃ¶rpern: Hodge-Pink structures (Prof. Dr. BÃ¶ckle, Dr. Perkins, Dr. Juan Cervino) Winter term 2015/16 Prof. Dr. BÃ¶ckle, Dr. Perkins, Dr. Juan Cervino Seminar WS WS2015 Prof. Dr. BÃ¶ckle, Dr. Perkins, Dr. Juan Cervino Hauptseminar Arithmetik von Zahl- und FunktionenkÃ¶rpern: Hodge-Pink structures (Prof. Dr. BÃ¶ckle, Dr. Perkins, Dr. Juan Cervino) ws2015-hauptseminar-arithmetik-von-zahl-und-funktionenkrp .md","url":"/teaching/?q=Hauptseminar+Arithmetik+von+Zahl-+und+Funktionenk%C3%B6rpern%3A+Hodge-Pink+structures+%28Prof.+Dr.+B%C3%B6ckle%2C+Dr.+Perkins%2C+Dr.+Juan+Cervino%29","category":"teaching","description":"Hauptseminar Arithmetik von Zahl- und FunktionenkÃ¶rpern: Hodge-Pink structures (Prof. Dr. BÃ¶ckle, Dr. Perkins, Dr. Juan Cervino)","tags":"","semester":"Winter term 2015/16","instructor":"Prof. Dr. BÃ¶ckle, Dr. Perkins, Dr. Juan Cervino","course_type":"Seminar","semester_year":2015,"semester_key":"WS2015"},{"id":"teaching-Seminar Modularity and Patching (Prof. Dr. BÃ¶ckle, Fischer, GrÃ¤f), Seminardetails","title":"Seminar Modularity and Patching (Prof. Dr. BÃ¶ckle, Fischer, GrÃ¤f), Seminardetails","content":"Seminar \"Modularity and Patching\" (Prof. Dr. BÃ¶ckle, Fischer, GrÃ¤f), Seminardetails   Seminar Modularity and Patching (Prof. Dr. BÃ¶ckle, Fischer, GrÃ¤f), Seminardetails Winter term 2015/16 Prof. Dr. BÃ¶ckle, Fischer, GrÃ¤f Seminar WS WS2015 Prof. Dr. BÃ¶ckle, Fischer, GrÃ¤f Seminar Modularity and Patching (Prof. Dr. BÃ¶ckle, Fischer, GrÃ¤f), Seminardetails ws2015-seminar-modularity-and-patching-prof-dr-bckle-fisc .md","url":"/teaching/?q=Seminar+Modularity+and+Patching+%28Prof.+Dr.+B%C3%B6ckle%2C+Fischer%2C+Gr%C3%A4f%29%2C+Seminardetails","category":"teaching","description":"Seminar Modularity and Patching (Prof. Dr. BÃ¶ckle, Fischer, GrÃ¤f), Seminardetails","tags":"","semester":"Winter term 2015/16","instructor":"Prof. Dr. BÃ¶ckle, Fischer, GrÃ¤f","course_type":"Seminar","semester_year":2015,"semester_key":"WS2015"},{"id":"teaching-Vorlesung Lineare Algebra 1 (Prof. Dr. BÃ¶ckle), Modulbeschreibung","title":"Vorlesung Lineare Algebra 1 (Prof. Dr. BÃ¶ckle), Modulbeschreibung","content":"Vorlesung \"Lineare Algebra 1\" (Prof. Dr. BÃ¶ckle), Modulbeschreibung   Vorlesung Lineare Algebra 1 (Prof. Dr. BÃ¶ckle), Modulbeschreibung Winter term 2015/16 Prof. Dr. BÃ¶ckle Vorlesung WS WS2015 Prof. Dr. BÃ¶ckle Vorlesung Lineare Algebra 1 (Prof. Dr. BÃ¶ckle), Modulbeschreibung {\"label\"=>\"Lineare Algebra 1\", \"url\"=>\"http://www1.iwr.uni-heidelberg.de/groups/arith-geom/LA1-WS201516/LA1_index.html\"} ws2015-vorlesung-lineare-algebra-1-prof-dr-bckle-modulbes .md","url":"/teaching/?q=Vorlesung+Lineare+Algebra+1+%28Prof.+Dr.+B%C3%B6ckle%29%2C+Modulbeschreibung","category":"teaching","description":"Vorlesung Lineare Algebra 1 (Prof. Dr. BÃ¶ckle), Modulbeschreibung","tags":"","semester":"Winter term 2015/16","instructor":"Prof. Dr. BÃ¶ckle","course_type":"Vorlesung","semester_year":2015,"semester_key":"WS2015"},{"id":"teaching-Hauptseminar Arithmetik von Zahl- und FunktionenkÃ¶rpern: Surveys on some conjectures, Themenliste","title":"Hauptseminar Arithmetik von Zahl- und FunktionenkÃ¶rpern: Surveys on some conjectures, Themenliste","content":"Hauptseminar Arithmetik von Zahl- und FunktionenkÃ¶rpern: \"Surveys on some conjectures\", Themenliste HomeMembersResearchPublicationsTeachingLinksContactInterna --> Uni Heidelberg > IWR > ARITHGEO > &nbsp;Teaching >&nbsp; [english]&nbsp;|&nbsp;[] Surveys on conjectures in number and function field arithmetic Hauptseminar Prof. BÃ¶ckle WS 2016/17 &nbsp;We meet thursdays at 9:15 in SR7 (4th floor). The talks are 90 minutes. Speakers and topics:&nbsp;20.10.16 - David Guiraud - Ngo's fundamental Lemma 27.10.16 - David Guiraud - Ngo's fundamental Lemma II 03.11.16 - no talk 10.11.16 - Samuele Anni - Maeda's Conjecture 17.11.16 - Andreas Maurischat - Grothendieck-Katz' p-curvature conjecture 24.11.16 - Andreas Maurischat - Grothendieck-Katz' p-curvature conjecture II 01.12.16 - Konrad Fischer - The Mumford-Tate Conjecture 08.12.16 - Konrad Fischer - The Mumford-Tate Conjecture II 15.12.16 - Rudy Perkins - The Manin-Mumford conjecture for Drinfeld modules 22.12.16 - Rudy Perkins - The Manin-Mumford conjecture for Drinfeld modules II 12.01.16 - Ãzge Ãlkem - The ABC-Conjecture 19.01.16 - Samuele Anni - Coleman's Conjecture 26.01.16 - Gebhard BÃ¶ckle - The local Langlands conjecture, for GL n and beyond 02.02.16 - Gebhard BÃ¶ckle - The local Langlands conjecture, for GL n and beyond II 09.02.16 - Ãzge Ãlkem - The ABC-Conjecture II &nbsp;arithgeo@iwr.uni-heidelberg.deLast Update:&nbsp;27.10.2021 - 11:46 &copy; Copyright Universit&auml;t Heidelberg.&nbsp;Impressum.   Hauptseminar Arithmetik von Zahl- und FunktionenkÃ¶rpern: Surveys on some conjectures, Themenliste Winter term 2016/17 Seminar WS WS2016 Hauptseminar Arithmetik von Zahl- und FunktionenkÃ¶rpern: Surveys on some conjectures, Themenliste ws2016-hauptseminar-arithmetik-von-zahl-und-funktionenkrp .md","url":"/teaching/?q=Hauptseminar+Arithmetik+von+Zahl-+und+Funktionenk%C3%B6rpern%3A+Surveys+on+some+conjectures%2C+Themenliste","category":"teaching","description":"Hauptseminar Arithmetik von Zahl- und FunktionenkÃ¶rpern: Surveys on some conjectures, Themenliste","tags":"","semester":"Winter term 2016/17","instructor":"","course_type":"Seminar","semester_year":2016,"semester_key":"WS2016"},{"id":"teaching-Proseminar Primzahlen und Faktorisierung fÃ¼r die Kryptographie (Prof. Dr. BÃ¶ckle, Fischer), Seminardetails","title":"Proseminar Primzahlen und Faktorisierung fÃ¼r die Kryptographie (Prof. Dr. BÃ¶ckle, Fischer), Seminardetails","content":"Proseminar \"Primzahlen und Faktorisierung fÃ¼r die Kryptographie\" (Prof. Dr. BÃ¶ckle, Fischer), Seminardetails HomeMembersResearchPublicationsTeachingLinksContactInterna --> Uni Heidelberg > IWR > ARITHGEO > &nbsp;Members >&nbsp;Proseminar [english]&nbsp;|&nbsp;[] &nbsp;Proseminar \"Primzahlen und Faktorisierung fÃ¼r die Kryptographie\" im Wintersemester 2016 Prof. Dr. Gebhard BÃ¶ckle, Konrad Fischer&nbsp;Ziel: Das Seminar wird sich nach dem Buch von Crandall und Pomerance richten und unter anderem folgende Themen behandeln: Schnelle Arithmetik, Pseudoprimzahlen, Primzahlentests, Faktorisierungsverfahren, Public-Key-Kryptographie. Eine AnkÃ¼ndigung findet sich hier. &nbsp;Update: Die detaillierte Vortragsliste findet sich hier.&nbsp;Zeit &amp; Ort: Das Seminar findet in Blockform anfang der Semesterferien im Februar 2017 statt. Vorkenntnisse: notwendig: Lineare Algebra 2, nÃ¼tzlich: Algebra, elementare Zahlentheorie Literatur: R. Crandall, C. Pomerance;&nbsp; Prime numbers - a computational perspective; Springer 2005 Wenn Sie Interesse an einem Vortrag haben, melden Sie sich bitte in MÃ¼sli an und kommen Sie zur Vorbesprechung: Dienstag, 18.10.2016 um 13:00 in SR3&nbsp;Bei Fragen schreiben sie mir bitte eine Email. &nbsp;arithgeo@iwr.uni-heidelberg.deLast Update:&nbsp;25.10.2021 - 15:12 &copy; Copyright Universit&auml;t Heidelberg.&nbsp;Impressum.   Proseminar Primzahlen und Faktorisierung fÃ¼r die Kryptographie (Prof. Dr. BÃ¶ckle, Fischer), Seminardetails Winter term 2016/17 Prof. Dr. BÃ¶ckle, Fischer Seminar WS WS2016 Prof. Dr. BÃ¶ckle, Fischer Proseminar Primzahlen und Faktorisierung fÃ¼r die Kryptographie (Prof. Dr. BÃ¶ckle, Fischer), Seminardetails ws2016-proseminar-primzahlen-und-faktorisierung-fr-die-kr .md","url":"/teaching/?q=Proseminar+Primzahlen+und+Faktorisierung+f%C3%BCr+die+Kryptographie+%28Prof.+Dr.+B%C3%B6ckle%2C+Fischer%29%2C+Seminardetails","category":"teaching","description":"Proseminar Primzahlen und Faktorisierung fÃ¼r die Kryptographie (Prof. Dr. BÃ¶ckle, Fischer), Seminardetails","tags":"","semester":"Winter term 2016/17","instructor":"Prof. Dr. BÃ¶ckle, Fischer","course_type":"Seminar","semester_year":2016,"semester_key":"WS2016"},{"id":"teaching-Hauptseminar Arithmetik von Zahl- und FunktionenkÃ¶rpern","title":"Hauptseminar Arithmetik von Zahl- und FunktionenkÃ¶rpern","content":"Hauptseminar Arithmetik von Zahl- und FunktionenkÃ¶rpern HomeMembersResearchPublicationsTeachingLinksContactInterna --> Uni Heidelberg > IWR > ARITHGEO > &nbsp;Members >&nbsp;Hauptseminar WS2017/18 [english]&nbsp;|&nbsp;[] Hauptseminar \"Arithmetik von Zahl- und FunktionenkÃ¶rpern\" (WS 2017/18)&nbsp; Topic: Big image theorems for Hida families We meet thursdays 9-11 in Seminarraum 2. The first talk will take place on October 19. Seminar program &nbsp;arithgeo@iwr.uni-heidelberg.deLast Update:&nbsp;25.10.2021 - 15:14 &copy; Copyright Universit&auml;t Heidelberg.&nbsp;Impressum.   Hauptseminar Arithmetik von Zahl- und FunktionenkÃ¶rpern Winter term 2017/18 Seminar WS WS2017 Hauptseminar Arithmetik von Zahl- und FunktionenkÃ¶rpern ws2017-hauptseminar-arithmetik-von-zahl-und-funktionenkrp .md","url":"/teaching/?q=Hauptseminar+Arithmetik+von+Zahl-+und+Funktionenk%C3%B6rpern","category":"teaching","description":"Hauptseminar Arithmetik von Zahl- und FunktionenkÃ¶rpern","tags":"","semester":"Winter term 2017/18","instructor":"","course_type":"Seminar","semester_year":2017,"semester_key":"WS2017"},{"id":"teaching-Seminar Gruppenkohomologie (Prof. Dr. BÃ¶ckle, Fischer),","title":"Seminar Gruppenkohomologie (Prof. Dr. BÃ¶ckle, Fischer),","content":"Seminar \"Gruppenkohomologie\" (Prof. Dr. BÃ¶ckle, Fischer), HomeMembersResearchPublicationsTeachingLinksContactInterna --> Uni Heidelberg > IWR > ARITHGEO > &nbsp;Members >&nbsp;Seminar Gruppenkohomologie [english]&nbsp;|&nbsp;[] &nbsp;Seminar \"Gruppenkohomologie\" im Wintersemester 2017 Prof. Dr. Gebhard BÃ¶ckle, Konrad Fischer &nbsp;Ziel: Das Seminar wird die (Ko-)Homologie von (diskreten) Gruppen behandeln. Im spÃ¤teren Verlauf werden Anwendungen in der Zahlentheorie (etwa auf die Brauergruppe eines KÃ¶rpers) thematisiert. Eine AnkÃ¼ndigung findet sich hier. Die detaillierte Vortragsliste gibt es hier: Programm. Zeit &amp; Ort: Dienstag 14-16 Uhr im kleinen HÃ¶rsaal des COS (INF 230); Raumnummer 00.001/kHS (kleiner HÃ¶rsaal im Untergeschoss). Erwartete Vorkenntnisse: Kenntnisse aus der Algebra 2: Ringe, Moduln, (exakte) Folgen, AuflÃ¶sungen, Tensorprodukte etc. FÃ¼r spÃ¤tere VortrÃ¤ge kann der Besuch der Alg. Zahlentheorie nÃ¼tzlich sein, ist aber nicht zwingend. Anmeldung: Bitte melden Sie sich in MÃ¼sli an. Einige VortrÃ¤ge wurden bei der Vorbesprechung bereits vergeben. Literatur: Hauptquelle: R. Sharifi - Skript \"Group and Galois Cohomology\" online ErgÃ¤nzend: Jacobson - Basic Algebra 2 und ggf. weitere Vorbesprechung: Wenn Sie Interesse an einem Vortrag haben, kommen Sie bitte zur Vorbesprechung am 27.7. um 16 s.t Uhr im Konferenzraum 5.OG (INF 205) oder schreiben Sie Konrad Fischer eine Email. &nbsp;arithgeo@iwr.uni-heidelberg.deLast Update:&nbsp;25.10.2021 - 15:12 &copy; Copyright Universit&auml;t Heidelberg.&nbsp;Impressum.   Seminar Gruppenkohomologie (Prof. Dr. BÃ¶ckle, Fischer), Winter term 2017/18 Prof. Dr. BÃ¶ckle, Fischer Seminar WS WS2017 Prof. Dr. BÃ¶ckle, Fischer Seminar Gruppenkohomologie (Prof. Dr. BÃ¶ckle, Fischer), ws2017-seminar-gruppenkohomologie-prof-dr-bckle-fischer .md","url":"/teaching/?q=Seminar+Gruppenkohomologie+%28Prof.+Dr.+B%C3%B6ckle%2C+Fischer%29%2C","category":"teaching","description":"Seminar Gruppenkohomologie (Prof. Dr. BÃ¶ckle, Fischer),","tags":"","semester":"Winter term 2017/18","instructor":"Prof. Dr. BÃ¶ckle, Fischer","course_type":"Seminar","semester_year":2017,"semester_key":"WS2017"},{"id":"teaching-Vorlesung Algebraische Zahlentheorie 1 (Prof. Dr. BÃ¶ckle, Dr. Guiraud),","title":"Vorlesung Algebraische Zahlentheorie 1 (Prof. Dr. BÃ¶ckle, Dr. Guiraud),","content":"Vorlesung \"Algebraische Zahlentheorie 1\" (Prof. Dr. BÃ¶ckle, Dr. Guiraud), HomeMembersResearchPublicationsTeachingLinksContactInterna --> Uni Heidelberg > IWR > ARITHGEO > &nbsp;Members >&nbsp;Algebraische Zahlentheorie 1 [english]&nbsp;|&nbsp;[] Vorlesung &quot;Algebraische Zahlentheorie 1&quot; (WS 2017/18) Dozent: Prof. Dr. Gebhard BÃ¶ckle Assistent: Dr. David-A. Guiraud &nbsp;Dienstags 11-13 Uhr Seminarraum SR 005 INF 230 (Ausnahme: 17.10.2017 in SR1 INF 327 Erdgeschoss) Freitags 9-11 Uhr Seminarraum C INF 205 &nbsp;&nbsp;Empfohlene Vorkenntnisse: Algebra 1 und Grundkenntnisse aus Algebra 2 &nbsp; Inhalte: Die Vorlesung Algebraische Zahlentheorie I enthÃ¤lt das Grundwissen Ã¼ber algebraische ZahlkÃ¶rper. Hauptthemen sind: Ganzheit, Ideale, Dedekindringe, Primidealzerlegung, Minkowski-Theorie, Klassenzahl, Dirichletscher Einheitensatz, quadratische ZahlkÃ¶rper, zyklotomische KÃ¶rper, Erweiterungen von Dedekindringen, Lokalisierung, Bewertungen, Fortsetzungen von Bewertungen, Galoistheorie der Bewertungen, Hilbertsche Verzweigungstheorie. Literatur:G.J. Janusz: Algebraic Number FieldsS. Lang: Algebraic Number TheoryD.A. Marcus: Algebraic Number FieldsJ. Milne: Algebraic Number Theory (http://www.jmilne.org/math/CourseNotes/ANT.pdf)J. Neukirch: Algebraische ZahlentheorieÃbungsbetrieb: Organisation Ã¼ber MÃ¼sli und Moodle. PrÃ¼fung:Haupttermin: Donnerstag, 15.2.2018, Uhrzeit und Raum werden noch bekannt gegeben.Nachtermin: TBA &nbsp;arithgeo@iwr.uni-heidelberg.deLast Update:&nbsp;25.10.2021 - 15:14 &copy; Copyright Universit&auml;t Heidelberg.&nbsp;Impressum.   Vorlesung Algebraische Zahlentheorie 1 (Prof. Dr. BÃ¶ckle, Dr. Guiraud), Winter term 2017/18 Prof. Dr. BÃ¶ckle, Dr. Guiraud Vorlesung WS WS2017 Prof. Dr. BÃ¶ckle, Dr. Guiraud Vorlesung Algebraische Zahlentheorie 1 (Prof. Dr. BÃ¶ckle, Dr. Guiraud), ws2017-vorlesung-algebraische-zahlentheorie-1-prof-dr-bck .md","url":"/teaching/?q=Vorlesung+Algebraische+Zahlentheorie+1+%28Prof.+Dr.+B%C3%B6ckle%2C+Dr.+Guiraud%29%2C","category":"teaching","description":"Vorlesung Algebraische Zahlentheorie 1 (Prof. Dr. BÃ¶ckle, Dr. Guiraud),","tags":"","semester":"Winter term 2017/18","instructor":"Prof. Dr. BÃ¶ckle, Dr. Guiraud","course_type":"Vorlesung","semester_year":2017,"semester_key":"WS2017"},{"id":"teaching-Hauptseminar Arithmetik von Zahl- und FunktionenkÃ¶rpern (Prof. Dr. BÃ¶ckle, Dr. Ludwig)","title":"Hauptseminar Arithmetik von Zahl- und FunktionenkÃ¶rpern (Prof. Dr. BÃ¶ckle, Dr. Ludwig)","content":"HauptseminarÂ Arithmetik von Zahl- und FunktionenkÃ¶rpernÂ (Prof. Dr. BÃ¶ckle, Dr. Ludwig)   Hauptseminar Arithmetik von Zahl- und FunktionenkÃ¶rpern (Prof. Dr. BÃ¶ckle, Dr. Ludwig) Winter term 2018/19 Prof. Dr. BÃ¶ckle, Dr. Ludwig Seminar WS WS2018 Prof. Dr. BÃ¶ckle, Dr. Ludwig Hauptseminar Arithmetik von Zahl- und FunktionenkÃ¶rpern (Prof. Dr. BÃ¶ckle, Dr. Ludwig) ws2018-hauptseminar-arithmetik-von-zahl-und-funktionenkrp .md","url":"/teaching/?q=Hauptseminar+Arithmetik+von+Zahl-+und+Funktionenk%C3%B6rpern+%28Prof.+Dr.+B%C3%B6ckle%2C+Dr.+Ludwig%29","category":"teaching","description":"Hauptseminar Arithmetik von Zahl- und FunktionenkÃ¶rpern (Prof. Dr. BÃ¶ckle, Dr. Ludwig)","tags":"","semester":"Winter term 2018/19","instructor":"Prof. Dr. BÃ¶ckle, Dr. Ludwig","course_type":"Seminar","semester_year":2018,"semester_key":"WS2018"},{"id":"teaching-Seminar Algorithmische Algebra (Dr. Maurischat),","title":"Seminar Algorithmische Algebra (Dr. Maurischat),","content":"Seminar \"Algorithmische Algebra\" (Dr. Maurischat), HomeMembersResearchPublicationsTeachingLinksContactInterna --> Uni Heidelberg > IWR > ARITHGEO > &nbsp;Members >&nbsp;Seminar Algorithmische Algebra [english]&nbsp;|&nbsp;[] &nbsp;Seminar \"Algorithmische Algebra\" im Wintersemester 2018/19 Dr. Andreas Maurischat Eine AnkÃ¼ndigung findet sich hier. Die detaillierte Vortragsliste gibt es hier: Programm. &nbsp;Zielgruppe: Bachelor- und Lehramtsstudierende der Mathematik, die Interessedaran haben, wie abstrakte Algebra auch rechnerisch umgesetzt wird. Erwartete Vorkenntnisse: Lineare Algebra 2 und Grundkenntnisse zu endlichen KÃ¶rpern Zeit &amp; Ort: Dienstag 14-16 Uhr, SR 7 Anmeldung: Bitte melden Sie sich per Email bei mir. &nbsp;Hauptquelle: Skript \"Computeralgebra\" von Prof. Matzat &nbsp;arithgeo@iwr.uni-heidelberg.deLast Update:&nbsp;25.10.2021 - 15:08 &copy; Copyright Universit&auml;t Heidelberg.&nbsp;Impressum.   Seminar Algorithmische Algebra (Dr. Maurischat), Winter term 2018/19 Dr. Maurischat Seminar WS WS2018 Dr. Maurischat Seminar Algorithmische Algebra (Dr. Maurischat), ws2018-seminar-algorithmische-algebra-dr-maurischat .md","url":"/teaching/?q=Seminar+Algorithmische+Algebra+%28Dr.+Maurischat%29%2C","category":"teaching","description":"Seminar Algorithmische Algebra (Dr. Maurischat),","tags":"","semester":"Winter term 2018/19","instructor":"Dr. Maurischat","course_type":"Seminar","semester_year":2018,"semester_key":"WS2018"},{"id":"teaching-Seminar Darstellungstheorie von GL_2 (Prof. Dr. BÃ¶ckle, Dr. Ludwig),","title":"Seminar Darstellungstheorie von GL_2 (Prof. Dr. BÃ¶ckle, Dr. Ludwig),","content":"Seminar \"Darstellungstheorie von GL 2\" (Prof. Dr. BÃ¶ckle, Dr. Ludwig),   Seminar Darstellungstheorie von GL_2 (Prof. Dr. BÃ¶ckle, Dr. Ludwig), Winter term 2018/19 Prof. Dr. BÃ¶ckle, Dr. Ludwig Seminar WS WS2018 Prof. Dr. BÃ¶ckle, Dr. Ludwig Seminar Darstellungstheorie von GL_2 (Prof. Dr. BÃ¶ckle, Dr. Ludwig), ws2018-seminar-darstellungstheorie-von-gl2-prof-dr-bckle- .md","url":"/teaching/?q=Seminar+Darstellungstheorie+von+GL_2+%28Prof.+Dr.+B%C3%B6ckle%2C+Dr.+Ludwig%29%2C","category":"teaching","description":"Seminar Darstellungstheorie von GL_2 (Prof. Dr. BÃ¶ckle, Dr. Ludwig),","tags":"","semester":"Winter term 2018/19","instructor":"Prof. Dr. BÃ¶ckle, Dr. Ludwig","course_type":"Seminar","semester_year":2018,"semester_key":"WS2018"},{"id":"teaching-Vorlesung Funktionentheorie 2 (Dr. Maurischat, Quast),","title":"Vorlesung Funktionentheorie 2 (Dr. Maurischat, Quast),","content":"Vorlesung \"Funktionentheorie 2\" (Dr. Maurischat, Quast), HomeMembersResearchPublicationsTeachingLinksContactInterna --> Uni Heidelberg > IWR > ARITHGEO > &nbsp;Members >&nbsp;Funktionentheorie 2 [english]&nbsp;|&nbsp;[] Vorlesung &quot;Funktionentheorie 2&quot; (WS 2018/19) Dozent: Gast-Prof. Dr. Andreas MaurischatAssistent: Julian Quast&nbsp;Vorlesungen:Mittwochs 9-11 Uhr, Seminarraum BFreitags 11-13 Uhr, Seminarraum A&nbsp;Sprechstunde:wird noch bekannt gegeben&nbsp;Ãbungen:Montags 14-16 Uhr, Seminarraum 0.200Dienstags 9-11 Uhr, Seminarraum A&nbsp;PlenarÃ¼bung: Freitag 15 Uhr (s.t.) in Seminarraum A.Termine:Ãbung 1: 26.10.2018Ãbung 2: 16.11.2018 (bis 16 Uhr)Ãbung 3: 30.11.2018&nbsp;PrÃ¼fung:Mo 11.02.19 von 9.30 Uhr bis 11.30 Uhr im HÃ¶rsaal im Mathematikon.Eine ausreichende Beteiligung an der Ãbungen ist notwendig, um an der PrÃ¼fung teilzunehmen.Die Klausureinsicht findet am Do 14.02.19 von 9.00 - 10.00 Uhr im Besprechungsraum 3/414 im 3. OG im Mathematikon statt.&nbsp;Empfohlene Vorkenntnisse: Funktionentheorie 1Literatur: Vorlesungsskript von Hendrik KastenÃbungsblÃ¤tter:Ãbungsblatt 1Ãbungsblatt 2Ãbungsblatt 3Ãbungsblatt 4Ãbungsblatt 5Ãbungsblatt 6Ãbungsblatt 7Ãbungsblatt 8Ãbungsblatt 9 (Korrektur 7.1.19)Ãbungsblatt 10Ãbungsblatt 11Ãbungsblatt 12 &nbsp;arithgeo@iwr.uni-heidelberg.deLast Update:&nbsp;25.10.2021 - 15:10 &copy; Copyright Universit&auml;t Heidelberg.&nbsp;Impressum.   Vorlesung Funktionentheorie 2 (Dr. Maurischat, Quast), Winter term 2018/19 Dr. Maurischat, Quast Vorlesung WS WS2018 Dr. Maurischat, Quast Vorlesung Funktionentheorie 2 (Dr. Maurischat, Quast), ws2018-vorlesung-funktionentheorie-2-dr-maurischat-quast .md","url":"/teaching/?q=Vorlesung+Funktionentheorie+2+%28Dr.+Maurischat%2C+Quast%29%2C","category":"teaching","description":"Vorlesung Funktionentheorie 2 (Dr. Maurischat, Quast),","tags":"","semester":"Winter term 2018/19","instructor":"Dr. Maurischat, Quast","course_type":"Vorlesung","semester_year":2018,"semester_key":"WS2018"},{"id":"teaching-Vorlesung Galoiskohomologie und Galoisdarstellungen (Prof. Dr. BÃ¶ckle),","title":"Vorlesung Galoiskohomologie und Galoisdarstellungen (Prof. Dr. BÃ¶ckle),","content":"Vorlesung \"Galoiskohomologie und Galoisdarstellungen\" (Prof. Dr. BÃ¶ckle), HomeMembersResearchPublicationsTeachingLinksContactInterna --> Uni Heidelberg > IWR > ARITHGEO > &nbsp;Members >&nbsp;Galoiskohomologie [english]&nbsp;|&nbsp;[] Vorlesung &quot;Galoiskohomologie und Galoisdarstellungen&quot; (WS 2018/2019) Dozent: Prof. Dr. Gebhard BÃ¶ckle &nbsp;Vorlesungen:Dienstags 11-13 Uhr, Seminarraum 9 Donnerstags 9-11 Uhr, Seminarraum 2 &nbsp;&nbsp; Ãbungen:Dienstags 16-18 Uhr, Seminarraum 0.200 &nbsp;Die PrÃ¼fung wird am Dienstag, 12. Februar 2019 stattfinden. Eine ausreichende Beteiligung an der Ãbungen ist notwendig, um an der PrÃ¼fung teilzunehmen. &nbsp;Empfohlene Vorkenntnisse: Algebraische Zahlentheorie 2Literatur:R. Sharifi, Algebraic Number Theory, lecture notesJ. Neukirch, Algebraische ZahlentheorieJ. Neukirch, KlassenkÃ¶rpertheorieJ. Neukirch, A. Schmidt, K. Wingberg, Cohomology of Number FieldsE. Artin, J. Tate, Class Field Theory&nbsp;ÃbungsblÃ¤tter:Finden sich unter Moodle. &nbsp;arithgeo@iwr.uni-heidelberg.deLast Update:&nbsp;25.10.2021 - 15:05 &copy; Copyright Universit&auml;t Heidelberg.&nbsp;Impressum.   Vorlesung Galoiskohomologie und Galoisdarstellungen (Prof. Dr. BÃ¶ckle), Winter term 2018/19 Prof. Dr. BÃ¶ckle Vorlesung WS WS2018 Prof. Dr. BÃ¶ckle Vorlesung Galoiskohomologie und Galoisdarstellungen (Prof. Dr. BÃ¶ckle), ws2018-vorlesung-galoiskohomologie-und-galoisdarstellunge .md","url":"/teaching/?q=Vorlesung+Galoiskohomologie+und+Galoisdarstellungen+%28Prof.+Dr.+B%C3%B6ckle%29%2C","category":"teaching","description":"Vorlesung Galoiskohomologie und Galoisdarstellungen (Prof. Dr. BÃ¶ckle),","tags":"","semester":"Winter term 2018/19","instructor":"Prof. Dr. BÃ¶ckle","course_type":"Vorlesung","semester_year":2018,"semester_key":"WS2018"},{"id":"teaching-Hauptseminar Arithmetik von Zahl- und FunktionenkÃ¶rpern (Prof. Dr. BÃ¶ckle)","title":"Hauptseminar Arithmetik von Zahl- und FunktionenkÃ¶rpern (Prof. Dr. BÃ¶ckle)","content":"HauptseminarÂ Arithmetik von Zahl- und FunktionenkÃ¶rpernÂ (Prof. Dr. BÃ¶ckle)   Hauptseminar Arithmetik von Zahl- und FunktionenkÃ¶rpern (Prof. Dr. BÃ¶ckle) Winter term 2019/20 Prof. Dr. BÃ¶ckle Seminar WS WS2019 Prof. Dr. BÃ¶ckle Hauptseminar Arithmetik von Zahl- und FunktionenkÃ¶rpern (Prof. Dr. BÃ¶ckle) ws2019-hauptseminar-arithmetik-von-zahl-und-funktionenkrp .md","url":"/teaching/?q=Hauptseminar+Arithmetik+von+Zahl-+und+Funktionenk%C3%B6rpern+%28Prof.+Dr.+B%C3%B6ckle%29","category":"teaching","description":"Hauptseminar Arithmetik von Zahl- und FunktionenkÃ¶rpern (Prof. Dr. BÃ¶ckle)","tags":"","semester":"Winter term 2019/20","instructor":"Prof. Dr. BÃ¶ckle","course_type":"Seminar","semester_year":2019,"semester_key":"WS2019"},{"id":"teaching-Seminar Affine algebraische Gruppen (Prof. Dr. BÃ¶ckle, Quast)","title":"Seminar Affine algebraische Gruppen (Prof. Dr. BÃ¶ckle, Quast)","content":"Seminar \"Affine algebraische Gruppen\" (Prof. Dr. BÃ¶ckle, Quast) HomeMembersResearchPublicationsTeachingLinksContactInterna --> Uni Heidelberg > IWR > ARITHGEO > &nbsp;Members >&nbsp;Seminar Affine algebraische Gruppen [english]&nbsp;|&nbsp;[] Seminar &quot;Affine algebraische Gruppen&quot; (WS 2019/20) Dozent:Prof. Dr. Gebhard BÃ¶ckleAssistent:Julian Quast&nbsp;Seminarsitzungen:Dienstag 14-16 Uhr s.t., SR 7Der erste Vortrag wird am 29.10.2019 stattfinden (dritte Vorlesungswoche).&nbsp;AushangProgramm&nbsp;Vorlage fÃ¼rs Handout&nbsp;Anmeldung: Eine MÃSLI-Seite ist inzwischen vorhanden. Die Anmeldung zum Seminar ist abgeschlossen.Anmeldungen wie Abmeldungen sind nur dann gÃ¼ltig, wenn sie mir per Mail mitgeteilt werden und im MÃSLI eingetragen werden.Abmeldefrist: Abmeldungen vom Seminar sind nur bis Dienstag, den 08. Oktober 2019 mÃ¶glich. SpÃ¤tere Abmeldungen werden als \"nicht bestanden\" gewertet.&nbsp;VortrÃ¤ge&nbsp;Nr.DatumTitelVortragender1.29.10.2019Gruppenobjekte, Gruppenschemata und GruppenfunktorenJulian Quast2. 05.11.2019Affine algebraische Gruppen und Hopf-AlgebrenJakob Schuhmacher3.12.11.2019Morphismen von GruppenschemataMaximilian Stier4.19.11.2019Algebraische DarstellungenLukas Heger5.26.11.2019AuflÃ¶sbare GruppenMaximilian Stier6.03.12.2019Die Lie-Algebra einer algebraischen GruppeJulian Quast7.10.12.2019ToriLukas Heger8.17.12.2019Unipotente algebraische Gruppen9.07.01.2019Halbeinfache Gruppen&nbsp;Sprechstunde fÃ¼r Vorbesprechungen:Nach Vereinbarung bei Julian Quast in Raum 3/222.&nbsp;Vorkenntnisse: Algebraische Geometrie 1.&nbsp;Literatur:[Mil] J.S. Milne: Algebraic Groups - The Theory of Group Schemes of Finite Type over a Field.&nbsp; &nbsp;arithgeo@iwr.uni-heidelberg.deLast Update:&nbsp;25.10.2021 - 15:10 &copy; Copyright Universit&auml;t Heidelberg.&nbsp;Impressum.   Seminar Affine algebraische Gruppen (Prof. Dr. BÃ¶ckle, Quast) Winter term 2019/20 Prof. Dr. BÃ¶ckle, Quast Seminar WS WS2019 Prof. Dr. BÃ¶ckle, Quast Seminar Affine algebraische Gruppen (Prof. Dr. BÃ¶ckle, Quast) ws2019-seminar-affine-algebraische-gruppen-prof-dr-bckle- .md","url":"/teaching/?q=Seminar+Affine+algebraische+Gruppen+%28Prof.+Dr.+B%C3%B6ckle%2C+Quast%29","category":"teaching","description":"Seminar Affine algebraische Gruppen (Prof. Dr. BÃ¶ckle, Quast)","tags":"","semester":"Winter term 2019/20","instructor":"Prof. Dr. BÃ¶ckle, Quast","course_type":"Seminar","semester_year":2019,"semester_key":"WS2019"},{"id":"teaching-Vorlesung Algebra 1 (Prof. Dr. BÃ¶ckle, Dr. Ludwig)","title":"Vorlesung Algebra 1 (Prof. Dr. BÃ¶ckle, Dr. Ludwig)","content":"Vorlesung \"Algebra 1\" (Prof. Dr. BÃ¶ckle, Dr. Ludwig)   Vorlesung Algebra 1 (Prof. Dr. BÃ¶ckle, Dr. Ludwig) Winter term 2019/20 Prof. Dr. BÃ¶ckle, Dr. Ludwig Vorlesung WS WS2019 Prof. Dr. BÃ¶ckle, Dr. Ludwig Vorlesung Algebra 1 (Prof. Dr. BÃ¶ckle, Dr. Ludwig) ws2019-vorlesung-algebra-1-prof-dr-bckle-dr-ludwig .md","url":"/teaching/?q=Vorlesung+Algebra+1+%28Prof.+Dr.+B%C3%B6ckle%2C+Dr.+Ludwig%29","category":"teaching","description":"Vorlesung Algebra 1 (Prof. Dr. BÃ¶ckle, Dr. Ludwig)","tags":"","semester":"Winter term 2019/20","instructor":"Prof. Dr. BÃ¶ckle, Dr. Ludwig","course_type":"Vorlesung","semester_year":2019,"semester_key":"WS2019"},{"id":"teaching-Seminar Elliptische Kurven (Prof. Dr. BÃ¶ckle, Dr. Ludwig)","title":"Seminar Elliptische Kurven (Prof. Dr. BÃ¶ckle, Dr. Ludwig)","content":"Seminar \"Elliptische Kurven\" (Prof. Dr. BÃ¶ckle, Dr. Ludwig) HomeMembersResearchPublicationsTeachingLinksContactInterna --> Uni Heidelberg > IWR > ARITHGEO > &nbsp;Members >&nbsp;elliptischekurven [english]&nbsp;|&nbsp;[] Seminar Elliptische Kurven (WS 2020/21) Dozent: Prof. Dr. BÃ¶ckle, Dr. Judith Ludwig&nbsp;Beginn: 03.11.20Zeit: Dienstags 14-16 UhrFormat: Online, via Webex. Zur besseren Organisation bitten wir alle Interessenten sich bald mÃ¶glichst im MÃ¼sli in die Sammelgruppe des Seminars einzutragen oder sich per E-Mail an Dr. Ludwig zu wenden. Ende Juli wird es online eine Vorbesprechung geben, die Koordinaten werden Ã¼ber die MÃ¼sli-Gruppe bekannt gegeben. Update (5.10.20): Falls Sie Interesse an einem Vortrag haben, bitte per Email (bei Dr. Ludwig) melden und im MÃ¼sli eintragen. Es gibt noch freie PlÃ¤tze.&nbsp; Thema: Das Seminar bietet eine EinfÃ¼hrung in die Theorie der elliptischen Kurven.&nbsp;Elliptische Kurven sind Kurven (1-dimensionale algebraisch-geometrische Objekte), die durch eine kubische Gleichung der Form y^2=x^3+ax+b bestimmt sind, a und b kÃ¶nnen hier aus unterschiedlichen Zahlbereichen stammen, zum Beispiel aus den ganzen Zahlen. Das Studium der elliptischen Kurven ist interessant, weil es Geometrie, Algebra und Arithmetik verbinden. Wieso? Nun, nach Definition sind elliptische Kurven geometrische Objekte. Die komplexen LÃ¶sungen haben die Form eines Doughnuts, welche sich mittels komplex-analytischer Geometries studieren lassen. Werkzeuge aus der algebraischen Geometrie helfen beim VerstÃ¤ndnis der Strukturen von elliptischen Kurven Ã¼ber allgemeinen KÃ¶rpern. Algebra taucht durch folgende zunÃ¤chst Ã¼berraschende Eigenschaft auf: Man kann auf elliptischen Kurven Punkte addieren! Es stellt sich sogar heraus, dass die Menge der LÃ¶sungen (x,y) einer elliptischen Kurve y^2=x^3+ax+b eine abelsche Gruppe bildet (a und b seien hier Elemente eines KÃ¶rpers K, und x und y ebenfalls, und um wirklich eine Gruppe zu bekommen man muss noch einen Punkt hinzunehmen, den so genannten Punkt \"an unendlichâ). Diese Gruppenstrukt   Seminar Elliptische Kurven (Prof. Dr. BÃ¶ckle, Dr. Ludwig) Winter term 2020/21 Prof. Dr. BÃ¶ckle, Dr. Ludwig Seminar WS WS2020 Prof. Dr. BÃ¶ckle, Dr. Ludwig Seminar Elliptische Kurven (Prof. Dr. BÃ¶ckle, Dr. Ludwig) ws2020-seminar-elliptische-kurven-prof-dr-bckle-dr-ludwig .md","url":"/teaching/?q=Seminar+Elliptische+Kurven+%28Prof.+Dr.+B%C3%B6ckle%2C+Dr.+Ludwig%29","category":"teaching","description":"Seminar Elliptische Kurven (Prof. Dr. BÃ¶ckle, Dr. Ludwig)","tags":"","semester":"Winter term 2020/21","instructor":"Prof. Dr. BÃ¶ckle, Dr. Ludwig","course_type":"Seminar","semester_year":2020,"semester_key":"WS2020"},{"id":"teaching-Vorlesung Algebraische Geometrie 1 (Prof. Dr. BÃ¶ckle, Chilla, Quast)","title":"Vorlesung Algebraische Geometrie 1 (Prof. Dr. BÃ¶ckle, Chilla, Quast)","content":"Vorlesung \"Algebraische Geometrie 1\" (Prof. Dr. BÃ¶ckle, Chilla, Quast) Algebraische Geometrie 1 Wintersemester 2020/21 Organisation Dozent: Prof. Dr. Gebhard B&ouml;ckle Assistent: Paola Chilla, Julian Quast Vorlesung Dienstag 09-11 Uhr asynchron via Moodle Donnerstag 09-11 Uhr asynchron via Moodle Erste Vorlesung: 03.11.2020, asynchron via Moodle Sprechstunde Wir bieten zus&auml;tzlich zur Vorlesung eine synchrone Sprechstunde an. Hier k&ouml;nnten uneingeschr&auml;nkt Fragen zum gesamten Vorlesungsstoff gestellt werden. Donnerstag 10:00-11:00 Uhr synchron via HeiConf Plenar&uuml;bung Dozent: Dr. Judith Ludwig Mo 14-16 Uhr in INF 205 (Mathematikon) / HS Erste Plenar&uuml;bung: 21.10.2019 --> &Uuml;bungsbetrieb Organisation &uuml;ber M&Uuml;SLI. Bitte dort anmelden. Montag 14:15-15:45 Uhr synchron via Webex Mittwoch 14:15-15:45 Uhr synchron via Webex Erste &Uuml;bungen: 09.11. bzw. 11.11.2020   Vorlesung Algebraische Geometrie 1 (Prof. Dr. BÃ¶ckle, Chilla, Quast) Winter term 2020/21 Prof. Dr. BÃ¶ckle, Chilla, Quast Vorlesung WS WS2020 Prof. Dr. BÃ¶ckle, Chilla, Quast Vorlesung Algebraische Geometrie 1 (Prof. Dr. BÃ¶ckle, Chilla, Quast) ws2020-vorlesung-algebraische-geometrie-1-prof-dr-bckle-c .md","url":"/teaching/?q=Vorlesung+Algebraische+Geometrie+1+%28Prof.+Dr.+B%C3%B6ckle%2C+Chilla%2C+Quast%29","category":"teaching","description":"Vorlesung Algebraische Geometrie 1 (Prof. Dr. BÃ¶ckle, Chilla, Quast)","tags":"","semester":"Winter term 2020/21","instructor":"Prof. Dr. BÃ¶ckle, Chilla, Quast","course_type":"Vorlesung","semester_year":2020,"semester_key":"WS2020"},{"id":"teaching-Hauptseminar Arithmetik von Zahl- und FunktionenkÃ¶rpern: Plectic Stark-Heegner points (Prof. Dr. BÃ¶ckle, Dr. GrÃ¤f)","title":"Hauptseminar Arithmetik von Zahl- und FunktionenkÃ¶rpern: Plectic Stark-Heegner points (Prof. Dr. BÃ¶ckle, Dr. GrÃ¤f)","content":"Hauptseminar Arithmetik von Zahl- und FunktionenkÃ¶rpern: \"Plectic Stark-Heegner points\" (Prof. Dr. BÃ¶ckle, Dr. GrÃ¤f)   Hauptseminar Arithmetik von Zahl- und FunktionenkÃ¶rpern: Plectic Stark-Heegner points (Prof. Dr. BÃ¶ckle, Dr. GrÃ¤f) Winter term 2021/22 Prof. Dr. BÃ¶ckle, Dr. GrÃ¤f Seminar WS WS2021 Prof. Dr. BÃ¶ckle, Dr. GrÃ¤f Hauptseminar Arithmetik von Zahl- und FunktionenkÃ¶rpern: Plectic Stark-Heegner points (Prof. Dr. BÃ¶ckle, Dr. GrÃ¤f) ws2021-hauptseminar-arithmetik-von-zahl-und-funktionenkrp .md","url":"/teaching/?q=Hauptseminar+Arithmetik+von+Zahl-+und+Funktionenk%C3%B6rpern%3A+Plectic+Stark-Heegner+points+%28Prof.+Dr.+B%C3%B6ckle%2C+Dr.+Gr%C3%A4f%29","category":"teaching","description":"Hauptseminar Arithmetik von Zahl- und FunktionenkÃ¶rpern: Plectic Stark-Heegner points (Prof. Dr. BÃ¶ckle, Dr. GrÃ¤f)","tags":"","semester":"Winter term 2021/22","instructor":"Prof. Dr. BÃ¶ckle, Dr. GrÃ¤f","course_type":"Seminar","semester_year":2021,"semester_key":"WS2021"},{"id":"teaching-Seminar Abelian Varieties (Dr. Banwait, Prof. Dr. BÃ¶ckle)","title":"Seminar Abelian Varieties (Dr. Banwait, Prof. Dr. BÃ¶ckle)","content":"Seminar \"Abelian Varieties\" (Dr. Banwait, Prof. Dr. BÃ¶ckle) HomeMembersResearchPublicationsTeachingLinksContactInterna --> Uni Heidelberg > IWR > ARITHGEO > &nbsp;Members >&nbsp;deriviertekategorien [english]&nbsp;|&nbsp;[] Seminar on Abelian Varieties (WiSe 2021/22) Dozent: Dr. Barinder Banwait, Prof. Dr. BÃ¶ckle&nbsp;Beginn: 19.10.21Zeit: Tuesdays 14-16 UhrFormat: Hybrid Seminar in SR8 and on Zoom Thema:Das Seminar bietet eine EinfÃ¼hrung in das Thema Abelian Varieties mit Anwendungen in der Algebraischen Geometrie.Bitte sehen Sie die Programm des Kurses.&nbsp; Programm &nbsp;Talks&nbsp;TitleSpeakerDateHandoutDefinitions and Basic ConceptsC V Sriram16.11.2021Handout 1Line bundles and divisors on abelian varietiesC V Sriram23.11.2021Handout 2Torsion and isogeniesB S Banwait30.11.2021&nbsp;The dual abelian varietyMax Stier7.12.2021&nbsp;Polarizations and Weil Pairings&nbsp;14.12.2021&nbsp;The endomorphism ringLukas Heger&nbsp;&nbsp;The Albert classificationLukas Heger&nbsp;&nbsp;&nbsp; &nbsp;arithgeo@iwr.uni-heidelberg.deLast Update:&nbsp;02.02.2022 - 10:36 &copy; Copyright Universit&auml;t Heidelberg.&nbsp;Impressum.   Seminar Abelian Varieties (Dr. Banwait, Prof. Dr. BÃ¶ckle) Winter term 2021/22 Dr. Banwait, Prof. Dr. BÃ¶ckle Seminar WS WS2021 Dr. Banwait, Prof. Dr. BÃ¶ckle Seminar Abelian Varieties (Dr. Banwait, Prof. Dr. BÃ¶ckle) ws2021-seminar-abelian-varieties-dr-banwait-prof-dr-bckle .md","url":"/teaching/?q=Seminar+Abelian+Varieties+%28Dr.+Banwait%2C+Prof.+Dr.+B%C3%B6ckle%29","category":"teaching","description":"Seminar Abelian Varieties (Dr. Banwait, Prof. Dr. BÃ¶ckle)","tags":"","semester":"Winter term 2021/22","instructor":"Dr. Banwait, Prof. Dr. BÃ¶ckle","course_type":"Seminar","semester_year":2021,"semester_key":"WS2021"},{"id":"teaching-Vorlesung Computational Number Theory (Dr. Banwait)","title":"Vorlesung Computational Number Theory (Dr. Banwait)","content":"Vorlesung \"Computational Number Theory\" (Dr. Banwait)   Vorlesung Computational Number Theory (Dr. Banwait) Winter term 2021/22 Dr. Banwait Vorlesung WS WS2021 Dr. Banwait Vorlesung Computational Number Theory (Dr. Banwait) ws2021-vorlesung-computational-number-theory-dr-banwait .md","url":"/teaching/?q=Vorlesung+Computational+Number+Theory+%28Dr.+Banwait%29","category":"teaching","description":"Vorlesung Computational Number Theory (Dr. Banwait)","tags":"","semester":"Winter term 2021/22","instructor":"Dr. Banwait","course_type":"Vorlesung","semester_year":2021,"semester_key":"WS2021"},{"id":"teaching-Vorlesung Ãtale Kohomologie (Prof. Dr. BÃ¶ckle, Chilla, Quast, Sriram)","title":"Vorlesung Ãtale Kohomologie (Prof. Dr. BÃ¶ckle, Chilla, Quast, Sriram)","content":"Vorlesung \"Ãtale Kohomologie\" (Prof. Dr. BÃ¶ckle, Chilla, Quast, Sriram)   Vorlesung Ãtale Kohomologie (Prof. Dr. BÃ¶ckle, Chilla, Quast, Sriram) Winter term 2021/22 Prof. Dr. BÃ¶ckle, Chilla, Quast, Sriram Vorlesung WS WS2021 Prof. Dr. BÃ¶ckle, Chilla, Quast, Sriram Vorlesung Ãtale Kohomologie (Prof. Dr. BÃ¶ckle, Chilla, Quast, Sriram) ws2021-vorlesung-tale-kohomologie-prof-dr-bckle-chilla-qu .md","url":"/teaching/?q=Vorlesung+%C3%89tale+Kohomologie+%28Prof.+Dr.+B%C3%B6ckle%2C+Chilla%2C+Quast%2C+Sriram%29","category":"teaching","description":"Vorlesung Ãtale Kohomologie (Prof. Dr. BÃ¶ckle, Chilla, Quast, Sriram)","tags":"","semester":"Winter term 2021/22","instructor":"Prof. Dr. BÃ¶ckle, Chilla, Quast, Sriram","course_type":"Vorlesung","semester_year":2021,"semester_key":"WS2021"},{"id":"teaching-Seminar on Affine Algebraic Groups (Prof. Dr. BÃ¶ckle, C.V. Sriram)","title":"Seminar on Affine Algebraic Groups (Prof. Dr. BÃ¶ckle, C.V. Sriram)","content":"Seminar on \"Affine Algebraic Groups\" (Prof. Dr. BÃ¶ckle, C.V. Sriram) HomeMembersResearchPublicationsTeachingLinksContactInterna --> Uni Heidelberg > IWR > ARITHGEO > &nbsp;Members >&nbsp;Affine Algebraic Groups [english]&nbsp;|&nbsp;[] Seminar on Affine Algebraic Groups(Winter Semester 2022/23) Organisers: Prof. Dr. G. BÃ¶ckle, C.V. SriramThe study of algebraic groups constitutes a prominant place in mathematical sciences today, having applications in fields such as algebraic geometry, number theory and mathematical physics. This seminar is about one of the building blocks of these groups the affine algebraic groups. We will mainly follow the self contained book of W.C. Waterhouse Introduction to Affine Group Schemes'' during the seminar.&nbsp; The seminar commences on October 25th, 2022 and will be held every Tuesday from 11 AM to 1PM. The location is INF 205. The lecture hall is SR3.The Vorbesprechung will be held on September 30, 2022 from 2 PM to 4 PM; SR2, INF 205Here you will find the announcement of the seminar: Announcement.A detailed description of the talks and also the practicalities of the seminar can be found here.A template(LaTeX file) for creating handout is available here (There are two ways of compiling this file :-(i) using the online editor https://www.overleaf.com/&nbsp; or (ii) downloading a LaTeX editor and compiler. There are loads of them available online(for free). One could download editor https://www.xm1math.net/texmaker/ and compiler https://miktex.org/download).Contact :- sriram.chinthalagiri@iwr.uni-heidelberg.de&nbsp;&nbsp;&nbsp; &nbsp;arithgeo@iwr.uni-heidelberg.deLast Update:&nbsp;18.10.2022 - 13:36 &copy; Copyright Universit&auml;t Heidelberg.&nbsp;Impressum.   Seminar on Affine Algebraic Groups (Prof. Dr. BÃ¶ckle, C.V. Sriram) Winter term 2022/23 Prof. Dr. BÃ¶ckle, C.V. Sriram Seminar WS WS2022 Prof. Dr. BÃ¶ckle, C.V. Sriram Seminar on Affine Algebraic Groups (Prof. Dr. BÃ¶ckle, C.V. Sriram) ws2022-seminar-on-affine-algebraic-groups-prof-dr-bckle-c .md","url":"/teaching/?q=Seminar+on+Affine+Algebraic+Groups+%28Prof.+Dr.+B%C3%B6ckle%2C+C.V.+Sriram%29","category":"teaching","description":"Seminar on Affine Algebraic Groups (Prof. Dr. BÃ¶ckle, C.V. Sriram)","tags":"","semester":"Winter term 2022/23","instructor":"Prof. Dr. BÃ¶ckle, C.V. Sriram","course_type":"Seminar","semester_year":2022,"semester_key":"WS2022"},{"id":"teaching-Vorlesung Lineare Algebra 1 (Prof. Dr. BÃ¶ckle, Dr. Ludwig)","title":"Vorlesung Lineare Algebra 1 (Prof. Dr. BÃ¶ckle, Dr. Ludwig)","content":"Vorlesung \"Lineare Algebra 1\" (Prof. Dr. BÃ¶ckle, Dr. Ludwig) Lineare Algebra I Vorlesung im Wintersemester 2022/23 an der Universit&auml;t Heidelberg Personen: Dozent: &nbsp; Prof. Dr. Gebhard BÃ¶ckle Assistentin: &nbsp; Dr. Judith Ludwig Termine: Vorlesung: &nbsp; Dienstags und Donnerstags von 9:30 - 11:00 Uhr im groÃen HÃ¶rsaal der Chemie, INF 252 (erster Termin: 18.10.). PlenarÃ¼bung: &nbsp; Montags von 14:15 - 15:45 Uhr im groÃen HÃ¶rsaal der Chemie, INF 252 (erster Termin: 24.10.). Tutorien: &nbsp; Die Tutorien finden an verschiedenen Terminen statt, siehe MÃSLI (Beginn 2. Vorlesungswoche). 1. Klausur: &nbsp; Der Termin fÃ¼r die erste Klausur ist Dienstag, der 21.02.2023, von 9:30-11:30 Uhr (Dauer: 120 Minuten). 2. Klausur: &nbsp; Der Termin fÃ¼r die zweite Klausur ist Montag, der 27.03.2023, von 13:30-15:30 Uhr (Dauer: 120 Minuten). AuÃer den beiden Klausuren wird es keine weiteren PrÃ¼fungen geben. Organisatorisches: FÃ¼r die Zulassung zur Modulklausur ist die erfolgreiche Teilnahme am Ãbungsbetrieb erforderlich. Ab dem 20.10. wird jeden Donnerstag gegen 11 Uhr ein Ãbungsblatt auf MaMpf (s.u.) hochgeladen werden. Werfen Sie bitte Ihre LÃ¶sungsvorschlÃ¤ge fÃ¼r das Ãbungsblatt jeweils am Donnerstag der Folgewoche bis 9:00 Uhr in die dafÃ¼r vorgesehenen EinwurfkÃ¤sten im Mathematikon, Im Neuenheimer Feld 205, 1. Etage, ein. Zum Besprechen der LÃ¶sungen und fÃ¼r Fragen zum aktuellen Stoff gibt es Tutorien, fÃ¼r die man sich via MÃSLI (s.u.) anmeldet. Diese werden ab der zweiten Vorlesungswoche stattfinden. Die Abgabe der Ãbungsaufgaben findet in Zweierteams statt, welche zu Beginn des Semesters innerhalb der Tutorien gebildet werden. Wiederholerregelung: Sollten Sie die Klausurzulassung fÃ¼r die Lineare Algebra 1 bereits im Wintersemester 2021/22 erworben haben (LA1/2122), so empfehlen wir dennoch, dass Sie in diesem Semester nochmals aktiv am Ãbungsbetrieb teilnehmen. Melden Sie sich dazu einfach regulÃ¤r in einer Ãbungsgruppe im MÃSLI an. Falls Sie den Ãbungsbetrieb nicht besuchen wollen, aber an der Klausur teilnehmen mÃ¶chten, so tragen   Vorlesung Lineare Algebra 1 (Prof. Dr. BÃ¶ckle, Dr. Ludwig) Winter term 2022/23 Prof. Dr. BÃ¶ckle, Dr. Ludwig Vorlesung WS WS2022 Prof. Dr. BÃ¶ckle, Dr. Ludwig Vorlesung Lineare Algebra 1 (Prof. Dr. BÃ¶ckle, Dr. Ludwig) ws2022-vorlesung-lineare-algebra-1-prof-dr-bckle-dr-ludwi .md","url":"/teaching/?q=Vorlesung+Lineare+Algebra+1+%28Prof.+Dr.+B%C3%B6ckle%2C+Dr.+Ludwig%29","category":"teaching","description":"Vorlesung Lineare Algebra 1 (Prof. Dr. BÃ¶ckle, Dr. Ludwig)","tags":"","semester":"Winter term 2022/23","instructor":"Prof. Dr. BÃ¶ckle, Dr. Ludwig","course_type":"Vorlesung","semester_year":2022,"semester_key":"WS2022"},{"id":"teaching-Hauptseminar Arithmetik von Zahl- und FunktionenkÃ¶rpern: Rigid meromorphic cocycles (Prof. Dr. BÃ¶ckle, Dr. GezmiÅ, Dr. Ludwig)","title":"Hauptseminar Arithmetik von Zahl- und FunktionenkÃ¶rpern: Rigid meromorphic cocycles (Prof. Dr. BÃ¶ckle, Dr. GezmiÅ, Dr. Ludwig)","content":"Hauptseminar Arithmetik von Zahl- und FunktionenkÃ¶rpern: \"Rigid meromorphic cocycles\" (Prof. Dr. BÃ¶ckle, Dr. GezmiÅ, Dr. Ludwig)   Hauptseminar Arithmetik von Zahl- und FunktionenkÃ¶rpern: Rigid meromorphic cocycles (Prof. Dr. BÃ¶ckle, Dr. GezmiÅ, Dr. Ludwig) Winter term 2023/24 Prof. Dr. BÃ¶ckle, Dr. GezmiÅ, Dr. Ludwig Seminar WS WS2023 Prof. Dr. BÃ¶ckle, Dr. GezmiÅ, Dr. Ludwig Hauptseminar Arithmetik von Zahl- und FunktionenkÃ¶rpern: Rigid meromorphic cocycles (Prof. Dr. BÃ¶ckle, Dr. GezmiÅ, Dr. Ludwig) ws2023-hauptseminar-arithmetik-von-zahl-und-funktionenkrp .md","url":"/teaching/?q=Hauptseminar+Arithmetik+von+Zahl-+und+Funktionenk%C3%B6rpern%3A+Rigid+meromorphic+cocycles+%28Prof.+Dr.+B%C3%B6ckle%2C+Dr.+Gezmi%C5%9F%2C+Dr.+Ludwig%29","category":"teaching","description":"Hauptseminar Arithmetik von Zahl- und FunktionenkÃ¶rpern: Rigid meromorphic cocycles (Prof. Dr. BÃ¶ckle, Dr. GezmiÅ, Dr. Ludwig)","tags":"","semester":"Winter term 2023/24","instructor":"Prof. Dr. BÃ¶ckle, Dr. GezmiÅ, Dr. Ludwig","course_type":"Seminar","semester_year":2023,"semester_key":"WS2023"},{"id":"teaching-Proseminar on Quadratic forms(Prof. Dr. BÃ¶ckle, C.V. Sriram)","title":"Proseminar on Quadratic forms(Prof. Dr. BÃ¶ckle, C.V. Sriram)","content":"Proseminar on \"Quadratic forms\"(Prof. Dr. BÃ¶ckle, C.V. Sriram) HomeMembersResearchPublicationsTeachingLinksContactInterna --> Uni Heidelberg > IWR > ARITHGEO > &nbsp;Members >&nbsp;Quadratic forms [english]&nbsp;|&nbsp;[] Proseminar on Quadratic forms(WS 23/24) The aim of this proseminar is to formulate and study a proof of the Hasse principle for quadratic forms. All the necessary tools required such as the field of p-adic numbers, geometry of numbers etc. will be introduced during the course. Here's the proseminar announcement; and here the rubric.Participants are also expected to prepare a handout for their talks. Regarding a sample format of an handout, please refer to a previous proseminar (or come up with your own format:-)).Handout for the last talk. &nbsp;arithgeo@iwr.uni-heidelberg.deLast Update:&nbsp;03.05.2024 - 15:53 &copy; Copyright Universit&auml;t Heidelberg.&nbsp;Impressum.   Proseminar on Quadratic forms(Prof. Dr. BÃ¶ckle, C.V. Sriram) Winter term 2023/24 Prof. Dr. BÃ¶ckle, C.V. Sriram Seminar WS WS2023 Prof. Dr. BÃ¶ckle, C.V. Sriram Proseminar on Quadratic forms(Prof. Dr. BÃ¶ckle, C.V. Sriram) ws2023-proseminar-on-quadratic-formsprof-dr-bckle-cv-srir .md","url":"/teaching/?q=Proseminar+on+Quadratic+forms%28Prof.+Dr.+B%C3%B6ckle%2C+C.V.+Sriram%29","category":"teaching","description":"Proseminar on Quadratic forms(Prof. Dr. BÃ¶ckle, C.V. Sriram)","tags":"","semester":"Winter term 2023/24","instructor":"Prof. Dr. BÃ¶ckle, C.V. Sriram","course_type":"Seminar","semester_year":2023,"semester_key":"WS2023"},{"id":"teaching-Vorlesung Algebra 1 (Prof. Dr. BÃ¶ckle, Shavali)","title":"Vorlesung Algebra 1 (Prof. Dr. BÃ¶ckle, Shavali)","content":"Vorlesung \"Algebra 1\" (Prof. Dr. BÃ¶ckle, Shavali) Algebra I Vorlesung im Wintersemester 2023/24 an der Universit&auml;t Heidelberg Personen: Dozent: &nbsp; Prof. Dr. Gebhard BÃ¶ckle Assistentin: &nbsp; Alireza Shavali Kohshor Termine: Vorlesung: &nbsp; Mittwoch und Freitag von 11:00 - 13:00 Uhr im Physik Kleiner HÃ¶rsaal, HS 2, INF 308 (erster Termin: 18.10.). PlenarÃ¼bung: &nbsp; Mittwoch von 14:15 - 15:45 Uhr im HÃ¶rsaal im Mathematikon (erster Termin: 25.10). Tutorien: &nbsp; Die Tutorien finden montags und dienstags nachmittags statt, siehe MÃSLI (Beginn 2. Vorlesungswoche). 1. Klausur: &nbsp; 07.02.2024, 11:00 - 13:00 Uhr. 2. Klausur: &nbsp; 08.04.2024, 14:00 - 16:00 Uhr. AuÃer den beiden Klausuren wird es keine weiteren PrÃ¼fungen geben. Die PlenarÃ¼bungen finden abwechselnd auf Englisch und Deutsch statt, beginnend am 25 Oktober mit Englisch. Organisatorisches: FÃ¼r die Zulassung zur Modulklausur ist die erfolgreiche Teilnahme am Ãbungsbetrieb erforderlich. Es wird in der Regel jeden Freitag gegen 13 Uhr ein Ãbungsblatt auf MaMpf (s.u.) hochgeladen werden. Werfen Sie bitte Ihre LÃ¶sungsvorschlÃ¤ge fÃ¼r das Ãbungsblatt jeweils am Freitag der Folgewoche bis 11:00 Uhr in die dafÃ¼r vorgesehenen EinwurfkÃ¤sten im Mathematikon, Im Neuenheimer Feld 205, 1. Etage, ein. Zum Besprechen der LÃ¶sungen und fÃ¼r Fragen zum aktuellen Stoff gibt es Tutorien, fÃ¼r die man sich via MÃSLI (s.u.) anmeldet. Die Anmeldung ist per Direktanmeldung ab dem 16.10., 11 Uhr mÃ¶glich Bis Freitag, den 27.10. ist es gestattet, die Ãbungsgruppe zu wechseln, falls ein anderer Termin fÃ¼r Sie vorteilhafter ist und es noch freie PlÃ¤tze gibt. Dies kÃ¶nnen Sie selbst im MÃSLI tun. Die Tutorien starten in der zweiten Vorlesungswoche. Die Abgabe der Ãbungsaufgaben findet in Zweierteams statt, welche zu Beginn des Semesters innerhalb der Tutorien gebildet werden. Wiederholerregelung: Sollten Sie die Klausurzulassung fÃ¼r die Algebra 1 bereits im Wintersemester 2022 erworben haben (A1/22), so empfehlen wir dennoch, dass Sie in diesem Semester nochmals aktiv am Ãbungs   Vorlesung Algebra 1 (Prof. Dr. BÃ¶ckle, Shavali) Winter term 2023/24 Prof. Dr. BÃ¶ckle, Shavali Vorlesung WS WS2023 Prof. Dr. BÃ¶ckle, Shavali Vorlesung Algebra 1 (Prof. Dr. BÃ¶ckle, Shavali) ws2023-vorlesung-algebra-1-prof-dr-bckle-shavali .md","url":"/teaching/?q=Vorlesung+Algebra+1+%28Prof.+Dr.+B%C3%B6ckle%2C+Shavali%29","category":"teaching","description":"Vorlesung Algebra 1 (Prof. Dr. BÃ¶ckle, Shavali)","tags":"","semester":"Winter term 2023/24","instructor":"Prof. Dr. BÃ¶ckle, Shavali","course_type":"Vorlesung","semester_year":2023,"semester_key":"WS2023"},{"id":"teaching-Hauptseminar Arithmetik von Zahl- und FunktionenkÃ¶rpern: Congruence Modules and the WilesâLenstraâDiamond Numerical Criterion in Higher Codimension (Prof. Dr. BÃ¶ckle, Dr. Andrea Conti)","title":"Hauptseminar Arithmetik von Zahl- und FunktionenkÃ¶rpern: Congruence Modules and the WilesâLenstraâDiamond Numerical Criterion in Higher Codimension (Prof. Dr. BÃ¶ckle, Dr. Andrea Conti)","content":"Hauptseminar Arithmetik von Zahl- und FunktionenkÃ¶rpern: \"Congruence Modules and the WilesâLenstraâDiamond Numerical Criterion in Higher Codimension\" (Prof. Dr. BÃ¶ckle, Dr. Andrea Conti)   Hauptseminar Arithmetik von Zahl- und FunktionenkÃ¶rpern: Congruence Modules and the WilesâLenstraâDiamond Numerical Criterion in Higher Codimension (Prof. Dr. BÃ¶ckle, Dr. Andrea Conti) Winter term 2024/25 Prof. Dr. BÃ¶ckle, Dr. Andrea Conti Seminar WS WS2024 Prof. Dr. BÃ¶ckle, Dr. Andrea Conti Hauptseminar Arithmetik von Zahl- und FunktionenkÃ¶rpern: Congruence Modules and the WilesâLenstraâDiamond Numerical Criterion in Higher Codimension (Prof. Dr. BÃ¶ckle, Dr. Andrea Conti) ws2024-hauptseminar-arithmetik-von-zahl-und-funktionenkrp .md","url":"/teaching/?q=Hauptseminar+Arithmetik+von+Zahl-+und+Funktionenk%C3%B6rpern%3A+Congruence+Modules+and+the+Wiles%E2%80%93Lenstra%E2%80%93Diamond+Numerical+Criterion+in+Higher+Codimension+%28Prof.+Dr.+B%C3%B6ckle%2C+Dr.+Andrea+Conti%29","category":"teaching","description":"Hauptseminar Arithmetik von Zahl- und FunktionenkÃ¶rpern: Congruence Modules and the WilesâLenstraâDiamond Numerical Criterion in Higher Codimension (Prof. Dr. BÃ¶ckle, Dr. Andrea Conti)","tags":"","semester":"Winter term 2024/25","instructor":"Prof. Dr. BÃ¶ckle, Dr. Andrea Conti","course_type":"Seminar","semester_year":2024,"semester_key":"WS2024"},{"id":"teaching-Seminar on Commutative Algebra (Prof. Dr. BÃ¶ckle, Dr. Conti)","title":"Seminar on Commutative Algebra (Prof. Dr. BÃ¶ckle, Dr. Conti)","content":"Seminar on \"Commutative Algebra\" (Prof. Dr. BÃ¶ckle, Dr. Conti)   Seminar on Commutative Algebra (Prof. Dr. BÃ¶ckle, Dr. Conti) Winter term 2024/25 Prof. Dr. BÃ¶ckle, Dr. Conti Seminar WS WS2024 Prof. Dr. BÃ¶ckle, Dr. Conti Seminar on Commutative Algebra (Prof. Dr. BÃ¶ckle, Dr. Conti) ws2024-seminar-on-commutative-algebra-prof-dr-bckle-dr-co .md","url":"/teaching/?q=Seminar+on+Commutative+Algebra+%28Prof.+Dr.+B%C3%B6ckle%2C+Dr.+Conti%29","category":"teaching","description":"Seminar on Commutative Algebra (Prof. Dr. BÃ¶ckle, Dr. Conti)","tags":"","semester":"Winter term 2024/25","instructor":"Prof. Dr. BÃ¶ckle, Dr. Conti","course_type":"Seminar","semester_year":2024,"semester_key":"WS2024"},{"id":"teaching-Vorlesung Modularity and Galois Representations (Prof. Dr. BÃ¶ckle, Shavali)","title":"Vorlesung Modularity and Galois Representations (Prof. Dr. BÃ¶ckle, Shavali)","content":"Vorlesung \"Modularity and Galois Representations\" (Prof. Dr. BÃ¶ckle, Shavali) HomeMembersResearchPublicationsTeachingLinksContactInterna --> Uni Heidelberg > IWR > ARITHGEO > &nbsp;Members >&nbsp;Modularity and Galois Representations [english]&nbsp;|&nbsp;[] Modularity and Galois Representations (Winter Semester 2024/25) Organisers: Prof. Dr. G. BÃ¶ckle, A. Shavali&nbsp; Lectures: Wednesdays and Fridays form 11:00 - 13:00 in SR3, Mathematikon, INF 205 (Starting from 16.10.24)Exercise Sessions: Mondays form 14:00 - 16:00 in SR3&nbsp;(Starting from 28.10.24)Exams: TBAThe language of the lectures will be English and the solutions to exercise sheets must be written in English.&nbsp;&nbsp;About the Course: Many questions in number theory can be formulated in terms of representations of the absolute Galois group of the rational numbers Q or of a general number field, typically with coefficients in a p-adic field. One source of such representations is the p-adic etale cohomology of varieties over a number field. The perhaps best known example that fits this description is the Tate module attached to an elliptic curve, or an abelian variety. Another rich source are modular (or more generally algebraic automorphic) forms. Starting with Eichler and Shimura there was a growing expectation that many such representations that arise from geometry also arise from automorphic forms; then the representation would be called modular. A first truly spectacular consequence of this philosophy was Wiles proof of Fermatâs Last Theorem (FLT), completed together with Taylor in 1995. They proved that any semistable elliptic curve wasâ modular. Still before Wiles, in the 1980s Serre formulated conjectures on absolutely irreducible 2-dimensional odd Galois representations of the absolute Galois group of Q with coefficients in finite fields, namely that they should all arise from modular forms. This would also give a proof of FLT, and these conjectures of Serre are now a theorem of Khare and Wintenberger from around 2007. The course will give an introduction to the theme   Vorlesung Modularity and Galois Representations (Prof. Dr. BÃ¶ckle, Shavali) Winter term 2024/25 Prof. Dr. BÃ¶ckle, Shavali Vorlesung WS WS2024 Prof. Dr. BÃ¶ckle, Shavali Vorlesung Modularity and Galois Representations (Prof. Dr. BÃ¶ckle, Shavali) ws2024-vorlesung-modularity-and-galois-representations-pr .md","url":"/teaching/?q=Vorlesung+Modularity+and+Galois+Representations+%28Prof.+Dr.+B%C3%B6ckle%2C+Shavali%29","category":"teaching","description":"Vorlesung Modularity and Galois Representations (Prof. Dr. BÃ¶ckle, Shavali)","tags":"","semester":"Winter term 2024/25","instructor":"Prof. Dr. BÃ¶ckle, Shavali","course_type":"Vorlesung","semester_year":2024,"semester_key":"WS2024"},{"id":"research-Drinfeld modular varieties and Drinfeld modular forms","title":"Drinfeld modular varieties and Drinfeld modular forms","content":"It has been observed that questions in number theory often have analogs over global function fields; then the ring of integers $\\mathbb{Z}$ is replaced by rings like the polynomial ring $\\mathbb{F} p[t]$, and the field of rational numbers $\\mathbb{Q}$ by the field of rational functions over the finite field $\\mathbb{F} p$ of $p$ elements, where $p$ is a prime number. Because methods from algebraic geometry can be applied to function fields, many questions over the latter are more tractable than the corresponding questions over number fields. One particular instance of this is Drinfeld's proof of the global Langlands correspondence for $\\mathrm{GL} 2$ over function fields. In his proof Drinfeld introduced what are now called Drinfeld modular varieties; these are function field analogs of certain Shimura varieties. Their cohomology gives rise to Galois representations and these varieties have an interesting geometry coming from their moduli interpretation.  Drinfeld modular varieties and Drinfeld modular forms drinfeld-modular-forms .md","url":"/research/drinfeld-modular-forms/","category":"research","description":"","tags":"","area":"","collaborators":""},{"id":"research-Galois representations and modular forms","title":"Galois representations and modular forms","content":"A modern way to look at algebraic number theory is to study the group $G {\\mathbb{Q}}$ of symmetries of all finite extension of the rational number $\\mathbb{Q}$, i.e. of all number fields. One way of doing this is via $p$-adic (or complex) Galois representations. These are homomorphisms from $G {\\mathbb{Q}}$ to $\\mathrm{GL} n(K)$ for (the complex or) a $p$-adic field $K$. If one would understand all these, one could deduce many results in number theory. The reason why this approach is promising is that the Langlands program predicts (conjectures) that many interesting Galois representation can be found in (arithmetic) geometry, for instance by studying modular forms or elliptic curves. The most visible success of this method has been the proof of Fermat's Last Theorem by Wiles and Taylor-Wiles building on work of many others.   Galois representations and modular forms galois-representations .md","url":"/research/galois-representations/","category":"research","description":"","tags":"","area":"","collaborators":""},{"id":"publication-the-generic-fiber-of-the-universal-deformation-space-associated-to-a-tame-galois-representation-1998","title":"The generic fiber of the universal deformation space associated to a tame Galois representation","content":"no. 2, 231-246 Gebhard BÃ¶ckle {\"label\"=>\"Journal Link\", \"url\"=>\"http://www.ams.org/mathscinet-getitem?mr=1624537\"} {\"file\"=>\"/assets/uploads/GeneriFiberMM2.pdf\", \"label\"=>\"PDF\", \"url\"=>\"/ag-comp-arith-geom/assets/uploads/GeneriFiberMM2.pdf\"} Published The generic fiber of the universal deformation space associated to a tame Galois representation Journal Article 1998 1998-the-generic-fiber-of-the-universal-deformation-spa .md","url":"/publications/?pub=the-generic-fiber-of-the-universal-deformation-space-associated-to-a-tame-galois-representation-1998","category":"publication","description":"no. 2, 231-246","tags":"","authors":"Gebhard BÃ¶ckle","year":"1998","journal":"","type":"Journal Article","status":"Published"},{"id":"publication-a-local-to-global-principle-for-deformations-of-galois-representations-1999","title":"A local-to-global principle for deformations of Galois representations","content":"199-236 Gebhard BÃ¶ckle {\"label\"=>\"Journal Link\", \"url\"=>\"http://www.ams.org/mathscinet-getitem?mr=1679172\"} {\"file\"=>\"/assets/uploads/LocalGlobalRev3.pdf\", \"label\"=>\"PDF\", \"url\"=>\"/ag-comp-arith-geom/assets/uploads/LocalGlobalRev3.pdf\"} Published A local-to-global principle for deformations of Galois representations Journal Article 1999 1999-a-local-to-global-principle-for-deformations-of-ga .md","url":"/publications/?pub=a-local-to-global-principle-for-deformations-of-galois-representations-1999","category":"publication","description":"199-236","tags":"","authors":"Gebhard BÃ¶ckle","year":"1999","journal":"","type":"Journal Article","status":"Published"},{"id":"publication-explicit-universal-deformations-of-even-galois-representations-1999","title":"Explicit universal deformations of even Galois representations","content":"85-110 Gebhard BÃ¶ckle {\"label\"=>\"Journal Link\", \"url\"=>\"http://www.ams.org/mathscinet-getitem?mr=1711558\"} {\"file\"=>\"/assets/uploads/Boeckle-Explicit.pdf\", \"label\"=>\"PDF\", \"url\"=>\"/ag-comp-arith-geom/assets/uploads/Boeckle-Explicit.pdf\"} Published Explicit universal deformations of even Galois representations Journal Article 1999 1999-explicit-universal-deformations-of-even-galois-rep .md","url":"/publications/?pub=explicit-universal-deformations-of-even-galois-representations-1999","category":"publication","description":"85-110","tags":"","authors":"Gebhard BÃ¶ckle","year":"1999","journal":"","type":"Journal Article","status":"Published"},{"id":"publication-the-prime-to-adjoint-principle-and-unobstructed-galois-deformations-in-the-borel-case-1999","title":"The prime-to-adjoint principle and unobstructed Galois deformations in the Borel case","content":"no. 2, 167-203 Gebhard BÃ¶ckle, A. Mezard {\"label\"=>\"Journal Link\", \"url\"=>\"http://www.ams.org/mathscinet-getitem?mr=1713485\"} {\"file\"=>\"/assets/uploads/AriGebJNTRev2.pdf\", \"label\"=>\"PDF\", \"url\"=>\"/ag-comp-arith-geom/assets/uploads/AriGebJNTRev2.pdf\"} Published The prime-to-adjoint principle and unobstructed Galois deformations in the Borel case Journal Article 1999 1999-the-prime-to-adjoint-principle-and-unobstructed-ga .md","url":"/publications/?pub=the-prime-to-adjoint-principle-and-unobstructed-galois-deformations-in-the-borel-case-1999","category":"publication","description":"no. 2, 167-203","tags":"","authors":"Gebhard BÃ¶ckle, A. Mezard","year":"1999","journal":"","type":"Journal Article","status":"Published"},{"id":"publication-demuskin-groups-with-group-actions-and-applications-to-deformations-of-galois-representations-2000","title":"Demuskin groups with group actions and applications to deformations of Galois representations","content":"no. 2, 109-154 Gebhard BÃ¶ckle {\"label\"=>\"Journal Link\", \"url\"=>\"http://www.ams.org/mathscinet-getitem?mr=1757878\"} {\"file\"=>\"/assets/uploads/DemGps.pdf\", \"label\"=>\"PDF\", \"url\"=>\"/ag-comp-arith-geom/assets/uploads/DemGps.pdf\"} Published Demuskin groups with group actions and applications to deformations of Galois representations Journal Article 2000 2000-demuskin-groups-with-group-actions-and-application .md","url":"/publications/?pub=demuskin-groups-with-group-actions-and-applications-to-deformations-of-galois-representations-2000","category":"publication","description":"no. 2, 109-154","tags":"","authors":"Gebhard BÃ¶ckle","year":"2000","journal":"","type":"Journal Article","status":"Published"},{"id":"publication-a-remark-on-a-finiteness-conjecture-on-mod-p-galois-representations-2001","title":"A remark on a finiteness conjecture on mod $p$ Galois representations","content":"no. 1, 39-44 Gebhard BÃ¶ckle {\"label\"=>\"Journal Link\", \"url\"=>\"http://www.ams.org/mathscinet-getitem?mr=1824882\"} {\"file\"=>\"/assets/uploads/RemOnKhare.pdf\", \"label\"=>\"PDF\", \"url\"=>\"/ag-comp-arith-geom/assets/uploads/RemOnKhare.pdf\"} Published A remark on a finiteness conjecture on mod $p$ Galois representations Journal Article 2001 2001-a-remark-on-a-finiteness-conjecture-on-mod-p-galoi .md","url":"/publications/?pub=a-remark-on-a-finiteness-conjecture-on-mod-p-galois-representations-2001","category":"publication","description":"no. 1, 39-44","tags":"","authors":"Gebhard BÃ¶ckle","year":"2001","journal":"","type":"Journal Article","status":"Published"},{"id":"publication-on-the-density-of-modular-points-in-universal-deformation-spaces-2001","title":"On the density of modular points in universal deformation spaces","content":"no. 5, 985-1007 Gebhard BÃ¶ckle {\"label\"=>\"Journal Link\", \"url\"=>\"http://www.ams.org/mathscinet-getitem?mr=1854117\"} {\"file\"=>\"/assets/uploads/DensityAJMCorr.pdf\", \"label\"=>\"PDF\", \"url\"=>\"/ag-comp-arith-geom/assets/uploads/DensityAJMCorr.pdf\"} Published On the density of modular points in universal deformation spaces Journal Article 2001 2001-on-the-density-of-modular-points-in-universal-defo .md","url":"/publications/?pub=on-the-density-of-modular-points-in-universal-deformation-spaces-2001","category":"publication","description":"no. 5, 985-1007","tags":"","authors":"Gebhard BÃ¶ckle","year":"2001","journal":"","type":"Journal Article","status":"Published"},{"id":"publication-finiteness-conjectures-for-fl-t-analytic-extensions-of-number-fields-2002","title":"Finiteness conjectures for Fl[[T]]-analytic extensions of number fields","content":"no. 2, 257-274 Gebhard BÃ¶ckle {\"label\"=>\"Journal Link\", \"url\"=>\"http://www.ams.org/mathscinet-getitem?mr=1932455\"} {\"file\"=>\"/assets/uploads/DeJongAnJNTbRev2.pdf\", \"label\"=>\"PDF\", \"url\"=>\"/ag-comp-arith-geom/assets/uploads/DeJongAnJNTbRev2.pdf\"} Published Finiteness conjectures for Fl[[T]]-analytic extensions of number fields Journal Article 2002 2002-finiteness-conjectures-for-flt-analytic-extensions .md","url":"/publications/?pub=finiteness-conjectures-for-fl-t-analytic-extensions-of-number-fields-2002","category":"publication","description":"no. 2, 257-274","tags":"","authors":"Gebhard BÃ¶ckle","year":"2002","journal":"","type":"Journal Article","status":"Published"},{"id":"publication-global-l-functions-over-function-fields-2002","title":"Global L-functions over function fields","content":"no. 4, 737-795 Gebhard BÃ¶ckle {\"label\"=>\"Journal Link\", \"url\"=>\"http://www.ams.org/mathscinet-getitem?mr=1924278\"} {\"file\"=>\"/assets/uploads/AofC-MAProof.pdf\", \"label\"=>\"PDF\", \"url\"=>\"/ag-comp-arith-geom/assets/uploads/AofC-MAProof.pdf\"} Published Global L-functions over function fields Journal Article 2002 2002-global-l-functions-over-function-fields .md","url":"/publications/?pub=global-l-functions-over-function-fields-2002","category":"publication","description":"no. 4, 737-795","tags":"","authors":"Gebhard BÃ¶ckle","year":"2002","journal":"","type":"Journal Article","status":"Published"},{"id":"publication-lifting-mod-p-representations-to-characteristic-p2-2003","title":"Lifting mod p representations to characteristic p2","content":"no. 2, 310-337 Gebhard BÃ¶ckle {\"label\"=>\"Journal Link\", \"url\"=>\"http://www.ams.org/mathscinet-getitem?mr=1989890\"} {\"file\"=>\"/assets/uploads/LiftModp2Corr.pdf\", \"label\"=>\"PDF\", \"url\"=>\"/ag-comp-arith-geom/assets/uploads/LiftModp2Corr.pdf\"} Published Lifting mod p representations to characteristic p2 Journal Article 2003 2003-lifting-mod-p-representations-to-characteristic-p2 .md","url":"/publications/?pub=lifting-mod-p-representations-to-characteristic-p2-2003","category":"publication","description":"no. 2, 310-337","tags":"","authors":"Gebhard BÃ¶ckle","year":"2003","journal":"","type":"Journal Article","status":"Published"},{"id":"publication-on-the-isomorphism-r0-t0-2003","title":"On the isomorphism R0 -> T0","content":"no. 1, 217-222 Gebhard BÃ¶ckle {\"label\"=>\"Journal Link\", \"url\"=>\"http://www.ams.org/mathscinet-getitem?mr=2004460\"} {\"file\"=>\"/assets/uploads/KhareAppboeckleNew2.pdf\", \"label\"=>\"PDF\", \"url\"=>\"/ag-comp-arith-geom/assets/uploads/KhareAppboeckleNew2.pdf\"} Published On the isomorphism R0 -> T0 Journal Article 2003 2003-on-the-isomorphism-r0-t0 .md","url":"/publications/?pub=on-the-isomorphism-r0-t0-2003","category":"publication","description":"no. 1, 217-222","tags":"","authors":"Gebhard BÃ¶ckle","year":"2003","journal":"","type":"Journal Article","status":"Published"},{"id":"publication-arithmetic-over-function-fields-a-cohomological-approach-2005","title":"Arithmetic over function fields: a cohomological approach","content":"Arithmetic over function fields: a cohomological approach.. Number fields and function fields---two parallel worlds, Gebhard BÃ¶ckle {\"label\"=>\"Journal Link\", \"url\"=>\"http://www.ams.org/mathscinet-getitem?mr=2176583\"} {\"file\"=>\"/assets/uploads/TexelProcRev.pdf\", \"label\"=>\"PDF\", \"url\"=>\"/ag-comp-arith-geom/assets/uploads/TexelProcRev.pdf\"} Published Arithmetic over function fields: a cohomological approach Journal Article 2005 2005-arithmetic-over-function-fields-a-cohomological-ap .md","url":"/publications/?pub=arithmetic-over-function-fields-a-cohomological-approach-2005","category":"publication","description":"Arithmetic over function fields: a cohomological approach.. Number fields and function fields---two parallel worlds,","tags":"","authors":"Gebhard BÃ¶ckle","year":"2005","journal":"","type":"Journal Article","status":"Published"},{"id":"publication-mod-l-representations-of-arithmetic-fundamental-groups-i-an-analog-of-serre-s-conjecture-for-function-fields-2005","title":"Mod l representations of arithmetic fundamental groups. I. An analog of Serre's conjecture for function fields","content":"no. 2, 337-369 Gebhard BÃ¶ckle, C. Khare {\"label\"=>\"Journal Link\", \"url\"=>\"http://www.ams.org/mathscinet-getitem?mr=2165545\"} {\"file\"=>\"/assets/uploads/BK-Serre-dmj4021.pdf\", \"label\"=>\"PDF\", \"url\"=>\"/ag-comp-arith-geom/assets/uploads/BK-Serre-dmj4021.pdf\"} Published Mod l representations of arithmetic fundamental groups. I. An analog of Serre's conjecture for function fields Journal Article 2005 2005-mod-l-representations-of-arithmetic-fundamental-gr .md","url":"/publications/?pub=mod-l-representations-of-arithmetic-fundamental-groups-i-an-analog-of-serre-s-conjecture-for-function-fields-2005","category":"publication","description":"no. 2, 337-369","tags":"","authors":"Gebhard BÃ¶ckle, C. Khare","year":"2005","journal":"","type":"Journal Article","status":"Published"},{"id":"publication-mod-l-representations-of-arithmetic-fundamental-groups-ii-a-conjecture-of-a-j-de-jong-2006","title":"Mod l representations of arithmetic fundamental groups. II. A conjecture of A. J. de Jong","content":"no. 2, 271-294 Gebhard BÃ¶ckle, C. Khare {\"label\"=>\"Journal Link\", \"url\"=>\"http://www.ams.org/mathscinet-getitem?mr=2218896\"} {\"file\"=>\"/assets/uploads/B-K-deJong-Rev2.pdf\", \"label\"=>\"PDF\", \"url\"=>\"/ag-comp-arith-geom/assets/uploads/B-K-deJong-Rev2.pdf\"} Published Mod l representations of arithmetic fundamental groups. II. A conjecture of A. J. de Jong Journal Article 2006 2006-mod-l-representations-of-arithmetic-fundamental-gr .md","url":"/publications/?pub=mod-l-representations-of-arithmetic-fundamental-groups-ii-a-conjecture-of-a-j-de-jong-2006","category":"publication","description":"no. 2, 271-294","tags":"","authors":"Gebhard BÃ¶ckle, C. Khare","year":"2006","journal":"","type":"Journal Article","status":"Published"},{"id":"publication-presentations-of-universal-deformation-rings-2007","title":"Presentations of universal deformation rings","content":"Presentations of universal deformation rings.. Gebhard BÃ¶ckle {\"label\"=>\"Journal Link\", \"url\"=>\"http://www.ams.org/mathscinet-getitem?mr=2392352\"} {\"file\"=>\"/assets/uploads/OnUDefPres9.pdf\", \"label\"=>\"PDF\", \"url\"=>\"/ag-comp-arith-geom/assets/uploads/OnUDefPres9.pdf\"} Published Presentations of universal deformation rings Journal Article 2007 2007-presentations-of-universal-deformation-rings .md","url":"/publications/?pub=presentations-of-universal-deformation-rings-2007","category":"publication","description":"Presentations of universal deformation rings..","tags":"","authors":"Gebhard BÃ¶ckle","year":"2007","journal":"","type":"Journal Article","status":"Published"},{"id":"publication-uniformizable-families-of-t-motives-2007","title":"Uniformizable families of t-motives","content":"no. 8, 3933-3972 Gebhard BÃ¶ckle, U. Hartl {\"label\"=>\"Journal Link\", \"url\"=>\"http://www.ams.org/mathscinet-getitem?mr=2302519\"} {\"file\"=>\"/assets/uploads/TAMS_4136_Bockle_Hartl.pdf\", \"label\"=>\"PDF\", \"url\"=>\"/ag-comp-arith-geom/assets/uploads/TAMS_4136_Bockle_Hartl.pdf\"} Published Uniformizable families of t-motives Journal Article 2007 2007-uniformizable-families-of-t-motives .md","url":"/publications/?pub=uniformizable-families-of-t-motives-2007","category":"publication","description":"no. 8, 3933-3972","tags":"","authors":"Gebhard BÃ¶ckle, U. Hartl","year":"2007","journal":"","type":"Journal Article","status":"Published"},{"id":"publication-deformations-and-the-rigidity-method-2008","title":"Deformations and the rigidity method","content":"no. 10, 3613-3658 Gebhard BÃ¶ckle {\"label\"=>\"Journal Link\", \"url\"=>\"http://www.ams.org/mathscinet-getitem?mr=2457713\"} {\"file\"=>\"/assets/uploads/Rigidity-CorrectionsThm8.9.pdf\", \"label\"=>\"PDF\", \"url\"=>\"/ag-comp-arith-geom/assets/uploads/Rigidity-CorrectionsThm8.9.pdf\"} Published Deformations and the rigidity method Journal Article 2008 2008-deformations-and-the-rigidity-method .md","url":"/publications/?pub=deformations-and-the-rigidity-method-2008","category":"publication","description":"no. 10, 3613-3658","tags":"","authors":"Gebhard BÃ¶ckle","year":"2008","journal":"","type":"Journal Article","status":"Published"},{"id":"publication-cohomological-theory-of-crystals-over-function-fields-2009","title":"Cohomological Theory of Crystals over Function Fields","content":"Cohomological Theory of Crystals over Function Fields. Gebhard BÃ¶ckle, R. Pink {\"label\"=>\"Journal Link\", \"url\"=>\"http://www.ams.org/mathscinet-getitem?mr=2561048\"} Published Cohomological Theory of Crystals over Function Fields Book 2009 2009-cohomological-theory-of-crystals-over-function-fie .md","url":"/publications/?pub=cohomological-theory-of-crystals-over-function-fields-2009","category":"publication","description":"Cohomological Theory of Crystals over Function Fields.","tags":"","authors":"Gebhard BÃ¶ckle, R. Pink","year":"2009","journal":"","type":"Book","status":"Published"},{"id":"publication-the-miller-rabin-test-with-randomized-exponents-2009","title":"The Miller-Rabin test with randomized exponents","content":"no. 4, 307-319 Gebhard BÃ¶ckle {\"label\"=>\"Journal Link\", \"url\"=>\"http://www.ams.org/mathscinet-getitem?mr=2608598\"} {\"file\"=>\"/assets/uploads/RandomizedMR.pdf\", \"label\"=>\"PDF\", \"url\"=>\"/ag-comp-arith-geom/assets/uploads/RandomizedMR.pdf\"} Published The Miller-Rabin test with randomized exponents Journal Article 2009 2009-the-miller-rabin-test-with-randomized-exponents .md","url":"/publications/?pub=the-miller-rabin-test-with-randomized-exponents-2009","category":"publication","description":"no. 4, 307-319","tags":"","authors":"Gebhard BÃ¶ckle","year":"2009","journal":"","type":"Journal Article","status":"Published"},{"id":"publication-deformation-rings-for-some-mod-3-galois-representations-of-the-absolute-galois-group-of-q3-2010","title":"Deformation rings for some mod 3 Galois representations of the absolute Galois group of Q3","content":"529-542 Gebhard BÃ¶ckle {\"label\"=>\"Journal Link\", \"url\"=>\"http://www.ams.org/mathscinet-getitem?mr=2642411\"} {\"file\"=>\"/assets/uploads/Boeckle-Mod3DefRings-2010_01_11.pdf\", \"label\"=>\"PDF\", \"url\"=>\"/ag-comp-arith-geom/assets/uploads/Boeckle-Mod3DefRings-2010_01_11.pdf\"} Published Deformation rings for some mod 3 Galois representations of the absolute Galois group of Q3 Journal Article 2010 2010-deformation-rings-for-some-mod-3-galois-representa .md","url":"/publications/?pub=deformation-rings-for-some-mod-3-galois-representations-of-the-absolute-galois-group-of-q3-2010","category":"publication","description":"529-542","tags":"","authors":"Gebhard BÃ¶ckle","year":"2010","journal":"","type":"Journal Article","status":"Published"},{"id":"publication-cartier-modules-finiteness-results-2011","title":"Cartier Modules: finiteness results","content":"85-123 Gebhard BÃ¶ckle, M. Blickle {\"label\"=>\"Journal Link\", \"url\"=>\"http://www.ams.org/mathscinet-getitem?mr=2863904\"} {\"file\"=>\"/assets/uploads/BlickleBoeckle-CartierModulesFinitenessResults.pdf\", \"label\"=>\"PDF\", \"url\"=>\"/ag-comp-arith-geom/assets/uploads/BlickleBoeckle-CartierModulesFinitenessResults.pdf\"} Published Cartier Modules: finiteness results Journal Article 2011 2011-cartier-modules-finiteness-results .md","url":"/publications/?pub=cartier-modules-finiteness-results-2011","category":"publication","description":"85-123","tags":"","authors":"Gebhard BÃ¶ckle, M. Blickle","year":"2011","journal":"","type":"Journal Article","status":"Published"},{"id":"publication-cohomological-theory-of-crystals-over-function-fields-and-applications-in-arithmetic-geometry-in-2012","title":"Cohomological theory of crystals over function fields and applications. \tIn \"Arithmetic Geometry in","content":"Cohomological theory of crystals over function fields and applications. In \"Arithmetic Geometry in . , to appear Gebhard BÃ¶ckle {\"file\"=>\"/assets/uploads/LectureNotesOnCrystals-Barcelona2012-01-24.pdf\", \"label\"=>\"PDF\", \"url\"=>\"/ag-comp-arith-geom/assets/uploads/LectureNotesOnCrystals-Barcelona2012-01-24.pdf\"} Published Cohomological theory of crystals over function fields and applications. \tIn \"Arithmetic Geometry in Lecture Series and Surveys 2012 2012-cohomological-theory-of-crystals-over-function-fie .md","url":"/publications/?pub=cohomological-theory-of-crystals-over-function-fields-and-applications-in-arithmetic-geometry-in-2012","category":"publication","description":"Cohomological theory of crystals over function fields and applications. In \"Arithmetic Geometry in . , to appear","tags":"","authors":"Gebhard BÃ¶ckle","year":"2012","journal":"","type":"Lecture Series and Surveys","status":"Published"},{"id":"publication-on-computing-quaternion-quotient-graphs-for-function-fields-2012","title":"On computing quaternion quotient graphs for function fields","content":"no. 1, 73-99 Gebhard BÃ¶ckle, R. Butenuth {\"label\"=>\"Journal Link\", \"url\"=>\"http://jtnb.cedram.org/jtnb-bin/item?id=JTNB_2012__24_1_73_0\"} {\"file\"=>\"/assets/uploads/Proofs-Boeckle-Butenuth.pdf\", \"label\"=>\"PDF\", \"url\"=>\"/ag-comp-arith-geom/assets/uploads/Proofs-Boeckle-Butenuth.pdf\"} Published On computing quaternion quotient graphs for function fields Journal Article 2012 2012-on-computing-quaternion-quotient-graphs-for-functi .md","url":"/publications/?pub=on-computing-quaternion-quotient-graphs-for-function-fields-2012","category":"publication","description":"no. 1, 73-99","tags":"","authors":"Gebhard BÃ¶ckle, R. Butenuth","year":"2012","journal":"","type":"Journal Article","status":"Published"},{"id":"publication-algebraic-hecke-characters-and-compatible-systems-of-abelian-mod-p-galois-representations-over-global-fields-2013","title":"Algebraic Hecke characters and compatible systems of abelian mod p Galois representations over global fields","content":"no. 3-4, 303-331 Gebhard BÃ¶ckle {\"label\"=>\"Journal Link\", \"url\"=>\"http://www.springerlink.com/content/ll5v246782212835/\"} {\"file\"=>\"/assets/uploads/Boeckle-AlgHeckeCharsAndStrictlyCompSys.pdf\", \"label\"=>\"PDF\", \"url\"=>\"/ag-comp-arith-geom/assets/uploads/Boeckle-AlgHeckeCharsAndStrictlyCompSys.pdf\"} Published Algebraic Hecke characters and compatible systems of abelian mod p Galois representations over global fields Journal Article 2013 2013-algebraic-hecke-characters-and-compatible-systems- .md","url":"/publications/?pub=algebraic-hecke-characters-and-compatible-systems-of-abelian-mod-p-galois-representations-over-global-fields-2013","category":"publication","description":"no. 3-4, 303-331","tags":"","authors":"Gebhard BÃ¶ckle","year":"2013","journal":"","type":"Journal Article","status":"Published"},{"id":"publication-deformations-of-galois-representations-2013","title":"Deformations of Galois representations","content":"Deformations of Galois representations. Elliptic curves, Hilbert modular forms and Galois deformations, Gebhard BÃ¶ckle {\"label\"=>\"Journal Link\", \"url\"=>\"http://link.springer.com/chapter/10.1007%2F978-3-0348-0618-3_2\"} {\"file\"=>\"/assets/uploads/Boeckle-Barcelona-DefTheory-Rev.pdf\", \"label\"=>\"PDF\", \"url\"=>\"/ag-comp-arith-geom/assets/uploads/Boeckle-Barcelona-DefTheory-Rev.pdf\"} Published Deformations of Galois representations Book Chapter 2013 2013-deformations-of-galois-representations .md","url":"/publications/?pub=deformations-of-galois-representations-2013","category":"publication","description":"Deformations of Galois representations. Elliptic curves, Hilbert modular forms and Galois deformations,","tags":"","authors":"Gebhard BÃ¶ckle","year":"2013","journal":"","type":"Book Chapter","status":"Published"},{"id":"publication-galois-representations-travaux-mathÃ©matiques-vol-xxiii-2013","title":"Galois representations.Travaux mathÃ©matiques. Vol. XXIII","content":"Galois representations.Travaux mathÃ©matiques. Vol. XXIII. Travaux mathÃ©matiques. Gebhard BÃ¶ckle {\"file\"=>\"/assets/uploads/Boeckle.pdf\", \"label\"=>\"PDF\", \"url\"=>\"http://wwwfr.uni.lu/content/download/75430/940982/file/Boeckle.pdf\"} Published Galois representations.Travaux mathÃ©matiques. Vol. XXIII Lecture Series and Surveys 2013 2013-galois-representationstravaux-mathmatiques-vol-xxi .md","url":"/publications/?pub=galois-representations-travaux-math%C3%A9matiques-vol-xxiii-2013","category":"publication","description":"Galois representations.Travaux mathÃ©matiques. Vol. XXIII. Travaux mathÃ©matiques.","tags":"","authors":"Gebhard BÃ¶ckle","year":"2013","journal":"","type":"Lecture Series and Surveys","status":"Published"},{"id":"publication-the-distribution-of-the-zeros-of-the-goss-zeta-function-for-2013","title":"The distribution of the zeros of the Goss zeta-function for","content":"no. 3-4, 835â861. Gebhard BÃ¶ckle {\"label\"=>\"Journal Link\", \"url\"=>\"http://www.ams.org/leavingmsn?url=http://dx.doi.org/10.1007/s00209-013-1162-9\"} {\"file\"=>\"/assets/uploads/ZeroDistribForOneA.pdf\", \"label\"=>\"PDF\", \"url\"=>\"/ag-comp-arith-geom/assets/uploads/ZeroDistribForOneA.pdf\"} Published The distribution of the zeros of the Goss zeta-function for Journal Article 2013 2013-the-distribution-of-the-zeros-of-the-goss-zeta-fun .md","url":"/publications/?pub=the-distribution-of-the-zeros-of-the-goss-zeta-function-for-2013","category":"publication","description":"no. 3-4, 835â861.","tags":"","authors":"Gebhard BÃ¶ckle","year":"2013","journal":"","type":"Journal Article","status":"Published"},{"id":"publication-computations-with-modular-forms-2014","title":"Computations with Modular Forms","content":"Computations with Modular Forms. Gebhard BÃ¶ckle, G. Wiese {\"label\"=>\"Journal Link\", \"url\"=>\"http://link.springer.com/book/10.1007/978-3-319-03847-6\"} Published Computations with Modular Forms Book 2014 2014-computations-with-modular-forms .md","url":"/publications/?pub=computations-with-modular-forms-2014","category":"publication","description":"Computations with Modular Forms.","tags":"","authors":"Gebhard BÃ¶ckle, G. Wiese","year":"2014","journal":"","type":"Book","status":"Published"},{"id":"publication-hecke-characters-associated-to-drinfeld-modular-forms-2015","title":"Hecke characters associated to Drinfeld modular forms","content":"53 p Gebhard BÃ¶ckle, T. Centeleghe {\"label\"=>\"Journal Link\", \"url\"=>\"http://dx.doi.org/10.1112/S0010437X15007290\"} {\"file\"=>\"/assets/uploads/Boeckle-Centeleghe-HeckeCharactersAssociatedToDrinfeldModularForms.pdf\", \"label\"=>\"PDF\", \"url\"=>\"/ag-comp-arith-geom/assets/uploads/Boeckle-Centeleghe-HeckeCharactersAssociatedToDrinfeldModularForms.pdf\"} Published Hecke characters associated to Drinfeld modular forms Journal Article 2015 2015-hecke-characters-associated-to-drinfeld-modular-fo .md","url":"/publications/?pub=hecke-characters-associated-to-drinfeld-modular-forms-2015","category":"publication","description":"53 p","tags":"","authors":"Gebhard BÃ¶ckle, T. Centeleghe","year":"2015","journal":"","type":"Journal Article","status":"Published"},{"id":"publication-independence-of-l-adic-representations-of-geometric-galois-groups-2015","title":"Independence of l-adic representations of geometric Galois groups","content":"25 p Gebhard BÃ¶ckle, W. Gajda, S. Petersen {\"label\"=>\"Journal Link\", \"url\"=>\"http://dx.doi.org/10.1515/crelle-2015-0024\"} {\"file\"=>\"/assets/uploads/Boeckle-Gajda-Petersen-crelle-2015-0024.pdf\", \"label\"=>\"PDF\", \"url\"=>\"/ag-comp-arith-geom/assets/uploads/Boeckle-Gajda-Petersen-crelle-2015-0024.pdf\"} Published Independence of l-adic representations of geometric Galois groups Journal Article 2015 2015-independence-of-l-adic-representations-of-geometri .md","url":"/publications/?pub=independence-of-l-adic-representations-of-geometric-galois-groups-2015","category":"publication","description":"25 p","tags":"","authors":"Gebhard BÃ¶ckle, W. Gajda, S. Petersen","year":"2015","journal":"","type":"Journal Article","status":"Published"},{"id":"publication-irreducibility-of-versal-deformation-rings-in-the-p-p-case-for-2-dimensional-representations-2015","title":"Irreducibility of versal deformation rings in the (p,p)-case for 2-dimensional representations","content":"81â123 Gebhard BÃ¶ckle, A.-K. Juschka {\"label\"=>\"Journal Link\", \"url\"=>\"http://www.sciencedirect.com/science/article/pii/S002186931500352X\"} {\"file\"=>\"/assets/uploads/BoeckleJuschka-Irreducibility.pdf\", \"label\"=>\"PDF\", \"url\"=>\"/ag-comp-arith-geom/assets/uploads/BoeckleJuschka-Irreducibility.pdf\"} Published Irreducibility of versal deformation rings in the (p,p)-case for 2-dimensional representations Journal Article 2015 2015-irreducibility-of-versal-deformation-rings-in-the- .md","url":"/publications/?pub=irreducibility-of-versal-deformation-rings-in-the-p-p-case-for-2-dimensional-representations-2015","category":"publication","description":"81â123","tags":"","authors":"Gebhard BÃ¶ckle, A.-K. Juschka","year":"2015","journal":"","type":"Journal Article","status":"Published"},{"id":"publication-a-control-theorem-for-p-adic-automorphic-forms-and-teitelbaum-s-l-invariant-the-ramanujan-journal-50-1-13-43-2019-2019","title":"A control theorem for p-adic automorphic forms and Teitelbaum's L-invariant (The Ramanujan Journal 50(1), 13-43, 2019","content":"13-43, 2019 Peter GrÃ¤f {\"label\"=>\"Journal Link\", \"url\"=>\"http://dx.doi.org/10.1007/s11139-019-00160-1\"} Published A control theorem for p-adic automorphic forms and Teitelbaum's L-invariant (The Ramanujan Journal 50(1), 13-43, 2019 Journal Article 2019 2019-a-control-theorem-for-p-adic-automorphic-forms-and .md","url":"/publications/?pub=a-control-theorem-for-p-adic-automorphic-forms-and-teitelbaum-s-l-invariant-the-ramanujan-journal-50-1-13-43-2019-2019","category":"publication","description":"13-43, 2019","tags":"","authors":"Peter GrÃ¤f","year":"2019","journal":"","type":"Journal Article","status":"Published"},{"id":"publication-computing-l-invariants-via-the-greenberg-stevens-formula-joint-with-s-anni-g-bÃ¶ckle-a-troya-2019","title":"Computing L-invariants via the Greenberg-Stevens formula (joint with S. Anni, G. BÃ¶ckle, A. Troya","content":"Computing L-invariants via the Greenberg-Stevens formula (joint with S. Anni, G. BÃ¶ckle, A. Troya Peter GrÃ¤f {\"label\"=>\"Journal Link\", \"url\"=>\"https://jtnb.centre-mersenne.org/article/JTNB_2019__31_3_727_0.pdf\"} Published Computing L-invariants via the Greenberg-Stevens formula (joint with S. Anni, G. BÃ¶ckle, A. Troya Journal Article 2019 2019-computing-l-invariants-via-the-greenberg-stevens-f .md","url":"/publications/?pub=computing-l-invariants-via-the-greenberg-stevens-formula-joint-with-s-anni-g-b%C3%B6ckle-a-troya-2019","category":"publication","description":"Computing L-invariants via the Greenberg-Stevens formula (joint with S. Anni, G. BÃ¶ckle, A. Troya","tags":"","authors":"Peter GrÃ¤f","year":"2019","journal":"","type":"Journal Article","status":"Published"},{"id":"publication-a-hecke-equivariant-decomposition-of-spaces-of-drinfeld-cusp-forms-via-representation-theory-and-an-investigation-of-its-subfactors-joint-with-g-bÃ¶ckle-r-perkins-2021","title":"A Hecke-equivariant decomposition of spaces of Drinfeld cusp forms via representation theory, and an investigation of its subfactors (joint with G. BÃ¶ckle, R. Perkins","content":"A Hecke-equivariant decomposition of spaces of Drinfeld cusp forms via representation theory, and an investigation of its subfactors (joint with G. BÃ¶ckle, R. Perkins Peter GrÃ¤f {\"label\"=>\"Journal Link\", \"url\"=>\"https://link.springer.com/article/10.1007%2Fs40993-021-00254-0\"} Published A Hecke-equivariant decomposition of spaces of Drinfeld cusp forms via representation theory, and an investigation of its subfactors (joint with G. BÃ¶ckle, R. Perkins Journal Article 2021 2021-a-hecke-equivariant-decomposition-of-spaces-of-dri .md","url":"/publications/?pub=a-hecke-equivariant-decomposition-of-spaces-of-drinfeld-cusp-forms-via-representation-theory-and-an-investigation-of-its-subfactors-joint-with-g-b%C3%B6ckle-r-perkins-2021","category":"publication","description":"A Hecke-equivariant decomposition of spaces of Drinfeld cusp forms via representation theory, and an investigation of its subfactors (joint with G. BÃ¶ckle, R. Perkins","tags":"","authors":"Peter GrÃ¤f","year":"2021","journal":"","type":"Journal Article","status":"Published"},{"id":"publication-an-eichler-shimura-isomorphism-over-function-fields-between-drinfeld-modular-forms-and-cohomology-cl-2024","title":"An Eichler-Shimura isomorphism over function fields between Drinfeld modular forms and cohomology cl","content":"183 pages Gebhard BÃ¶ckle {\"file\"=>\"/assets/uploads/EiShNew.pdf\", \"label\"=>\"PDF\", \"url\"=>\"/ag-comp-arith-geom/assets/uploads/EiShNew.pdf\"} Published An Eichler-Shimura isomorphism over function fields between Drinfeld modular forms and cohomology cl Preprint 2024 2024-an-eichler-shimura-isomorphism-over-function-field .md","url":"/publications/?pub=an-eichler-shimura-isomorphism-over-function-fields-between-drinfeld-modular-forms-and-cohomology-cl-2024","category":"publication","description":"183 pages","tags":"","authors":"Gebhard BÃ¶ckle","year":"2024","journal":"","type":"Preprint","status":"Published"},{"id":"publication-joint-with-a-k-juschka-equidimensionality-of-universal-pseudodeformation-rings-in-characteristic-2024","title":"(joint with A.-K. Juschka) Equidimensionality of universal pseudodeformation rings in characteristic","content":"91 pages Gebhard BÃ¶ckle, A.-K. Juschka {\"file\"=>\"/assets/uploads/Boeckle-Juschka-Pseudo-20230701.pdf\", \"label\"=>\"PDF\", \"url\"=>\"/ag-comp-arith-geom/assets/uploads/Boeckle-Juschka-Pseudo-20230701.pdf\"} Published (joint with A.-K. Juschka) Equidimensionality of universal pseudodeformation rings in characteristic Preprint 2024 2024-joint-with-a-k-juschka-equidimensionality-of-unive .md","url":"/publications/?pub=joint-with-a-k-juschka-equidimensionality-of-universal-pseudodeformation-rings-in-characteristic-2024","category":"publication","description":"91 pages","tags":"","authors":"Gebhard BÃ¶ckle, A.-K. Juschka","year":"2024","journal":"","type":"Preprint","status":"Published"},{"id":"publication-joint-with-m-blickle-cartier-crystals-an-overview-can-be-found-in-a-chapter-of-the-habilitation-2024","title":"(joint with M. Blickle) Cartier Crystals. An overview can be found in a chapter of the habilitation","content":"(joint with M. Blickle) Cartier Crystals. An overview can be found in a chapter of the habilitation . Cartier Crystals. An overview can be found in a chapter of the habilitation treatise of M.Blickle Gebhard BÃ¶ckle, M. Blickle Published (joint with M. Blickle) Cartier Crystals. An overview can be found in a chapter of the habilitation In Preparation 2024 2024-joint-with-m-blickle-cartier-crystals-an-overview- .md","url":"/publications/?pub=joint-with-m-blickle-cartier-crystals-an-overview-can-be-found-in-a-chapter-of-the-habilitation-2024","category":"publication","description":"(joint with M. Blickle) Cartier Crystals. An overview can be found in a chapter of the habilitation . Cartier Crystals. An overview can be found in a chapter of the habilitation treatise of M.Blickle","tags":"","authors":"Gebhard BÃ¶ckle, M. Blickle","year":"2024","journal":"","type":"In Preparation","status":"Published"},{"id":"publication-joint-with-m-dettweiler-division-towers-for-triangle-shimura-curves-2024","title":"(joint with M. Dettweiler) Division Towers for Triangle Shimura Curves","content":"(joint with M. Dettweiler) Division Towers for Triangle Shimura Curves.. Division Towers for Triangle Shimura Curves Gebhard BÃ¶ckle, M. Dettweiler Published (joint with M. Dettweiler) Division Towers for Triangle Shimura Curves In Preparation 2024 2024-joint-with-m-dettweiler-division-towers-for-triang .md","url":"/publications/?pub=joint-with-m-dettweiler-division-towers-for-triangle-shimura-curves-2024","category":"publication","description":"(joint with M. Dettweiler) Division Towers for Triangle Shimura Curves.. Division Towers for Triangle Shimura Curves","tags":"","authors":"Gebhard BÃ¶ckle, M. Dettweiler","year":"2024","journal":"","type":"In Preparation","status":"Published"},{"id":"publication-lifts-of-mod-p-galois-representations-with-local-supercuspidal-types-2024","title":"Lifts of mod p Galois representations with local supercuspidal types","content":"Lifts of mod p Galois representations with local supercuspidal types. Gebhard BÃ¶ckle Published Lifts of mod p Galois representations with local supercuspidal types In Preparation 2024 2024-lifts-of-mod-p-galois-representations-with-local-s .md","url":"/publications/?pub=lifts-of-mod-p-galois-representations-with-local-supercuspidal-types-2024","category":"publication","description":"Lifts of mod p Galois representations with local supercuspidal types.","tags":"","authors":"Gebhard BÃ¶ckle","year":"2024","journal":"","type":"In Preparation","status":"Published"},{"id":"publication-magma-package-qaquotgraphs-to-compute-the-action-by-unit-groups-of-maximal-orders-in-quaternion-algebras-over-mathbb-f-q-t-by-dr-ralf-butenuth-2024","title":"Magma package QaQuotGraphsÂ to compute the action by unit groups of maximal orders in quaternion algebras over $\\mathbb{F}_q(T)$ by Dr. Ralf Butenuth","content":"Research Group {\"label\"=>\"Magma package QaQuotGraphs\", \"url\"=>\"/ag-comp-arith-geom/members/ralf-butenuth/\"} Published Magma package QaQuotGraphsÂ to compute the action by unit groups of maximal orders in quaternion algebras over $\\mathbb{F}_q(T)$ by Dr. Ralf Butenuth Software 2024 2024-magma-package-qaquotgraphs-to-compute-the-action-b .md","url":"/publications/?pub=magma-package-qaquotgraphs-to-compute-the-action-by-unit-groups-of-maximal-orders-in-quaternion-algebras-over-mathbb-f-q-t-by-dr-ralf-butenuth-2024","category":"publication","description":"","tags":"","authors":"Research Group","year":"2024","journal":"","type":"Software","status":"Published"},{"id":"publication-magma-package-to-compute-hecke-eigensystems-for-harmonic-cocycles-on-the-bruhat-tits-tree-for-mathrm-gl-2-mathbb-f-q-t-by-master-s-student-burak-cakir-thesis-available-here-2024","title":"Magma package to compute Hecke eigensystems for harmonic cocycles on the Bruhat-Tits tree for $\\mathrm{GL}_2(\\mathbb{F}_q(T))$ by Master's student Burak Cakir, thesis available here","content":"Research Group {\"label\"=>\"Magma package\", \"url\"=>\"https://github.com/b-cakir/hecke-operator\"} {\"label\"=>\"Thesis PDF\", \"url\"=>\"/ag-comp-arith-geom/assets/uploads/Thesis_Cakir.pdf\"} Published Magma package to compute Hecke eigensystems for harmonic cocycles on the Bruhat-Tits tree for $\\mathrm{GL}_2(\\mathbb{F}_q(T))$ by Master's student Burak Cakir, thesis available here Software 2024 2024-magma-package-to-compute-hecke-eigensystems-for-ha .md","url":"/publications/?pub=magma-package-to-compute-hecke-eigensystems-for-harmonic-cocycles-on-the-bruhat-tits-tree-for-mathrm-gl-2-mathbb-f-q-t-by-master-s-student-burak-cakir-thesis-available-here-2024","category":"publication","description":"","tags":"","authors":"Research Group","year":"2024","journal":"","type":"Software","status":"Published"},{"id":"publication-magma-package-to-compute-quotients-of-bruhat-tits-buildings-over-function-fields-modulo-congruence-subgroups-and-the-action-of-hecke-operators-on-harmonic-cocycles-with-coefficients-in-char-0-by-former-master-s-student-lutz-hofmann-2024","title":"Magma package to compute quotients of Bruhat-Tits buildings over function fields modulo congruence subgroups and the action of Hecke operators on harmonic cocycles with coefficients in char. 0 by former Master's student Lutz Hofmann","content":"Research Group {\"label\"=>\"Magma package\", \"url\"=>\"https://github.com/lhofmann/buildings\"} Published Magma package to compute quotients of Bruhat-Tits buildings over function fields modulo congruence subgroups and the action of Hecke operators on harmonic cocycles with coefficients in char. 0 by former Master's student Lutz Hofmann Software 2024 2024-magma-package-to-compute-quotients-of-bruhat-tits- .md","url":"/publications/?pub=magma-package-to-compute-quotients-of-bruhat-tits-buildings-over-function-fields-modulo-congruence-subgroups-and-the-action-of-hecke-operators-on-harmonic-cocycles-with-coefficients-in-char-0-by-former-master-s-student-lutz-hofmann-2024","category":"publication","description":"","tags":"","authors":"Research Group","year":"2024","journal":"","type":"Software","status":"Published"}]